Workbook

Sheet PQRs
A1: CASO | B1: TRAMITE | C1: TIMESTAP | D1: CONTACTO | E1: ESTADO | F1: PRIORIDAD | G1: ASESOR ASIGNADO | H1: FECHA DE ASIGNACION | I1: Column 9 | J1: Column 10 | K1: Column 11 | L1: Column 12
A2: 1 | B2: QUEJA | C2: 2026-02-17T10:08:27.4016176 | D2: {"solicitante":{"nombreCompleto":"María González López","tipoDocumento":"CE","numeroDocumento":"9876543210","email":"maria.gonzalez@example.com","telefono":"3109876543"},"tramite":{"tipoSolicitud":"QUEJA","productoRelacionado":"ATENCION_CLIENTE","asunto":"Recibí mala atención en la oficina principal el día de ayer","descripcionDetallada":"Recibí mala atención en la oficina principal el día de ayer","fechaCreacion":"2026-02-17T10:08:27.4016176"}} | E2: Pendiente | F2: Baja | G2: yo@proyectiva.com | H2: 46064 | I2: 46064 | J2: [{"fecha":"2026-02-19T23:28:10.058Z","usuario":"cristian.mosquera@segurosbolivar.com","accion":"esto es un ejemplo","estadoAnterior":"Pendiente","estadoNuevo":"Pendiente"}]
A3: PQR-20260220-0013 | B3: PETICION | C3: 2026-02-20T08:25:46.503748318 | D3: {"solicitante":{"nombreCompleto":"Nicolas 2","tipoDocumento":"CC","numeroDocumento":"1000969735","email":"nicolas.cano@serviciosbolivar.com","telefono":"3193403518"},"tramite":{"tipoSolicitud":"PETICION","productoRelacionado":"SALUD","asunto":"prueba asunto","descripcionDetallada":"pruebaaaaaaaaaaaaaaaaaaaaaaaaaaaaaaaaaaaaaa","fechaCreacion":"2026-02-20T08:25:46.503748318"}} | E3: En Proceso | F3: Media | G3: maria.gaitan@proyectivaseguros.com | H3: 2026-02-24T14:31:55.370Z | J3: [{"fecha":"2026-02-24T14:31:55.330Z","usuario":"cristian.mosquera@segurosbolivar.com","accion":"PQR asignada a maria.gaitan@proyectivaseguros.com desde panel administrativo.","estadoAnterior":"Pendiente","estadoNuevo":"En Proceso"}]
A4: PQR-20260220-0011 | B4: QUEJA | C4: 2026-02-20T07:16:17.372854713 | D4: {"solicitante":{"nombreCompleto":"María González López","tipoDocumento":"CE","numeroDocumento":"98765432210","email":"maria.gonzalez@example.com","telefono":"3109876543"},"tramite":{"tipoSolicitud":"QUEJA","productoRelacionado":"SALUD","asunto":"test asunto","descripcionDetallada":"Recibí mala atención en la oficina principal el día de ayer","fechaCreacion":"2026-02-20T07:16:17.372854713"}} | E4: En Proceso | F4: Media | G4: maria.gaitan@proyectivaseguros.com | H4: 2026-02-24T14:31:55.328Z | J4: [{"fecha":"2026-02-24T14:31:55.295Z","usuario":"cristian.mosquera@segurosbolivar.com","accion":"PQR asignada a maria.gaitan@proyectivaseguros.com desde panel administrativo.","estadoAnterior":"Pendiente","estadoNuevo":"En Proceso"}]
A5: PQR-20260220-0012 | B5: FELICITACIONES | C5: 2026-02-20T08:14:54.700900395 | D5: {"solicitante":{"nombreCompleto":"Julio Alfredo Roncallo Polo","tipoDocumento":"CC","numeroDocumento":"1082962828","email":"julio.roncallo@segurosbolivar.com","telefono":"3229720435"},"tramite":{"tipoSolicitud":"FELICITACIONES","productoRelacionado":"OTRO","asunto":"Felicitaciones","descripcionDetallada":"Equipo de desarrollo proyectiva, felicitaciones por este arduo trabajo en equipo, se entrelazan desde el amor y el codigo el equipo del back con el front","fechaCreacion":"2026-02-20T08:14:54.700900395"}}
A6: PQR-20260220-0014 | B6: PETICION | C6: 2026-02-20T15:43:47.023715303 | D6: {"solicitante":{"nombreCompleto":"Nicolas Cano","tipoDocumento":"CC","numeroDocumento":"1000969735","email":"nicolas.cano@serviciosbolivar.com","telefono":"3193403518"},"tramite":{"tipoSolicitud":"PETICION","productoRelacionado":"OTRO","asunto":"prueba asunto","descripcionDetallada":"pruebaaaaaaaaaaaaaaaaaaaa","fechaCreacion":"2026-02-20T15:43:47.023715303"}}
A7: PQR-20260220-0015 | B7: PETICION | C7: 2026-02-20T15:51:52.725596096 | D7: {"solicitante":{"nombreCompleto":"Rodrigo Suarez","tipoDocumento":"NIT","numeroDocumento":"1192765243","email":"rodrigo@gmail.com","telefono":"3216363324"},"tramite":{"tipoSolicitud":"PETICION","productoRelacionado":"OTRO","asunto":"No me sirve la página","descripcionDetallada":"Quién hizo estpoooo ","fechaCreacion":"2026-02-20T15:51:52.725596096"}}
A8: PQR-20260220-0016 | B8: SUGERENCIA | C8: 2026-02-20T15:54:28.232192577 | D8: {"solicitante":{"nombreCompleto":"Nicolas Cano 5","tipoDocumento":"CC","numeroDocumento":"1000969735","email":"nicolas.cano@serviciosbolivar.com","telefono":"3193403518"},"tramite":{"tipoSolicitud":"SUGERENCIA","productoRelacionado":"OTRO","asunto":"prueba asunto","descripcionDetallada":"prueba 2222222222222222222222","fechaCreacion":"2026-02-20T15:54:28.232192577"}} | E8: Pendiente | F8: Media | G8: cristian.mosquera@segurosbolivar.com | H8: 2026-02-24T21:25:49.806Z | J8: [{"fecha":"2026-02-24T21:25:49.778Z","usuario":"cristian.mosquera@segurosbolivar.com","accion":"Asignación desde panel admin","estadoAnterior":"Pendiente","estadoNuevo":"Pendiente"}]
A9: PQR-20260223-0017 | B9: PETICION | C9: 46076.343 | D9: {"solicitante":{"nombreCompleto":"María Fernanda López Martínez","tipoDocumento":"CC","numeroDocumento":"5298765432","email":"maria.lopez@example.com","telefono":"3109876543"},"tramite":{"tipoSolicitud":"PETICION","productoRelacionado":"SALUD","asunto":"Consulta sobre cobertura de robo","descripcionDetallada":"Deseo conocer los detalles de la cobertura de robo incluida en mi póliza de hogar.","fechaCreacion":"2026-02-23 8:13:15"}} | E9: Pendiente | F9: Media | G9: desarrollocrmlibertador@ellibertador.co | H9: 2026-02-24T21:25:32.919Z | J9: [{"fecha":"2026-02-24T21:25:32.719Z","usuario":"cristian.mosquera@segurosbolivar.com","accion":"Asignación desde panel admin","estadoAnterior":"Pendiente","estadoNuevo":"Pendiente"}]
A10: PQR-20260224-0001 | B10: QUEJA | C10: 46077.715 | D10: {"solicitante":{"nombreCompleto":"María González López Diaz","tipoDocumento":"CE","numeroDocumento":"1192722255","email":"maria.gonzalez@example.com","telefono":"3109876543"},"tramite":{"tipoSolicitud":"QUEJA","productoRelacionado":"SALUD","asunto":"test asunto","descripcionDetallada":"Recibí mala atención en la oficina principal el día de ayer","fechaCreacion":"2026-02-24 17:09:45"}}
A11: PQR-20260224-0002 | B11: FELICITACIONES | C11: 46077.716 | D11: {"solicitante":{"nombreCompleto":"María González López Diaz","tipoDocumento":"CE","numeroDocumento":"1192722255","email":"maria.gonzalez@example.com","telefono":"3109876543"},"tramite":{"tipoSolicitud":"FELICITACIONES","productoRelacionado":"SALUD","asunto":"test asunto","descripcionDetallada":"Recibí mala atención en la oficina principal el día de ayer","fechaCreacion":"2026-02-24 17:11:23"}}
A12: PQR-20260225-0018 | B12: FELICITACIONES | C12: 46078.347 | D12: {"solicitante":{"nombreCompleto":"Julio Alfredo Roncallo Polo","tipoDocumento":"CC","numeroDocumento":"1082962828","email":"julio.roncallo@segurosbolivar.com","telefono":"3229720435"},"tramite":{"tipoSolicitud":"FELICITACIONES","productoRelacionado":"OTRO","asunto":"Felicitaciones","descripcionDetallada":"este es un mensaje de prueba","fechaCreacion":"2026-02-25 8:20:22"}}
A13: PQR-20260225-0019 | B13: PETICION | C13: 46078.406 | D13: {"solicitante":{"nombreCompleto":"Nicolas Cano pqrsf","tipoDocumento":"CC","numeroDocumento":"1000969735","email":"nicolas.cano@serviciosbolivar.com","telefono":"3193403518"},"tramite":{"tipoSolicitud":"PETICION","productoRelacionado":"OTRO","asunto":"prueba asunto","descripcionDetallada":"pruebaaaaaaaaaaaaaaaaaaa","fechaCreacion":"2026-02-25 9:45:01"}}
A14: PQR-20260225-0020 | B14: PETICION | C14: 46078.607 | D14: {"solicitante":{"nombreCompleto":"Nicolas Cano","tipoDocumento":"CC","numeroDocumento":"1000969735","email":"nicolas.cano@segurosbolivar.com","telefono":"3193403518"},"tramite":{"tipoSolicitud":"PETICION","productoRelacionado":"EMPRESA","asunto":"prueba asunto","descripcionDetallada":"pruebaaaaaaaaaaaaaaaaaaaaaa","fechaCreacion":"2026-02-25 14:34:27"}}

Sheet Leads
A1: Fecha ingreso | B1: Numero Solicitud | C1: Datos del lead | D1: Nombre agente | E1: Etapa Funel | F1: Estado Gestion | G1: Producto | H1: Observaciones | I1: fecha ultima gestion | J1: datos vida | K1: datos desempleo
A2: 45881.375 | B2: 7847382 | C2: {"poliza":"2252","nombre":"FABIAN ANDRES PERILLA MANJARES","id":"1019098199","telefono":"","correo":"","ciudad":"BOGOTA, D.C.","direccion":"CR 57 128B BIS 06","tipoInmueble":"Vivienda","canon":"1300000","fechaRadicacion":"11/08/2025 3:08:43","fechaAprobacion":"11/08/2025 4:08:58","estado":"APROBADA"} | D2: Anyuley.daza@aselibertador.com | E2: Contacto Inicial y Datos | F2: DESISTIDO | G2: Seguro de Vida | H2: [{"fecha":"2025-08-12 09:21:32","usuario":"anyuley.daza@aselibertador.com","accionRealizada":"DESISTIDO","leadEtapaActual":"Contacto Inicial y Datos","productosGestion":"Seguro de Vida","observaciones":"No Contesta"}] | I2: 45881.39 | J2: {"Contacto Inicial y Datos":{"nomAgt":"","emailCte":"","autorizaDatosPersonales":false,"fechaNacimiento":"","tipoDocumento":"","observacionesPresentacion":"No hay número de contacto se valida sai y tampoco hay registro","genero":"","resultadoGestion":"Cliente ilocalizable","accion":"Cliente ilocalizable","usuario":"anyuley.daza@aselibertador.com"},"Cotización y Pre-Asegurabilidad":{"periosidad":"","nPagosMensuales":"","admin":"","observacionesCotizacion":"","valorAseguradoVida":0,"primaVidaITP":0,"fechaCotizacionVida":""},"Declaración de Asegurabilidad":{"actividadesLicita":false,"procesoPenal":false,"frecuenciaDeportesAltoRiesgo":"","peso":"","estatura":"","imcCalculado":"","observacionImc":"","estadoAsegurabilidad":"","hipertensionArterial":false,"colesterolTrigliceridosElevados":false,"diabetes":false,"enfermedadCoronariaInfarto":false,"insuficienciaRenal":false,"cancerTumores":false,"derrameTrombosisCerebral":false,"enfermedadesPsicologicasPsiquiatricas":false,"sidaVih":false,"pruebaVihPositiva":false,"secuelasEnfermedadAccidente":"","diagnosticoEnfermedadFracturas":"","tratamientoAlcoholAlucinogenos":false,"cirugiaProgramada":false,"autorizacionInformacionMedica":false,"fechaAsegurabilidad":""},"Autorización de Descuento Débito":{"canalDescuento":"","tipoDeCuenta":"","entidadBancaria":"","numeroCuentaDebito":"","fechaVencimientoTC":"","numeroCuotasTC":"","autorizaDescuentoAutomatico":false,"entiendeMoraPrima":false,"valorPrima":0,"fechaAutorizacionDebito":"","observacionesCierre":""},"Beneficiarios y Autorizaciones":{"nombreBeneficiario1":"","apellidoBeneficiario1":"","parentescoBeneficiario1":"","designacionBeneficiario1":0,"nombreBeneficiario2":"","apellidoBeneficiario2":"","parentescoBeneficiario2":"","designacionBeneficiario2":0,"nombreBeneficiario3":"","apellidoBeneficiario3":"","parentescoBeneficiario3":"","designacionBeneficiario3":0,"beneficiariosRegistrados":false,"fechaRegistroBeneficiarios":""},"Emisión de Póliza":{"numeroCertificadoFinal":"","resultadoEmision":"","fechaVigenciaPoliza":"","polizaPrincipal":"","periodicidadPagoPoliza":"MENSUAL","confirmacionVentaSegurosBolivar":false,"liderClavo":"","certificado":"75272","observacionesEmision":"","fechaEmisionPoliza":"","estadoPoliza":"","numeroContrato":""}}
A3: 45881.375 | B3: 7847475 | C3: {"poliza":"1136","nombre":"GROUP SAS MARQUESA GROUP","id":"901769660","telefono":"3123027512","correo":"gerencia@marquesagroup.co","ciudad":"BOGOTA, D.C.","direccion":"CL 56 4 A 11","tipoInmueble":"Comercial","canon":"13090000","fechaRadicacion":"11/08/2025 9:08:31","fechaAprobacion":"11/08/2025 1:08:58","estado":"APROBADA"} | D3: maria.gaitan@proyectivaseguros.com | E3: Contacto Inicial y Datos | F3: DESISTIDO | G3: Seguro de Vida | H3: [{"fecha":"2025-08-12 09:29:47","usuario":"maria.gaitan@segurosbolivar.com","accionRealizada":"DESISTIDO","leadEtapaActual":"Contacto Inicial y Datos","productosGestion":"Seguro de Vida","observaciones":"Preguntas Sarlaft cliente sin CC"}] | I3: 45881.396 | J3: {"Contacto Inicial y Datos":{"nomAgt":"","emailCte":"","autorizaDatosPersonales":false,"fechaNacimiento":"","tipoDocumento":"","observacionesPresentacion":"","genero":"","resultadoGestion":"","accion":"No Asegurable","usuario":"maria.gaitan@segurosbolivar.com"},"Cotización y Pre-Asegurabilidad":{"periosidad":"","nPagosMensuales":"","admin":"","observacionesCotizacion":"","valorAseguradoVida":0,"primaVidaITP":0,"fechaCotizacionVida":""},"Declaración de Asegurabilidad":{"actividadesLicita":false,"procesoPenal":false,"frecuenciaDeportesAltoRiesgo":"","peso":"","estatura":"","imcCalculado":"","observacionImc":"","estadoAsegurabilidad":"","hipertensionArterial":false,"colesterolTrigliceridosElevados":false,"diabetes":false,"enfermedadCoronariaInfarto":false,"insuficienciaRenal":false,"cancerTumores":false,"derrameTrombosisCerebral":false,"enfermedadesPsicologicasPsiquiatricas":false,"sidaVih":false,"pruebaVihPositiva":false,"secuelasEnfermedadAccidente":"","diagnosticoEnfermedadFracturas":"","tratamientoAlcoholAlucinogenos":false,"cirugiaProgramada":false,"autorizacionInformacionMedica":false,"fechaAsegurabilidad":""},"Autorización de Descuento Débito":{"canalDescuento":"","tipoDeCuenta":"","entidadBancaria":"","numeroCuentaDebito":"","fechaVencimientoTC":"","numeroCuotasTC":"","autorizaDescuentoAutomatico":false,"entiendeMoraPrima":false,"valorPrima":0,"fechaAutorizacionDebito":"","observacionesCierre":""},"Beneficiarios y Autorizaciones":{"nombreBeneficiario1":"","apellidoBeneficiario1":"","parentescoBeneficiario1":"","designacionBeneficiario1":0,"nombreBeneficiario2":"","apellidoBeneficiario2":"","parentescoBeneficiario2":"","designacionBeneficiario2":0,"nombreBeneficiario3":"","apellidoBeneficiario3":"","parentescoBeneficiario3":"","designacionBeneficiario3":0,"beneficiariosRegistrados":false,"fechaRegistroBeneficiarios":""},"Emisión de Póliza":{"numeroCertificadoFinal":"","resultadoEmision":"","fechaVigenciaPoliza":"","polizaPrincipal":"","periodicidadPagoPoliza":"MENSUAL","confirmacionVentaSegurosBolivar":false,"liderClavo":"","certificado":"75272","observacionesEmision":"","fechaEmisionPoliza":"","estadoPoliza":"","numeroContrato":""}}
A4: 45881.375 | B4: 11696200 | C4: {"poliza":"429","nombre":"BLANCA ALICIA OROZCO PATINO","id":"51559718","telefono":"3229442151","correo":"blancorozko@yahoo.es","ciudad":"BOGOTA, D.C.","direccion":"CL 60A SUR 73 40 TO 2 AP 308","tipoInmueble":"Vivienda","canon":"1100000","fechaRadicacion":"11/08/2025 2:08:07","fechaAprobacion":"11/08/2025 10:08:28","estado":"APROBADA"} | D4: angela.caipa@segurosbolivar.com | E4: Contacto Inicial y Datos | F4: DESISTIDO | G4: Seguro de Vida | H4: [{"fecha":"2025-08-12 09:29:17","usuario":"anyuley.daza@aselibertador.com","accionRealizada":"DESISTIDO","leadEtapaActual":"Contacto Inicial y Datos","productosGestion":"Seguro de Vida","observaciones":"No Contesta"}] | I4: 45881.395 | J4: {"Contacto Inicial y Datos":{"nomAgt":"","emailCte":"","autorizaDatosPersonales":false,"fechaNacimiento":"","tipoDocumento":"","observacionesPresentacion":"","genero":"","resultadoGestion":"Cliente ilocalizable","accion":"Cliente ilocalizable","usuario":"anyuley.daza@aselibertador.com"},"Cotización y Pre-Asegurabilidad":{"periosidad":"","nPagosMensuales":"","admin":"","observacionesCotizacion":"","valorAseguradoVida":0,"primaVidaITP":0,"fechaCotizacionVida":""},"Declaración de Asegurabilidad":{"actividadesLicita":false,"procesoPenal":false,"frecuenciaDeportesAltoRiesgo":"","peso":"","estatura":"","imcCalculado":"","observacionImc":"","estadoAsegurabilidad":"","hipertensionArterial":false,"colesterolTrigliceridosElevados":false,"diabetes":false,"enfermedadCoronariaInfarto":false,"insuficienciaRenal":false,"cancerTumores":false,"derrameTrombosisCerebral":false,"enfermedadesPsicologicasPsiquiatricas":false,"sidaVih":false,"pruebaVihPositiva":false,"secuelasEnfermedadAccidente":"","diagnosticoEnfermedadFracturas":"","tratamientoAlcoholAlucinogenos":false,"cirugiaProgramada":false,"autorizacionInformacionMedica":false,"fechaAsegurabilidad":""},"Autorización de Descuento Débito":{"canalDescuento":"","tipoDeCuenta":"","entidadBancaria":"","numeroCuentaDebito":"","fechaVencimientoTC":"","numeroCuotasTC":"","autorizaDescuentoAutomatico":false,"entiendeMoraPrima":false,"valorPrima":0,"fechaAutorizacionDebito":"","observacionesCierre":""},"Beneficiarios y Autorizaciones":{"nombreBeneficiario1":"","apellidoBeneficiario1":"","parentescoBeneficiario1":"","designacionBeneficiario1":0,"nombreBeneficiario2":"","apellidoBeneficiario2":"","parentescoBeneficiario2":"","designacionBeneficiario2":0,"nombreBeneficiario3":"","apellidoBeneficiario3":"","parentescoBeneficiario3":"","designacionBeneficiario3":0,"beneficiariosRegistrados":false,"fechaRegistroBeneficiarios":""},"Emisión de Póliza":{"numeroCertificadoFinal":"","resultadoEmision":"","fechaVigenciaPoliza":"","polizaPrincipal":"","periodicidadPagoPoliza":"MENSUAL","confirmacionVentaSegurosBolivar":false,"liderClavo":"","certificado":"75272","observacionesEmision":"","fechaEmisionPoliza":"","estadoPoliza":"","numeroContrato":""}}
A5: 45881.375 | B5: 11696324 | C5: {"poliza":"139","nombre":"DOLLY MARIA OROZCO GALLEGO","id":"51653652","telefono":"3163506755","correo":"dollymaorozco@gmail.com","ciudad":"BOGOTA, D.C.","direccion":"CL 163 B 50 64 IN 5 AP 21","tipoInmueble":"Vivienda","canon":"1800000","fechaRadicacion":"11/08/2025 9:08:58","fechaAprobacion":"11/08/2025 2:08:20","estado":"APROBADA"} | D5: maria.gaitan@proyectivaseguros.com | E5: Contacto Inicial y Datos | F5: DESISTIDO | G5: Seguro de Vida | H5: [{"fecha":"2025-08-12 09:31:36","usuario":"maria.gaitan@segurosbolivar.com","accionRealizada":"DESISTIDO","leadEtapaActual":"Contacto Inicial y Datos","productosGestion":"Seguro de Vida","observaciones":"Edad no asegurable"},{"fecha":"2025-08-15 11:59:54","usuario":"anyuley.daza@aselibertador.com","accionRealizada":"DESISTIDO","leadEtapaActual":"Contacto Inicial y Datos","productosGestion":"Seguro de Vida","observaciones":"No Contesta"},{"fecha":"2025-08-15 12:00:51","usuario":"anyuley.daza@aselibertador.com","accionRealizada":"DESISTIDO","leadEtapaActual":"Contacto Inicial y Datos","productosGestion":"Seguro de Vida","observaciones":"No Contesta"},{"fecha":"2025-08-15 12:03:50","usuario":"anyuley.daza@aselibertador.com","accionRealizada":"DESISTIDO","leadEtapaActual":"Contacto Inicial y Datos","productosGestion":"Seguro de Vida","observaciones":"No Contesta"},{"fecha":"2025-08-15 12:21:15","usuario":"anyuley.daza@aselibertador.com","accionRealizada":"DESISTIDO","leadEtapaActual":"Contacto Inicial y Datos","productosGestion":"Seguro de Vida","observaciones":"No Contesta"},{"fecha":"2025-08-15 12:49:14","usuario":"anyuley.daza@aselibertador.com","accionRealizada":"DESISTIDO","leadEtapaActual":"Contacto Inicial y Datos","productosGestion":"Seguro de Vida","observaciones":"No Contesta"},{"fecha":"2025-08-16 10:04:30","usuario":"anyuley.daza@aselibertador.com","accionRealizada":"DESISTIDO","leadEtapaActual":"Contacto Inicial y Datos","productosGestion":"Seguro de Vida","observaciones":"No Contesta"},{"fecha":"2025-08-19 12:36:15","usuario":"anyuley.daza@aselibertador.com","accionRealizada":"DESISTIDO","leadEtapaActual":"Contacto Inicial y Datos","productosGestion":"Seguro de Vida","observaciones":"No Contesta"},{"fecha":"2025-08-19 12:37:17","usuario":"anyuley.daza@aselibertador.com","accionRealizada":"DESISTIDO","leadEtapaActual":"Contacto Inicial y Datos","productosGestion":"Seguro de Vida","observaciones":"No Contesta"}] | I5: 45888.526 | J5: {"Contacto Inicial y Datos":{"nomAgt":"","emailCte":"","autorizaDatosPersonales":false,"fechaNacimiento":"","tipoDocumento":"","observacionesPresentacion":"Se marca tres vces,No contesta","genero":"","resultadoGestion":"Cliente ilocalizable","accion":"Cliente ilocalizable","usuario":"anyuley.daza@aselibertador.com"},"Cotización y Pre-Asegurabilidad":{"periosidad":"","nPagosMensuales":"","admin":"","observacionesCotizacion":"","valorAseguradoVida":0,"primaVidaITP":0,"fechaCotizacionVida":""},"Declaración de Asegurabilidad":{"actividadesLicita":false,"procesoPenal":false,"frecuenciaDeportesAltoRiesgo":"","peso":"","estatura":"","imcCalculado":"","observacionImc":"","estadoAsegurabilidad":"","hipertensionArterial":false,"colesterolTrigliceridosElevados":false,"diabetes":false,"enfermedadCoronariaInfarto":false,"insuficienciaRenal":false,"cancerTumores":false,"derrameTrombosisCerebral":false,"enfermedadesPsicologicasPsiquiatricas":false,"sidaVih":false,"pruebaVihPositiva":false,"secuelasEnfermedadAccidente":"","diagnosticoEnfermedadFracturas":"","tratamientoAlcoholAlucinogenos":false,"cirugiaProgramada":false,"autorizacionInformacionMedica":false,"fechaAsegurabilidad":""},"Autorización de Descuento Débito":{"canalDescuento":"","tipoDeCuenta":"","entidadBancaria":"","numeroCuentaDebito":"","fechaVencimientoTC":"","numeroCuotasTC":"","autorizaDescuentoAutomatico":false,"entiendeMoraPrima":false,"valorPrima":0,"fechaAutorizacionDebito":"","observacionesCierre":""},"Beneficiarios y Autorizaciones":{"nombreBeneficiario1":"","apellidoBeneficiario1":"","parentescoBeneficiario1":"","designacionBeneficiario1":0,"nombreBeneficiario2":"","apellidoBeneficiario2":"","parentescoBeneficiario2":"","designacionBeneficiario2":0,"nombreBeneficiario3":"","apellidoBeneficiario3":"","parentescoBeneficiario3":"","designacionBeneficiario3":0,"beneficiariosRegistrados":false,"fechaRegistroBeneficiarios":""},"Emisión de Póliza":{"numeroCertificadoFinal":"","resultadoEmision":"","fechaVigenciaPoliza":"","polizaPrincipal":"","periodicidadPagoPoliza":"MENSUAL","confirmacionVentaSegurosBolivar":false,"liderClavo":"","certificado":"75272","observacionesEmision":"","fechaEmisionPoliza":"","estadoPoliza":"","numeroContrato":""}}
A6: 45881.787 | B6: 7847403 | C6: {"poliza":"11474","nombre":"YEIFIN ANDRES BAYONA GUERREO","id":"1193131955","telefono":"3228601520","correo":"YELFINBAYONA@ICLOUD.COM","ciudad":"BUCARAMANGA","direccion":"DG 9 7B 93","tipoInmueble":"Vivienda","canon":"900000","fechaRadicacion":"12/8/2025","fechaAprobacion":"12/8/2025","estado":"APROBADA"} | D6: ana.prieto@aselibertador.com | E6: Contacto Inicial y Datos | F6: DESISTIDO | G6: Seguro de Vida | H6: [{"fecha":"2025-08-13 09:14:17","usuario":"ana.prieto@aselibertador.com","accionRealizada":"DESISTIDO","leadEtapaActual":"Contacto Inicial y Datos","productosGestion":"Seguro de Vida","observaciones":"No Contesta"}] | I6: 45882.385 | J6: {"Contacto Inicial y Datos":{"nomAgt":"","emailCte":"","autorizaDatosPersonales":false,"fechaNacimiento":"","tipoDocumento":"CC","observacionesPresentacion":"","genero":"Masculino","resultadoGestion":"Cliente ilocalizable","accion":"Cliente ilocalizable","usuario":"ana.prieto@aselibertador.com"},"Cotización y Pre-Asegurabilidad":{"periosidad":"","nPagosMensuales":"","admin":"","observacionesCotizacion":"","valorAseguradoVida":0,"primaVidaITP":0,"fechaCotizacionVida":""},"Declaración de Asegurabilidad":{"actividadesLicita":false,"procesoPenal":false,"frecuenciaDeportesAltoRiesgo":"","peso":"","estatura":"","imcCalculado":"","observacionImc":"","estadoAsegurabilidad":"","hipertensionArterial":false,"colesterolTrigliceridosElevados":false,"diabetes":false,"enfermedadCoronariaInfarto":false,"insuficienciaRenal":false,"cancerTumores":false,"derrameTrombosisCerebral":false,"enfermedadesPsicologicasPsiquiatricas":false,"sidaVih":false,"pruebaVihPositiva":false,"secuelasEnfermedadAccidente":"","diagnosticoEnfermedadFracturas":"","tratamientoAlcoholAlucinogenos":false,"cirugiaProgramada":false,"autorizacionInformacionMedica":false,"fechaAsegurabilidad":""},"Autorización de Descuento Débito":{"canalDescuento":"","tipoDeCuenta":"","entidadBancaria":"","numeroCuentaDebito":"","fechaVencimientoTC":"","numeroCuotasTC":"","autorizaDescuentoAutomatico":false,"entiendeMoraPrima":false,"valorPrima":0,"fechaAutorizacionDebito":"","observacionesCierre":""},"Beneficiarios y Autorizaciones":{"nombreBeneficiario1":"","apellidoBeneficiario1":"","parentescoBeneficiario1":"","designacionBeneficiario1":0,"nombreBeneficiario2":"","apellidoBeneficiario2":"","parentescoBeneficiario2":"","designacionBeneficiario2":0,"nombreBeneficiario3":"","apellidoBeneficiario3":"","parentescoBeneficiario3":"","designacionBeneficiario3":0,"beneficiariosRegistrados":false,"fechaRegistroBeneficiarios":""},"Emisión de Póliza":{"numeroCertificadoFinal":"","resultadoEmision":"","fechaVigenciaPoliza":"","polizaPrincipal":"","periodicidadPagoPoliza":"MENSUAL","confirmacionVentaSegurosBolivar":false,"liderClavo":"","certificado":"75272","observacionesEmision":"","fechaEmisionPoliza":"","estadoPoliza":"","numeroContrato":""}}
A7: 45881.787 | B7: 7847488 | C7: {"poliza":"11196","nombre":"MIGUEL ANTONIO JAIMES FLOREZ","id":"13249605","telefono":"3203459151","correo":"MAJAFLO@HOTMAIL.COM","ciudad":"BUCARAMANGA","direccion":"ALTOS DE LA CANAVERA TERCERA T 5 AP 403","tipoInmueble":"Vivienda","canon":"850000","fechaRadicacion":"11/8/2025","fechaAprobacion":"12/8/2025","estado":"APROBADA"} | D7: cristian.mosquera@segurosbolivar.com | E7: Contacto Inicial y Datos | G7: Seguro de Vida | H7: [{"fecha":"2025-08-14 16:17:35","usuario":"diana.salas@segurosbolivar.com","accionRealizada":"DESISTIDO","leadEtapaActual":"Contacto Inicial y Datos","productosGestion":"Seguro de Vida","observaciones":"Edad no asegurable"}] | I7: 45883.679 | J7: {"Contacto Inicial y Datos":{"nomAgt":"","emailCte":"","autorizaDatosPersonales":false,"fechaNacimiento":"","tipoDocumento":"","observacionesPresentacion":"","genero":"","resultadoGestion":"","accion":"No Asegurable","usuario":"diana.salas@segurosbolivar.com"},"Cotización y Pre-Asegurabilidad":{"periosidad":"","nPagosMensuales":"","admin":"","observacionesCotizacion":"","valorAseguradoVida":0,"primaVidaITP":0,"fechaCotizacionVida":""},"Declaración de Asegurabilidad":{"actividadesLicita":false,"procesoPenal":false,"frecuenciaDeportesAltoRiesgo":"","peso":"","estatura":"","imcCalculado":"","observacionImc":"","estadoAsegurabilidad":"","hipertensionArterial":false,"colesterolTrigliceridosElevados":false,"diabetes":false,"enfermedadCoronariaInfarto":false,"insuficienciaRenal":false,"cancerTumores":false,"derrameTrombosisCerebral":false,"enfermedadesPsicologicasPsiquiatricas":false,"sidaVih":false,"pruebaVihPositiva":false,"secuelasEnfermedadAccidente":"","diagnosticoEnfermedadFracturas":"","tratamientoAlcoholAlucinogenos":false,"cirugiaProgramada":false,"autorizacionInformacionMedica":false,"fechaAsegurabilidad":""},"Autorización de Descuento Débito":{"canalDescuento":"","tipoDeCuenta":"","entidadBancaria":"","numeroCuentaDebito":"","fechaVencimientoTC":"","numeroCuotasTC":"","autorizaDescuentoAutomatico":false,"entiendeMoraPrima":false,"valorPrima":0,"fechaAutorizacionDebito":"","observacionesCierre":""},"Beneficiarios y Autorizaciones":{"nombreBeneficiario1":"","apellidoBeneficiario1":"","parentescoBeneficiario1":"","designacionBeneficiario1":0,"nombreBeneficiario2":"","apellidoBeneficiario2":"","parentescoBeneficiario2":"","designacionBeneficiario2":0,"nombreBeneficiario3":"","apellidoBeneficiario3":"","parentescoBeneficiario3":"","designacionBeneficiario3":0,"beneficiariosRegistrados":false,"fechaRegistroBeneficiarios":""},"Emisión de Póliza":{"numeroCertificadoFinal":"","resultadoEmision":"","fechaVigenciaPoliza":"","polizaPrincipal":"","periodicidadPagoPoliza":"MENSUAL","confirmacionVentaSegurosBolivar":false,"liderClavo":"","certificado":"75272","observacionesEmision":"","fechaEmisionPoliza":"","estadoPoliza":"","numeroContrato":""}}
A8: 45881.787 | B8: 7847493 | C8: {"poliza":"10670","nombre":"LUZ MERY HOYA CUESTA","id":"47441183","telefono":"3102824190","correo":"merynmoon7521@gmail.com","ciudad":"PALMIRA","direccion":"CR 44 3 26 80 AP 301B CLUB RESIDENCIAL OTOBO","tipoInmueble":"Vivienda","canon":"1800000","fechaRadicacion":"12/8/2025","fechaAprobacion":"12/8/2025","estado":"APROBADA"} | D8: maria.gaitan@proyectivaseguros.com | E8: Contacto Inicial y Datos | F8: DESISTIDO | G8: Seguro de Vida | H8: [{"fecha":"2025-08-13 08:13:45","usuario":"maria.gaitan@segurosbolivar.com","accionRealizada":"DESISTIDO","leadEtapaActual":"Contacto Inicial y Datos","productosGestion":"Seguro de Vida","observaciones":"No Contesta"}] | I8: 45882.343 | J8: {"Contacto Inicial y Datos":{"nomAgt":"","emailCte":"","autorizaDatosPersonales":false,"fechaNacimiento":"","tipoDocumento":"","observacionesPresentacion":"","genero":"","resultadoGestion":"Cliente ilocalizable","accion":"Cliente ilocalizable","usuario":"maria.gaitan@segurosbolivar.com"},"Cotización y Pre-Asegurabilidad":{"periosidad":"Mensual","nPagosMensuales":"12","admin":"","observacionesCotizacion":"","valorAseguradoVida":0,"primaVidaITP":0,"fechaCotizacionVida":"","resultadoGestion":""},"Declaración de Asegurabilidad":{"actividadesLicita":false,"procesoPenal":false,"frecuenciaDeportesAltoRiesgo":"","peso":"","estatura":"","imcCalculado":"","observacionImc":"","estadoAsegurabilidad":"","hipertensionArterial":false,"colesterolTrigliceridosElevados":false,"diabetes":false,"enfermedadCoronariaInfarto":false,"insuficienciaRenal":false,"cancerTumores":false,"derrameTrombosisCerebral":false,"enfermedadesPsicologicasPsiquiatricas":false,"sidaVih":false,"pruebaVihPositiva":false,"secuelasEnfermedadAccidente":"","diagnosticoEnfermedadFracturas":"","tratamientoAlcoholAlucinogenos":false,"cirugiaProgramada":false,"autorizacionInformacionMedica":false,"fechaAsegurabilidad":""},"Autorización de Descuento Débito":{"canalDescuento":"","tipoDeCuenta":"","entidadBancaria":"","numeroCuentaDebito":"","fechaVencimientoTC":"","numeroCuotasTC":"","autorizaDescuentoAutomatico":false,"entiendeMoraPrima":false,"valorPrima":0,"fechaAutorizacionDebito":"","observacionesCierre":""},"Beneficiarios y Autorizaciones":{"nombreBeneficiario1":"","apellidoBeneficiario1":"","parentescoBeneficiario1":"","designacionBeneficiario1":0,"nombreBeneficiario2":"","apellidoBeneficiario2":"","parentescoBeneficiario2":"","designacionBeneficiario2":0,"nombreBeneficiario3":"","apellidoBeneficiario3":"","parentescoBeneficiario3":"","designacionBeneficiario3":0,"beneficiariosRegistrados":false,"fechaRegistroBeneficiarios":""},"Emisión de Póliza":{"numeroCertificadoFinal":"","resultadoEmision":"","fechaVigenciaPoliza":"","polizaPrincipal":"","periodicidadPagoPoliza":"MENSUAL","confirmacionVentaSegurosBolivar":false,"liderClavo":"","certificado":"75272","observacionesEmision":"","fechaEmisionPoliza":"","estadoPoliza":"","numeroContrato":""}}
A9: 45881.787 | B9: 7847503 | C9: {"poliza":"11475","nombre":"DE JESUS FEREZ RAMIREZ","id":"18915352","telefono":"3165897782","correo":"wilsonferez@hotmail.com","ciudad":"FLORIDABLANCA","direccion":"CR 23 27 51","tipoInmueble":"Vivienda","canon":"1737000","fechaRadicacion":"12/8/2025","fechaAprobacion":"12/8/2025","estado":"APROBADA"} | D9: cristian.mosquera@segurosbolivar.com | E9: Contacto Inicial y Datos | F9: DESISTIDO | G9: Seguro de Vida | H9: [{"fecha":"2025-08-13 08:09:29","usuario":"olga.obando@segurosbolivar.com","accionRealizada":"Cliente no contesta","leadEtapaActual":"Contacto Inicial y Datos","productosGestion":"Seguro de Vida","observaciones":"2 INTENTOS SIN RESPUESTA"},{"fecha":"2025-08-13 09:42:46","usuario":"olga.obando@segurosbolivar.com","accionRealizada":"DESISTIDO","leadEtapaActual":"Contacto Inicial y Datos","productosGestion":"Seguro de Vida","observaciones":"No Contesta"}] | I9: 45882.405 | J9: {"Contacto Inicial y Datos":{"nomAgt":"","emailCte":"","autorizaDatosPersonales":false,"fechaNacimiento":"1999-01-01","tipoDocumento":"CC","observacionesPresentacion":"2 INTENTOS SIN RESPUESTA","genero":"Masculino","resultadoGestion":"Cliente ilocalizable","accion":"Cliente ilocalizable","usuario":"olga.obando@segurosbolivar.com"},"Cotización y Pre-Asegurabilidad":{"periosidad":"","nPagosMensuales":"","admin":"","observacionesCotizacion":"","valorAseguradoVida":0,"primaVidaITP":0,"fechaCotizacionVida":""},"Declaración de Asegurabilidad":{"actividadesLicita":false,"procesoPenal":false,"frecuenciaDeportesAltoRiesgo":"","peso":"","estatura":"","imcCalculado":"","observacionImc":"","estadoAsegurabilidad":"","hipertensionArterial":false,"colesterolTrigliceridosElevados":false,"diabetes":false,"enfermedadCoronariaInfarto":false,"insuficienciaRenal":false,"cancerTumores":false,"derrameTrombosisCerebral":false,"enfermedadesPsicologicasPsiquiatricas":false,"sidaVih":false,"pruebaVihPositiva":false,"secuelasEnfermedadAccidente":"","diagnosticoEnfermedadFracturas":"","tratamientoAlcoholAlucinogenos":false,"cirugiaProgramada":false,"autorizacionInformacionMedica":false,"fechaAsegurabilidad":""},"Autorización de Descuento Débito":{"canalDescuento":"","tipoDeCuenta":"","entidadBancaria":"","numeroCuentaDebito":"","fechaVencimientoTC":"","numeroCuotasTC":"","autorizaDescuentoAutomatico":false,"entiendeMoraPrima":false,"valorPrima":0,"fechaAutorizacionDebito":"","observacionesCierre":""},"Beneficiarios y Autorizaciones":{"nombreBeneficiario1":"","apellidoBeneficiario1":"","parentescoBeneficiario1":"","designacionBeneficiario1":0,"nombreBeneficiario2":"","apellidoBeneficiario2":"","parentescoBeneficiario2":"","designacionBeneficiario2":0,"nombreBeneficiario3":"","apellidoBeneficiario3":"","parentescoBeneficiario3":"","designacionBeneficiario3":0,"beneficiariosRegistrados":false,"fechaRegistroBeneficiarios":""},"Emisión de Póliza":{"numeroCertificadoFinal":"","resultadoEmision":"","fechaVigenciaPoliza":"","polizaPrincipal":"","periodicidadPagoPoliza":"MENSUAL","confirmacionVentaSegurosBolivar":false,"liderClavo":"","certificado":"75272","observacionesEmision":"","fechaEmisionPoliza":"","estadoPoliza":"","numeroContrato":""}}
A10: 45881.787 | B10: 7847796 | C10: {"poliza":"13187","nombre":"MARIA NATACHA AGUDELO BERMUDEZ","id":"1036607917","telefono":"3003630656","correo":"NATA1310@HOTMAIL.ES","ciudad":"ITAGUI","direccion":"CL 81A 52A 57 OF 201","tipoInmueble":"Comercial","canon":"2700000","fechaRadicacion":"11/8/2025","fechaAprobacion":"12/8/2025","estado":"APROBADA"} | D10: angela.caipa@segurosbolivar.com | E10: Contacto Inicial y Datos | F10: DESISTIDO | G10: Seguro de Vida | H10: [{"fecha":"2025-08-13 08:22:58","usuario":"angela.caipa@segurosbolivar.com","accionRealizada":"DESISTIDO","leadEtapaActual":"Contacto Inicial y Datos","productosGestion":"Seguro de Vida","observaciones":"Contesta y Cuelga Inmediatamente"}] | I10: 45882.349 | J10: {"Contacto Inicial y Datos":{"nomAgt":"","emailCte":"","autorizaDatosPersonales":false,"fechaNacimiento":"","tipoDocumento":"CC","observacionesPresentacion":"cuelga al preguntar por ella","genero":"Femenino","resultadoGestion":"Cliente ilocalizable","accion":"Cliente ilocalizable","usuario":"angela.caipa@segurosbolivar.com"},"Cotización y Pre-Asegurabilidad":{"periosidad":"","nPagosMensuales":"","admin":"","observacionesCotizacion":"","valorAseguradoVida":0,"primaVidaITP":0,"fechaCotizacionVida":""},"Declaración de Asegurabilidad":{"actividadesLicita":false,"procesoPenal":false,"frecuenciaDeportesAltoRiesgo":"","peso":"","estatura":"","imcCalculado":"","observacionImc":"","estadoAsegurabilidad":"","hipertensionArterial":false,"colesterolTrigliceridosElevados":false,"diabetes":false,"enfermedadCoronariaInfarto":false,"insuficienciaRenal":false,"cancerTumores":false,"derrameTrombosisCerebral":false,"enfermedadesPsicologicasPsiquiatricas":false,"sidaVih":false,"pruebaVihPositiva":false,"secuelasEnfermedadAccidente":"","diagnosticoEnfermedadFracturas":"","tratamientoAlcoholAlucinogenos":false,"cirugiaProgramada":false,"autorizacionInformacionMedica":false,"fechaAsegurabilidad":""},"Autorización de Descuento Débito":{"canalDescuento":"","tipoDeCuenta":"","entidadBancaria":"","numeroCuentaDebito":"","fechaVencimientoTC":"","numeroCuotasTC":"","autorizaDescuentoAutomatico":false,"entiendeMoraPrima":false,"valorPrima":0,"fechaAutorizacionDebito":"","observacionesCierre":""},"Beneficiarios y Autorizaciones":{"nombreBeneficiario1":"","apellidoBeneficiario1":"","parentescoBeneficiario1":"","designacionBeneficiario1":0,"nombreBeneficiario2":"","apellidoBeneficiario2":"","parentescoBeneficiario2":"","designacionBeneficiario2":0,"nombreBeneficiario3":"","apellidoBeneficiario3":"","parentescoBeneficiario3":"","designacionBeneficiario3":0,"beneficiariosRegistrados":false,"fechaRegistroBeneficiarios":""},"Emisión de Póliza":{"numeroCertificadoFinal":"","resultadoEmision":"","fechaVigenciaPoliza":"","polizaPrincipal":"","periodicidadPagoPoliza":"MENSUAL","confirmacionVentaSegurosBolivar":false,"liderClavo":"","certificado":"75272","observacionesEmision":"","fechaEmisionPoliza":"","estadoPoliza":"","numeroContrato":""}}
A11: 45881.787 | B11: 7847839 | C11: {"poliza":"10913","nombre":"ELVIS SIPRIAN CASTRO ALZATE","id":"14838008","telefono":"3166280479","correo":"ELVIS.CASTRO@CORREOUNIVALLE.EDU.CO","ciudad":"CALI","direccion":"CR 48 4 71 AP 306 TORRE D UR ANTONIO NARI O","tipoInmueble":"Vivienda","canon":"876000","fechaRadicacion":"12/8/2025","fechaAprobacion":"12/8/2025","estado":"APROBADA"} | D11: cristian.mosquera@segurosbolivar.com | E11: Contacto Inicial y Datos | F11: DESISTIDO | G11: Seguro de Vida | H11: [{"fecha":"2025-08-13 08:12:09","usuario":"mildre.rico@segurosbolivar.com","accionRealizada":"DESISTIDO","leadEtapaActual":"Contacto Inicial y Datos","productosGestion":"Seguro de Vida","observaciones":"Cambio de inmueble"}] | I11: 45882.342 | J11: {"Contacto Inicial y Datos":{"nomAgt":"","emailCte":"","autorizaDatosPersonales":false,"fechaNacimiento":"","tipoDocumento":"","observacionesPresentacion":"NO TOMRAA EL INMUEBLE","genero":"Masculino","resultadoGestion":"Venta Cancelada","accion":"Venta Cancelada","usuario":"mildre.rico@segurosbolivar.com"},"Cotización y Pre-Asegurabilidad":{"periosidad":"","nPagosMensuales":"","admin":"","observacionesCotizacion":"","valorAseguradoVida":0,"primaVidaITP":0,"fechaCotizacionVida":""},"Declaración de Asegurabilidad":{"actividadesLicita":false,"procesoPenal":false,"frecuenciaDeportesAltoRiesgo":"","peso":"","estatura":"","imcCalculado":"","observacionImc":"","estadoAsegurabilidad":"","hipertensionArterial":false,"colesterolTrigliceridosElevados":false,"diabetes":false,"enfermedadCoronariaInfarto":false,"insuficienciaRenal":false,"cancerTumores":false,"derrameTrombosisCerebral":false,"enfermedadesPsicologicasPsiquiatricas":false,"sidaVih":false,"pruebaVihPositiva":false,"secuelasEnfermedadAccidente":"","diagnosticoEnfermedadFracturas":"","tratamientoAlcoholAlucinogenos":false,"cirugiaProgramada":false,"autorizacionInformacionMedica":false,"fechaAsegurabilidad":""},"Autorización de Descuento Débito":{"canalDescuento":"","tipoDeCuenta":"","entidadBancaria":"","numeroCuentaDebito":"","fechaVencimientoTC":"","numeroCuotasTC":"","autorizaDescuentoAutomatico":false,"entiendeMoraPrima":false,"valorPrima":0,"fechaAutorizacionDebito":"","observacionesCierre":""},"Beneficiarios y Autorizaciones":{"nombreBeneficiario1":"","apellidoBeneficiario1":"","parentescoBeneficiario1":"","designacionBeneficiario1":0,"nombreBeneficiario2":"","apellidoBeneficiario2":"","parentescoBeneficiario2":"","designacionBeneficiario2":0,"nombreBeneficiario3":"","apellidoBeneficiario3":"","parentescoBeneficiario3":"","designacionBeneficiario3":0,"beneficiariosRegistrados":false,"fechaRegistroBeneficiarios":""},"Emisión de Póliza":{"numeroCertificadoFinal":"","resultadoEmision":"","fechaVigenciaPoliza":"","polizaPrincipal":"","periodicidadPagoPoliza":"MENSUAL","confirmacionVentaSegurosBolivar":false,"liderClavo":"","certificado":"75272","observacionesEmision":"","fechaEmisionPoliza":"","estadoPoliza":"","numeroContrato":""}}
A12: 45881.787 | B12: 11695035 | C12: {"poliza":"13573","nombre":"MONICA MARIA PUERTA GALLO","id":"1017150295","telefono":"3022650431","correo":"puertamonicamaria@gmail.com","ciudad":"COPACABANA","direccion":"PENDIENTE","tipoInmueble":"Vivienda","canon":"900000","fechaRadicacion":"9/8/2025","fechaAprobacion":"12/8/2025","estado":"APROBADA"} | D12: Anyuley.daza@aselibertador.com | E12: Contacto Inicial y Datos | F12: DESISTIDO | G12: Seguro de Vida | H12: [{"fecha":"2025-08-13 08:14:41","usuario":"anyuley.daza@aselibertador.com","accionRealizada":"DESISTIDO","leadEtapaActual":"Contacto Inicial y Datos","productosGestion":"Seguro de Vida","observaciones":"No Contesta"}] | I12: 45882.344 | J12: {"Contacto Inicial y Datos":{"nomAgt":"","emailCte":"","autorizaDatosPersonales":false,"fechaNacimiento":"","tipoDocumento":"CC","observacionesPresentacion":"","genero":"Femenino","resultadoGestion":"Cliente ilocalizable","accion":"Cliente ilocalizable","usuario":"anyuley.daza@aselibertador.com"},"Cotización y Pre-Asegurabilidad":{"periosidad":"","nPagosMensuales":"","admin":"","observacionesCotizacion":"","valorAseguradoVida":0,"primaVidaITP":0,"fechaCotizacionVida":""},"Declaración de Asegurabilidad":{"actividadesLicita":false,"procesoPenal":false,"frecuenciaDeportesAltoRiesgo":"","peso":"","estatura":"","imcCalculado":"","observacionImc":"","estadoAsegurabilidad":"","hipertensionArterial":false,"colesterolTrigliceridosElevados":false,"diabetes":false,"enfermedadCoronariaInfarto":false,"insuficienciaRenal":false,"cancerTumores":false,"derrameTrombosisCerebral":false,"enfermedadesPsicologicasPsiquiatricas":false,"sidaVih":false,"pruebaVihPositiva":false,"secuelasEnfermedadAccidente":"","diagnosticoEnfermedadFracturas":"","tratamientoAlcoholAlucinogenos":false,"cirugiaProgramada":false,"autorizacionInformacionMedica":false,"fechaAsegurabilidad":""},"Autorización de Descuento Débito":{"canalDescuento":"","tipoDeCuenta":"","entidadBancaria":"","numeroCuentaDebito":"","fechaVencimientoTC":"","numeroCuotasTC":"","autorizaDescuentoAutomatico":false,"entiendeMoraPrima":false,"valorPrima":0,"fechaAutorizacionDebito":"","observacionesCierre":""},"Beneficiarios y Autorizaciones":{"nombreBeneficiario1":"","apellidoBeneficiario1":"","parentescoBeneficiario1":"","designacionBeneficiario1":0,"nombreBeneficiario2":"","apellidoBeneficiario2":"","parentescoBeneficiario2":"","designacionBeneficiario2":0,"nombreBeneficiario3":"","apellidoBeneficiario3":"","parentescoBeneficiario3":"","designacionBeneficiario3":0,"beneficiariosRegistrados":false,"fechaRegistroBeneficiarios":""},"Emisión de Póliza":{"numeroCertificadoFinal":"","resultadoEmision":"","fechaVigenciaPoliza":"","polizaPrincipal":"","periodicidadPagoPoliza":"MENSUAL","confirmacionVentaSegurosBolivar":false,"liderClavo":"","certificado":"75272","observacionesEmision":"","fechaEmisionPoliza":"","estadoPoliza":"","numeroContrato":""}}
A13: 45881.787 | B13: 11695057 | C13: {"poliza":"13404","nombre":"EDWIN MAURICIO PEÑA RUBIO","id":"1121830090","telefono":"3216051933","correo":"rubio_090@hotmail.com","ciudad":"MEDELLIN","direccion":"CL 58 #31 36 P 1","tipoInmueble":"Vivienda","canon":"1150000","fechaRadicacion":"9/8/2025","fechaAprobacion":"12/8/2025","estado":"APROBADA"} | D13: ana.prieto@aselibertador.com | E13: Contacto Inicial y Datos | F13: DESISTIDO | G13: Seguro de Vida | H13: [{"fecha":"2025-08-13 09:16:31","usuario":"ana.prieto@aselibertador.com","accionRealizada":"DESISTIDO","leadEtapaActual":"Contacto Inicial y Datos","productosGestion":"Seguro de Vida","observaciones":"No Contesta"}] | I13: 45882.386 | J13: {"Contacto Inicial y Datos":{"nomAgt":"","emailCte":"","autorizaDatosPersonales":false,"fechaNacimiento":"","tipoDocumento":"","observacionesPresentacion":"","genero":"","resultadoGestion":"Cliente ilocalizable","accion":"Cliente ilocalizable","usuario":"ana.prieto@aselibertador.com"},"Cotización y Pre-Asegurabilidad":{"periosidad":"","nPagosMensuales":"","admin":"","observacionesCotizacion":"","valorAseguradoVida":0,"primaVidaITP":0,"fechaCotizacionVida":""},"Declaración de Asegurabilidad":{"actividadesLicita":false,"procesoPenal":false,"frecuenciaDeportesAltoRiesgo":"","peso":"","estatura":"","imcCalculado":"","observacionImc":"","estadoAsegurabilidad":"","hipertensionArterial":false,"colesterolTrigliceridosElevados":false,"diabetes":false,"enfermedadCoronariaInfarto":false,"insuficienciaRenal":false,"cancerTumores":false,"derrameTrombosisCerebral":false,"enfermedadesPsicologicasPsiquiatricas":false,"sidaVih":false,"pruebaVihPositiva":false,"secuelasEnfermedadAccidente":"","diagnosticoEnfermedadFracturas":"","tratamientoAlcoholAlucinogenos":false,"cirugiaProgramada":false,"autorizacionInformacionMedica":false,"fechaAsegurabilidad":""},"Autorización de Descuento Débito":{"canalDescuento":"","tipoDeCuenta":"","entidadBancaria":"","numeroCuentaDebito":"","fechaVencimientoTC":"","numeroCuotasTC":"","autorizaDescuentoAutomatico":false,"entiendeMoraPrima":false,"valorPrima":0,"fechaAutorizacionDebito":"","observacionesCierre":""},"Beneficiarios y Autorizaciones":{"nombreBeneficiario1":"","apellidoBeneficiario1":"","parentescoBeneficiario1":"","designacionBeneficiario1":0,"nombreBeneficiario2":"","apellidoBeneficiario2":"","parentescoBeneficiario2":"","designacionBeneficiario2":0,"nombreBeneficiario3":"","apellidoBeneficiario3":"","parentescoBeneficiario3":"","designacionBeneficiario3":0,"beneficiariosRegistrados":false,"fechaRegistroBeneficiarios":""},"Emisión de Póliza":{"numeroCertificadoFinal":"","resultadoEmision":"","fechaVigenciaPoliza":"","polizaPrincipal":"","periodicidadPagoPoliza":"MENSUAL","confirmacionVentaSegurosBolivar":false,"liderClavo":"","certificado":"75272","observacionesEmision":"","fechaEmisionPoliza":"","estadoPoliza":"","numeroContrato":""}}
A14: 45881.787 | B14: 11695063 | C14: {"poliza":"1993","nombre":"JUAN DAVID BAYONA RAMIREZ","id":"1020757640","telefono":"3168789731","correo":"eyobayona@hotmail.com","ciudad":"BOGOTA, D.C.","direccion":"CR 19A 104 48","tipoInmueble":"Vivienda","canon":"2515616","fechaRadicacion":"9/8/2025","fechaAprobacion":"12/8/2025","estado":"APROBADA"} | D14: diana.salas@segurosbolivar.com | E14: Contacto Inicial y Datos | F14: DESISTIDO | G14: Seguro de Vida | H14: [{"fecha":"2025-08-13 08:27:08","usuario":"diana.salas@segurosbolivar.com","accionRealizada":"DESISTIDO","leadEtapaActual":"Contacto Inicial y Datos","productosGestion":"Seguro de Vida","observaciones":"No le interesa"}] | I14: 45882.352 | J14: {"Contacto Inicial y Datos":{"nomAgt":"","emailCte":"","autorizaDatosPersonales":false,"fechaNacimiento":"","tipoDocumento":"CC","observacionesPresentacion":"","genero":"","resultadoGestion":"Cliente no interesado","accion":"Cliente no interesado","usuario":"diana.salas@segurosbolivar.com"},"Cotización y Pre-Asegurabilidad":{"periosidad":"","nPagosMensuales":"","admin":"","observacionesCotizacion":"","valorAseguradoVida":0,"primaVidaITP":0,"fechaCotizacionVida":""},"Declaración de Asegurabilidad":{"actividadesLicita":false,"procesoPenal":false,"frecuenciaDeportesAltoRiesgo":"","peso":"","estatura":"","imcCalculado":"","observacionImc":"","estadoAsegurabilidad":"","hipertensionArterial":false,"colesterolTrigliceridosElevados":false,"diabetes":false,"enfermedadCoronariaInfarto":false,"insuficienciaRenal":false,"cancerTumores":false,"derrameTrombosisCerebral":false,"enfermedadesPsicologicasPsiquiatricas":false,"sidaVih":false,"pruebaVihPositiva":false,"secuelasEnfermedadAccidente":"","diagnosticoEnfermedadFracturas":"","tratamientoAlcoholAlucinogenos":false,"cirugiaProgramada":false,"autorizacionInformacionMedica":false,"fechaAsegurabilidad":""},"Autorización de Descuento Débito":{"canalDescuento":"","tipoDeCuenta":"","entidadBancaria":"","numeroCuentaDebito":"","fechaVencimientoTC":"","numeroCuotasTC":"","autorizaDescuentoAutomatico":false,"entiendeMoraPrima":false,"valorPrima":0,"fechaAutorizacionDebito":"","observacionesCierre":""},"Beneficiarios y Autorizaciones":{"nombreBeneficiario1":"","apellidoBeneficiario1":"","parentescoBeneficiario1":"","designacionBeneficiario1":0,"nombreBeneficiario2":"","apellidoBeneficiario2":"","parentescoBeneficiario2":"","designacionBeneficiario2":0,"nombreBeneficiario3":"","apellidoBeneficiario3":"","parentescoBeneficiario3":"","designacionBeneficiario3":0,"beneficiariosRegistrados":false,"fechaRegistroBeneficiarios":""},"Emisión de Póliza":{"numeroCertificadoFinal":"","resultadoEmision":"","fechaVigenciaPoliza":"","polizaPrincipal":"","periodicidadPagoPoliza":"MENSUAL","confirmacionVentaSegurosBolivar":false,"liderClavo":"","certificado":"75272","observacionesEmision":"","fechaEmisionPoliza":"","estadoPoliza":"","numeroContrato":""}}
A15: 45881.787 | B15: 11695100 | C15: {"poliza":"10017","nombre":"ANGELA MARIA LOPEZ VALENCIA","id":"31575495","telefono":"3164688197","correo":"amalova17@hotmail.com","ciudad":"CALI","direccion":"CL 13E 65 C 55","tipoInmueble":"Vivienda","canon":"2300000","fechaRadicacion":"9/8/2025","fechaAprobacion":"12/8/2025","estado":"APROBADA"} | D15: maria.gaitan@proyectivaseguros.com | E15: Contacto Inicial y Datos | F15: DESISTIDO | G15: Seguro de Vida | H15: [{"fecha":"2025-08-13 08:18:30","usuario":"maria.gaitan@segurosbolivar.com","accionRealizada":"DESISTIDO","leadEtapaActual":"Contacto Inicial y Datos","productosGestion":"Seguro de Vida","observaciones":"No Contesta"}] | I15: 45882.346 | J15: {"Contacto Inicial y Datos":{"nomAgt":"","emailCte":"","autorizaDatosPersonales":false,"fechaNacimiento":"","tipoDocumento":"CC","observacionesPresentacion":"","genero":"Femenino","resultadoGestion":"Cliente ilocalizable","accion":"Cliente ilocalizable","usuario":"maria.gaitan@segurosbolivar.com"},"Cotización y Pre-Asegurabilidad":{"periosidad":"Mensual","nPagosMensuales":"12","admin":"","observacionesCotizacion":"","valorAseguradoVida":0,"primaVidaITP":0,"fechaCotizacionVida":"","resultadoGestion":""},"Declaración de Asegurabilidad":{"actividadesLicita":false,"procesoPenal":false,"frecuenciaDeportesAltoRiesgo":"","peso":"","estatura":"","imcCalculado":"","observacionImc":"","estadoAsegurabilidad":"","hipertensionArterial":false,"colesterolTrigliceridosElevados":false,"diabetes":false,"enfermedadCoronariaInfarto":false,"insuficienciaRenal":false,"cancerTumores":false,"derrameTrombosisCerebral":false,"enfermedadesPsicologicasPsiquiatricas":false,"sidaVih":false,"pruebaVihPositiva":false,"secuelasEnfermedadAccidente":"","diagnosticoEnfermedadFracturas":"","tratamientoAlcoholAlucinogenos":false,"cirugiaProgramada":false,"autorizacionInformacionMedica":false,"fechaAsegurabilidad":""},"Autorización de Descuento Débito":{"canalDescuento":"","tipoDeCuenta":"","entidadBancaria":"","numeroCuentaDebito":"","fechaVencimientoTC":"","numeroCuotasTC":"","autorizaDescuentoAutomatico":false,"entiendeMoraPrima":false,"valorPrima":0,"fechaAutorizacionDebito":"","observacionesCierre":""},"Beneficiarios y Autorizaciones":{"nombreBeneficiario1":"","apellidoBeneficiario1":"","parentescoBeneficiario1":"","designacionBeneficiario1":0,"nombreBeneficiario2":"","apellidoBeneficiario2":"","parentescoBeneficiario2":"","designacionBeneficiario2":0,"nombreBeneficiario3":"","apellidoBeneficiario3":"","parentescoBeneficiario3":"","designacionBeneficiario3":0,"beneficiariosRegistrados":false,"fechaRegistroBeneficiarios":""},"Emisión de Póliza":{"numeroCertificadoFinal":"","resultadoEmision":"","fechaVigenciaPoliza":"","polizaPrincipal":"","periodicidadPagoPoliza":"MENSUAL","confirmacionVentaSegurosBolivar":false,"liderClavo":"","certificado":"75272","observacionesEmision":"","fechaEmisionPoliza":"","estadoPoliza":"","numeroContrato":""}}
A16: 45881.787 | B16: 11695127 | C16: {"poliza":"13404","nombre":"JHOEL ESTEBAN SÁNCHEZ MONSALVE","id":"1032259700","telefono":"3006664693","correo":"maryuli1957@gmail.com","ciudad":"MEDELLIN","direccion":"CRA 79 A #111 29","tipoInmueble":"Vivienda","canon":"900000","fechaRadicacion":"9/8/2025","fechaAprobacion":"12/8/2025","estado":"APROBADA"} | D16: olga.obando@proyectivaseguros.com | E16: Declaración de Asegurabilidad | F16: DESISTIDO | G16: Seguro de Vida | H16: [{"fecha":"2025-08-13 08:21:20","usuario":"olga.obando@segurosbolivar.com","accionRealizada":"DESISTIDO","leadEtapaActual":"Declaración de Asegurabilidad","productosGestion":"Seguro de Vida","observaciones":"Declaración"},{"fecha":"2025-08-13 08:22:54","usuario":"olga.obando@segurosbolivar.com","accionRealizada":"DESISTIDO","leadEtapaActual":"Declaración de Asegurabilidad","productosGestion":"Seguro de Vida","observaciones":"Declaración"}] | I16: 45882.349 | J16: {"Contacto Inicial y Datos":{"nomAgt":"olga.obando@segurosbolivar.com","emailCte":"","autorizaDatosPersonales":true,"fechaNacimiento":"1996-05-15","tipoDocumento":"CC","observacionesPresentacion":"TODO OK","genero":"Masculino","resultadoGestion":"Cliente acepta tratamiento de datos personales","accion":"Cliente acepta tratamiento de datos personales","usuario":"olga.obando@segurosbolivar.com"},"Cotización y Pre-Asegurabilidad":{"periosidad":"Mensual","nPagosMensuales":"24","admin":"","observacionesCotizacion":"TODO","valorAseguradoVida":21600000,"primaVidaITP":22140.000000000004,"fechaCotizacionVida":"13/8/2025","resultadoGestion":"Cliente acepta Cotización","accion":"Cliente acepta Cotización","usuario":"olga.obando@segurosbolivar.com"},"Declaración de Asegurabilidad":{"actividadesLicita":true,"procesoPenal":true,"frecuenciaDeportesAltoRiesgo":"0","peso":"","estatura":"","imcCalculado":"","observacionImc":"","estadoAsegurabilidad":"","hipertensionArterial":false,"colesterolTrigliceridosElevados":false,"diabetes":false,"enfermedadCoronariaInfarto":false,"insuficienciaRenal":false,"cancerTumores":false,"derrameTrombosisCerebral":false,"enfermedadesPsicologicasPsiquiatricas":false,"sidaVih":false,"pruebaVihPositiva":false,"secuelasEnfermedadAccidente":"","diagnosticoEnfermedadFracturas":"","tratamientoAlcoholAlucinogenos":false,"cirugiaProgramada":false,"autorizacionInformacionMedica":false,"fechaAsegurabilidad":"","sarlaft":false,"resultadoGestion":"No Asegurable","observacionesNegociacion":"IMC ELEVADO 33,30","accion":"No Asegurable","usuario":"olga.obando@segurosbolivar.com"},"Autorización de Descuento Débito":{"canalDescuento":"","tipoDeCuenta":"","entidadBancaria":"","numeroCuentaDebito":"","fechaVencimientoTC":"","numeroCuotasTC":"","autorizaDescuentoAutomatico":false,"entiendeMoraPrima":false,"valorPrima":0,"fechaAutorizacionDebito":"","observacionesCierre":""},"Beneficiarios y Autorizaciones":{"nombreBeneficiario1":"","apellidoBeneficiario1":"","parentescoBeneficiario1":"","designacionBeneficiario1":0,"nombreBeneficiario2":"","apellidoBeneficiario2":"","parentescoBeneficiario2":"","designacionBeneficiario2":0,"nombreBeneficiario3":"","apellidoBeneficiario3":"","parentescoBeneficiario3":"","designacionBeneficiario3":0,"beneficiariosRegistrados":false,"fechaRegistroBeneficiarios":""},"Emisión de Póliza":{"numeroCertificadoFinal":"","resultadoEmision":"","fechaVigenciaPoliza":"","polizaPrincipal":"","periodicidadPagoPoliza":"MENSUAL","confirmacionVentaSegurosBolivar":false,"liderClavo":"","certificado":"75272","observacionesEmision":"","fechaEmisionPoliza":"","estadoPoliza":"","numeroContrato":""}}
A17: 45881.787 | B17: 11695130 | C17: {"poliza":"13818","nombre":"LUIS ALBERTO MERCADO AGUAS","id":"1103109777","telefono":"3013751548","correo":"marmag992@gmail.com","ciudad":"MEDELLIN","direccion":"CR 93 # 82 59 AURES II","tipoInmueble":"Vivienda","canon":"950000","fechaRadicacion":"9/8/2025","fechaAprobacion":"12/8/2025","estado":"APROBADA"} | D17: angela.caipa@segurosbolivar.com | E17: Contacto Inicial y Datos | F17: DESISTIDO | G17: Seguro de Vida | H17: [{"fecha":"2025-08-13 08:31:57","usuario":"angela.caipa@segurosbolivar.com","accionRealizada":"Cliente no contesta","leadEtapaActual":"Contacto Inicial y Datos","productosGestion":"Seguro de Vida","observaciones":"Sin observaciones específicas"},{"fecha":"2025-08-13 09:28:00","usuario":"angela.caipa@segurosbolivar.com","accionRealizada":"DESISTIDO","leadEtapaActual":"Contacto Inicial y Datos","productosGestion":"Seguro de Vida","observaciones":"No Contesta"}] | I17: 45882.394 | J17: {"Contacto Inicial y Datos":{"nomAgt":"","emailCte":"","autorizaDatosPersonales":false,"fechaNacimiento":"2025-08-13","tipoDocumento":"","observacionesPresentacion":"","genero":"","resultadoGestion":"Cliente ilocalizable","accion":"Cliente ilocalizable","usuario":"angela.caipa@segurosbolivar.com"},"Cotización y Pre-Asegurabilidad":{"periosidad":"","nPagosMensuales":"","admin":"","observacionesCotizacion":"","valorAseguradoVida":0,"primaVidaITP":0,"fechaCotizacionVida":""},"Declaración de Asegurabilidad":{"actividadesLicita":false,"procesoPenal":false,"frecuenciaDeportesAltoRiesgo":"","peso":"","estatura":"","imcCalculado":"","observacionImc":"","estadoAsegurabilidad":"","hipertensionArterial":false,"colesterolTrigliceridosElevados":false,"diabetes":false,"enfermedadCoronariaInfarto":false,"insuficienciaRenal":false,"cancerTumores":false,"derrameTrombosisCerebral":false,"enfermedadesPsicologicasPsiquiatricas":false,"sidaVih":false,"pruebaVihPositiva":false,"secuelasEnfermedadAccidente":"","diagnosticoEnfermedadFracturas":"","tratamientoAlcoholAlucinogenos":false,"cirugiaProgramada":false,"autorizacionInformacionMedica":false,"fechaAsegurabilidad":""},"Autorización de Descuento Débito":{"canalDescuento":"","tipoDeCuenta":"","entidadBancaria":"","numeroCuentaDebito":"","fechaVencimientoTC":"","numeroCuotasTC":"","autorizaDescuentoAutomatico":false,"entiendeMoraPrima":false,"valorPrima":0,"fechaAutorizacionDebito":"","observacionesCierre":""},"Beneficiarios y Autorizaciones":{"nombreBeneficiario1":"","apellidoBeneficiario1":"","parentescoBeneficiario1":"","designacionBeneficiario1":0,"nombreBeneficiario2":"","apellidoBeneficiario2":"","parentescoBeneficiario2":"","designacionBeneficiario2":0,"nombreBeneficiario3":"","apellidoBeneficiario3":"","parentescoBeneficiario3":"","designacionBeneficiario3":0,"beneficiariosRegistrados":false,"fechaRegistroBeneficiarios":""},"Emisión de Póliza":{"numeroCertificadoFinal":"","resultadoEmision":"","fechaVigenciaPoliza":"","polizaPrincipal":"","periodicidadPagoPoliza":"MENSUAL","confirmacionVentaSegurosBolivar":false,"liderClavo":"","certificado":"75272","observacionesEmision":"","fechaEmisionPoliza":"","estadoPoliza":"","numeroContrato":""}}
A18: 45881.787 | B18: 11695136 | C18: {"poliza":"999","nombre":"LAURA MARIA SALAZAR GOMEZ","id":"1128404560","telefono":"3128981034","correo":"lauram.salazar@gmail.com","ciudad":"MEDELLIN","direccion":"PENDIENTE","tipoInmueble":"Vivienda","canon":"3500000","fechaRadicacion":"9/8/2025","fechaAprobacion":"12/8/2025","estado":"APROBADA"} | D18: mildre.rico@segurosbolivar.com | E18: Cotización y Pre-Asegurabilidad | F18: DESISTIDO | G18: Seguro de Vida | H18: [{"fecha":"2025-08-13 08:25:19","usuario":"mildre.rico@segurosbolivar.com","accionRealizada":"DESISTIDO","leadEtapaActual":"Cotización y Pre-Asegurabilidad","productosGestion":"Seguro de Vida","observaciones":"Evade ofrecimiento"}] | I18: 45882.351 | J18: {"Contacto Inicial y Datos":{"nomAgt":"","emailCte":"","autorizaDatosPersonales":false,"fechaNacimiento":"2006-06-14","tipoDocumento":"","observacionesPresentacion":"no","genero":"Femenino","resultadoGestion":"Cliente acepta tratamiento de datos personales","accion":"Cliente acepta tratamiento de datos personales","usuario":"mildre.rico@segurosbolivar.com"},"Cotización y Pre-Asegurabilidad":{"periosidad":"Mensual","nPagosMensuales":"24","admin":"","observacionesCotizacion":"kl,j","valorAseguradoVida":0,"primaVidaITP":0,"fechaCotizacionVida":"","resultadoGestion":"Cliente no acepta tratamiento de datos personales","accion":"Cliente no acepta tratamiento de datos personales","usuario":"mildre.rico@segurosbolivar.com"},"Declaración de Asegurabilidad":{"actividadesLicita":false,"procesoPenal":false,"frecuenciaDeportesAltoRiesgo":"","peso":"","estatura":"","imcCalculado":"","observacionImc":"","estadoAsegurabilidad":"","hipertensionArterial":false,"colesterolTrigliceridosElevados":false,"diabetes":false,"enfermedadCoronariaInfarto":false,"insuficienciaRenal":false,"cancerTumores":false,"derrameTrombosisCerebral":false,"enfermedadesPsicologicasPsiquiatricas":false,"sidaVih":false,"pruebaVihPositiva":false,"secuelasEnfermedadAccidente":"","diagnosticoEnfermedadFracturas":"","tratamientoAlcoholAlucinogenos":false,"cirugiaProgramada":false,"autorizacionInformacionMedica":false,"fechaAsegurabilidad":""},"Autorización de Descuento Débito":{"canalDescuento":"","tipoDeCuenta":"","entidadBancaria":"","numeroCuentaDebito":"","fechaVencimientoTC":"","numeroCuotasTC":"","autorizaDescuentoAutomatico":false,"entiendeMoraPrima":false,"valorPrima":0,"fechaAutorizacionDebito":"","observacionesCierre":""},"Beneficiarios y Autorizaciones":{"nombreBeneficiario1":"","apellidoBeneficiario1":"","parentescoBeneficiario1":"","designacionBeneficiario1":0,"nombreBeneficiario2":"","apellidoBeneficiario2":"","parentescoBeneficiario2":"","designacionBeneficiario2":0,"nombreBeneficiario3":"","apellidoBeneficiario3":"","parentescoBeneficiario3":"","designacionBeneficiario3":0,"beneficiariosRegistrados":false,"fechaRegistroBeneficiarios":""},"Emisión de Póliza":{"numeroCertificadoFinal":"","resultadoEmision":"","fechaVigenciaPoliza":"","polizaPrincipal":"","periodicidadPagoPoliza":"MENSUAL","confirmacionVentaSegurosBolivar":false,"liderClavo":"","certificado":"75272","observacionesEmision":"","fechaEmisionPoliza":"","estadoPoliza":"","numeroContrato":""}}
A19: 45881.787 | B19: 11695156 | C19: {"poliza":"10717","nombre":"BRAYAN ARMANDO PORTILLA ORTIZ","id":"1143993729","telefono":"3177237542","correo":"od.portillaortiz@gmail.com","ciudad":"CALI","direccion":"AV 3 NORTE 44 38","tipoInmueble":"Comercial","canon":"1500000","fechaRadicacion":"9/8/2025","fechaAprobacion":"12/8/2025","estado":"APROBADA"} | D19: Anyuley.daza@aselibertador.com | E19: Contacto Inicial y Datos | F19: DESISTIDO | G19: Seguro de Vida | H19: [{"fecha":"2025-08-13 08:17:05","usuario":"anyuley.daza@aselibertador.com","accionRealizada":"DESISTIDO","leadEtapaActual":"Contacto Inicial y Datos","productosGestion":"Seguro de Vida","observaciones":"No Contesta"}] | I19: 45882.345 | J19: {"Contacto Inicial y Datos":{"nomAgt":"","emailCte":"","autorizaDatosPersonales":false,"fechaNacimiento":"","tipoDocumento":"","observacionesPresentacion":"Se marca tres veces,no contesta","genero":"","resultadoGestion":"Cliente ilocalizable","accion":"Cliente ilocalizable","usuario":"anyuley.daza@aselibertador.com"},"Cotización y Pre-Asegurabilidad":{"periosidad":"","nPagosMensuales":"","admin":"","observacionesCotizacion":"","valorAseguradoVida":0,"primaVidaITP":0,"fechaCotizacionVida":""},"Declaración de Asegurabilidad":{"actividadesLicita":false,"procesoPenal":false,"frecuenciaDeportesAltoRiesgo":"","peso":"","estatura":"","imcCalculado":"","observacionImc":"","estadoAsegurabilidad":"","hipertensionArterial":false,"colesterolTrigliceridosElevados":false,"diabetes":false,"enfermedadCoronariaInfarto":false,"insuficienciaRenal":false,"cancerTumores":false,"derrameTrombosisCerebral":false,"enfermedadesPsicologicasPsiquiatricas":false,"sidaVih":false,"pruebaVihPositiva":false,"secuelasEnfermedadAccidente":"","diagnosticoEnfermedadFracturas":"","tratamientoAlcoholAlucinogenos":false,"cirugiaProgramada":false,"autorizacionInformacionMedica":false,"fechaAsegurabilidad":""},"Autorización de Descuento Débito":{"canalDescuento":"","tipoDeCuenta":"","entidadBancaria":"","numeroCuentaDebito":"","fechaVencimientoTC":"","numeroCuotasTC":"","autorizaDescuentoAutomatico":false,"entiendeMoraPrima":false,"valorPrima":0,"fechaAutorizacionDebito":"","observacionesCierre":""},"Beneficiarios y Autorizaciones":{"nombreBeneficiario1":"","apellidoBeneficiario1":"","parentescoBeneficiario1":"","designacionBeneficiario1":0,"nombreBeneficiario2":"","apellidoBeneficiario2":"","parentescoBeneficiario2":"","designacionBeneficiario2":0,"nombreBeneficiario3":"","apellidoBeneficiario3":"","parentescoBeneficiario3":"","designacionBeneficiario3":0,"beneficiariosRegistrados":false,"fechaRegistroBeneficiarios":""},"Emisión de Póliza":{"numeroCertificadoFinal":"","resultadoEmision":"","fechaVigenciaPoliza":"","polizaPrincipal":"","periodicidadPagoPoliza":"MENSUAL","confirmacionVentaSegurosBolivar":false,"liderClavo":"","certificado":"75272","observacionesEmision":"","fechaEmisionPoliza":"","estadoPoliza":"","numeroContrato":""}}
... A64: 45885.497 | B64: 11703271 | C64: {"poliza":"2252","nombre":"ANA FABIOLA VALENCIA MEDINA","id":"20390786","telefono":"3225121109","correo":"sindycasva@gmail.com","ciudad":"MADRID","direccion":"CL 4 ESTE # 1 100","tipoInmueble":"Vivienda","canon":"1350000","fechaRadicacion":"15/8/2025","fechaAprobacion":"16/8/2025","estado":"APROBADA"} | D64: angela.caipa@segurosbolivar.com | E64: Contacto Inicial y Datos | F64: DESISTIDO | G64: Seguro de Vida | H64: [{"fecha":"2025-08-19 08:22:55","usuario":"angela.caipa@segurosbolivar.com","accionRealizada":"DESISTIDO","leadEtapaActual":"Contacto Inicial y Datos","productosGestion":"Seguro de Vida","observaciones":"Tiene otras polizas"}] | I64: 45888.349 | J64: {"Contacto Inicial y Datos":{"nomAgt":"","emailCte":"","autorizaDatosPersonales":false,"fechaNacimiento":"","tipoDocumento":"","observacionesPresentacion":"","genero":"","resultadoGestion":"","accion":"No Asegurable","usuario":"angela.caipa@segurosbolivar.com"},"Cotización y Pre-Asegurabilidad":{"periosidad":"","nPagosMensuales":"","admin":"","observacionesCotizacion":"","valorAseguradoVida":0,"primaVidaITP":0,"fechaCotizacionVida":""},"Declaración de Asegurabilidad":{"actividadesLicita":false,"procesoPenal":false,"frecuenciaDeportesAltoRiesgo":"","peso":"","estatura":"","imcCalculado":"","observacionImc":"","estadoAsegurabilidad":"","hipertensionArterial":false,"colesterolTrigliceridosElevados":false,"diabetes":false,"enfermedadCoronariaInfarto":false,"insuficienciaRenal":false,"cancerTumores":false,"derrameTrombosisCerebral":false,"enfermedadesPsicologicasPsiquiatricas":false,"sidaVih":false,"pruebaVihPositiva":false,"secuelasEnfermedadAccidente":"","diagnosticoEnfermedadFracturas":"","tratamientoAlcoholAlucinogenos":false,"cirugiaProgramada":false,"autorizacionInformacionMedica":false,"fechaAsegurabilidad":""},"Autorización de Descuento Débito":{"canalDescuento":"","tipoDeCuenta":"","entidadBancaria":"","numeroCuentaDebito":"","fechaVencimientoTC":"","numeroCuotasTC":"","autorizaDescuentoAutomatico":false,"entiendeMoraPrima":false,"valorPrima":0,"fechaAutorizacionDebito":"","observacionesCierre":""},"Beneficiarios y Autorizaciones":{"nombreBeneficiario1":"","apellidoBeneficiario1":"","parentescoBeneficiario1":"","designacionBeneficiario1":0,"nombreBeneficiario2":"","apellidoBeneficiario2":"","parentescoBeneficiario2":"","designacionBeneficiario2":0,"nombreBeneficiario3":"","apellidoBeneficiario3":"","parentescoBeneficiario3":"","designacionBeneficiario3":0,"beneficiariosRegistrados":false,"fechaRegistroBeneficiarios":""},"Emisión de Póliza":{"numeroCertificadoFinal":"","resultadoEmision":"","fechaVigenciaPoliza":"","polizaPrincipal":"","periodicidadPagoPoliza":"MENSUAL","confirmacionVentaSegurosBolivar":false,"liderClavo":"","certificado":"75272","observacionesEmision":"","fechaEmisionPoliza":"","estadoPoliza":"","numeroContrato":""}}
A65: 45885.497 | B65: 11703312 | C65: {"poliza":"1993","nombre":"CRISTHIAN EDUARDO MATUSAN ACUÑA","id":"11203201","telefono":"3105513757","correo":"christianmatusan@hotmail.com","ciudad":"BOGOTA, D.C.","direccion":"CL 49 9 25 AP 709","tipoInmueble":"Vivienda","canon":"2380000","fechaRadicacion":"15/8/2025","fechaAprobacion":"16/8/2025","estado":"APROBADA"} | D65: desarrollocrmlibertador@ellibertador.co | E65: Contacto Inicial y Datos | F65: pendiente gestion | G65: Seguro de Vida
A66: 45885.497 | B66: 11703324 | C66: {"poliza":"1474","nombre":"ALBA DOLORES CORDOBA HERRERA","id":"42082239","telefono":"3168223830","correo":"albacordoba1@hotmail.com","ciudad":"BOGOTA, D.C.","direccion":"CL 64 13 55","tipoInmueble":"Vivienda","canon":"950000","fechaRadicacion":"15/8/2025","fechaAprobacion":"16/8/2025","estado":"APROBADA"} | D66: desarrollocrmlibertador@ellibertador.co | E66: Contacto Inicial y Datos | F66: pendiente gestion | G66: Seguro de Vida
A67: 45885.497 | B67: 11703556 | C67: {"poliza":"13793","nombre":"ARROYAVE DANIEL RIVERA ARROYAVE","id":"1020479064","telefono":"3128851318","correo":"danielriveraarroyave@gmail.com","ciudad":"BELLO","direccion":"CL 52B 64 95","tipoInmueble":"Vivienda","canon":"1500000","fechaRadicacion":"16/8/2025","fechaAprobacion":"16/8/2025","estado":"APROBADA"} | D67: mildre.rico@segurosbolivar.com | E67: Contacto Inicial y Datos | F67: DESISTIDO | G67: Seguro de Vida | H67: [{"fecha":"2025-08-19 08:41:46","usuario":"mildre.rico@segurosbolivar.com","accionRealizada":"DESISTIDO","leadEtapaActual":"Contacto Inicial y Datos","productosGestion":"Seguro de Vida","observaciones":"Cliente sin señal"}] | I67: 45888.362 | J67: {"Contacto Inicial y Datos":{"nomAgt":"","emailCte":"","autorizaDatosPersonales":false,"fechaNacimiento":"","tipoDocumento":"","observacionesPresentacion":"","genero":"","resultadoGestion":"Cliente ilocalizable","accion":"Cliente ilocalizable","usuario":"mildre.rico@segurosbolivar.com"},"Cotización y Pre-Asegurabilidad":{"periosidad":"","nPagosMensuales":"","admin":"","observacionesCotizacion":"","valorAseguradoVida":0,"primaVidaITP":0,"fechaCotizacionVida":""},"Declaración de Asegurabilidad":{"actividadesLicita":false,"procesoPenal":false,"frecuenciaDeportesAltoRiesgo":"","peso":"","estatura":"","imcCalculado":"","observacionImc":"","estadoAsegurabilidad":"","hipertensionArterial":false,"colesterolTrigliceridosElevados":false,"diabetes":false,"enfermedadCoronariaInfarto":false,"insuficienciaRenal":false,"cancerTumores":false,"derrameTrombosisCerebral":false,"enfermedadesPsicologicasPsiquiatricas":false,"sidaVih":false,"pruebaVihPositiva":false,"secuelasEnfermedadAccidente":"","diagnosticoEnfermedadFracturas":"","tratamientoAlcoholAlucinogenos":false,"cirugiaProgramada":false,"autorizacionInformacionMedica":false,"fechaAsegurabilidad":""},"Autorización de Descuento Débito":{"canalDescuento":"","tipoDeCuenta":"","entidadBancaria":"","numeroCuentaDebito":"","fechaVencimientoTC":"","numeroCuotasTC":"","autorizaDescuentoAutomatico":false,"entiendeMoraPrima":false,"valorPrima":0,"fechaAutorizacionDebito":"","observacionesCierre":""},"Beneficiarios y Autorizaciones":{"nombreBeneficiario1":"","apellidoBeneficiario1":"","parentescoBeneficiario1":"","designacionBeneficiario1":0,"nombreBeneficiario2":"","apellidoBeneficiario2":"","parentescoBeneficiario2":"","designacionBeneficiario2":0,"nombreBeneficiario3":"","apellidoBeneficiario3":"","parentescoBeneficiario3":"","designacionBeneficiario3":0,"beneficiariosRegistrados":false,"fechaRegistroBeneficiarios":""},"Emisión de Póliza":{"numeroCertificadoFinal":"","resultadoEmision":"","fechaVigenciaPoliza":"","polizaPrincipal":"","periodicidadPagoPoliza":"MENSUAL","confirmacionVentaSegurosBolivar":false,"liderClavo":"","certificado":"75272","observacionesEmision":"","fechaEmisionPoliza":"","estadoPoliza":"","numeroContrato":""}}
A68: 45885.497 | B68: 11703608 | C68: {"poliza":"13078","nombre":"DAVID FELIPE GARCIA CASTAÑO","id":"1017275973","telefono":"3104447747","correo":"gcdavid20@gmail.com","ciudad":"BELLO","direccion":"CL 37 43A56 AP 1305 TORRE4","tipoInmueble":"Vivienda","canon":"1600000","fechaRadicacion":"16/8/2025","fechaAprobacion":"16/8/2025","estado":"APROBADA"} | D68: diana.salas@segurosbolivar.com | E68: Contacto Inicial y Datos | F68: Cliente no contesta | G68: Seguro de Vida | H68: [{"fecha":"2025-08-16 12:08:46","usuario":"diana.salas@segurosbolivar.com","accionRealizada":"Cliente no contesta","leadEtapaActual":"Contacto Inicial y Datos","productosGestion":"Seguro de Vida","observaciones":"Sin observaciones específicas"},{"fecha":"2025-08-16 12:38:36","usuario":"diana.salas@segurosbolivar.com","accionRealizada":"Cliente no contesta","leadEtapaActual":"Contacto Inicial y Datos","productosGestion":"Seguro de Vida","observaciones":"Sin observaciones específicas"}] | I68: 45885.527 | J68: {"Contacto Inicial y Datos":{"nomAgt":"","emailCte":"","autorizaDatosPersonales":false,"fechaNacimiento":"1986-04-03","tipoDocumento":"CC","observacionesPresentacion":"","genero":"Masculino","resultadoGestion":"Cliente no contesta","accion":"Cliente no contesta","usuario":"diana.salas@segurosbolivar.com"},"Cotización y Pre-Asegurabilidad":{"periosidad":"","nPagosMensuales":"","admin":"","observacionesCotizacion":"","valorAseguradoVida":0,"primaVidaITP":0,"fechaCotizacionVida":""},"Declaración de Asegurabilidad":{"actividadesLicita":false,"procesoPenal":false,"frecuenciaDeportesAltoRiesgo":"","peso":"","estatura":"","imcCalculado":"","observacionImc":"","estadoAsegurabilidad":"","hipertensionArterial":false,"colesterolTrigliceridosElevados":false,"diabetes":false,"enfermedadCoronariaInfarto":false,"insuficienciaRenal":false,"cancerTumores":false,"derrameTrombosisCerebral":false,"enfermedadesPsicologicasPsiquiatricas":false,"sidaVih":false,"pruebaVihPositiva":false,"secuelasEnfermedadAccidente":"","diagnosticoEnfermedadFracturas":"","tratamientoAlcoholAlucinogenos":false,"cirugiaProgramada":false,"autorizacionInformacionMedica":false,"fechaAsegurabilidad":""},"Autorización de Descuento Débito":{"canalDescuento":"","tipoDeCuenta":"","entidadBancaria":"","numeroCuentaDebito":"","fechaVencimientoTC":"","numeroCuotasTC":"","autorizaDescuentoAutomatico":false,"entiendeMoraPrima":false,"valorPrima":0,"fechaAutorizacionDebito":"","observacionesCierre":""},"Beneficiarios y Autorizaciones":{"nombreBeneficiario1":"","apellidoBeneficiario1":"","parentescoBeneficiario1":"","designacionBeneficiario1":0,"nombreBeneficiario2":"","apellidoBeneficiario2":"","parentescoBeneficiario2":"","designacionBeneficiario2":0,"nombreBeneficiario3":"","apellidoBeneficiario3":"","parentescoBeneficiario3":"","designacionBeneficiario3":0,"beneficiariosRegistrados":false,"fechaRegistroBeneficiarios":""},"Emisión de Póliza":{"numeroCertificadoFinal":"","resultadoEmision":"","fechaVigenciaPoliza":"","polizaPrincipal":"","periodicidadPagoPoliza":"MENSUAL","confirmacionVentaSegurosBolivar":false,"liderClavo":"","certificado":"75272","observacionesEmision":"","fechaEmisionPoliza":"","estadoPoliza":"","numeroContrato":""}}
A69: 45885.497 | B69: 11703624 | C69: {"poliza":"13072","nombre":"JAIME HUMBERTO ALZATE SERNA","id":"1037571780","telefono":"3116194722","correo":"jaime.alzate@sura-am.com","ciudad":"ENVIGADO","direccion":"PENDIENTE","tipoInmueble":"Vivienda","canon":"3500000","fechaRadicacion":"16/8/2025","fechaAprobacion":"16/8/2025","estado":"APROBADA"} | D69: maria.gaitan@proyectivaseguros.com | E69: Contacto Inicial y Datos | F69: DESISTIDO | G69: Seguro de Vida | H69: [{"fecha":"2025-08-16 12:02:46","usuario":"maria.gaitan@segurosbolivar.com","accionRealizada":"DESISTIDO","leadEtapaActual":"Contacto Inicial y Datos","productosGestion":"Seguro de Vida","observaciones":"No conoce el inmueble"}] | I69: 45885.502 | J69: {"Contacto Inicial y Datos":{"nomAgt":"","emailCte":"","autorizaDatosPersonales":false,"fechaNacimiento":"","tipoDocumento":"","observacionesPresentacion":"NO CONOCE EL APTO","genero":"","resultadoGestion":"Venta Cancelada","accion":"Venta Cancelada","usuario":"maria.gaitan@segurosbolivar.com"},"Cotización y Pre-Asegurabilidad":{"periosidad":"","nPagosMensuales":"","admin":"","observacionesCotizacion":"","valorAseguradoVida":0,"primaVidaITP":0,"fechaCotizacionVida":""},"Declaración de Asegurabilidad":{"actividadesLicita":false,"procesoPenal":false,"frecuenciaDeportesAltoRiesgo":"","peso":"","estatura":"","imcCalculado":"","observacionImc":"","estadoAsegurabilidad":"","hipertensionArterial":false,"colesterolTrigliceridosElevados":false,"diabetes":false,"enfermedadCoronariaInfarto":false,"insuficienciaRenal":false,"cancerTumores":false,"derrameTrombosisCerebral":false,"enfermedadesPsicologicasPsiquiatricas":false,"sidaVih":false,"pruebaVihPositiva":false,"secuelasEnfermedadAccidente":"","diagnosticoEnfermedadFracturas":"","tratamientoAlcoholAlucinogenos":false,"cirugiaProgramada":false,"autorizacionInformacionMedica":false,"fechaAsegurabilidad":""},"Autorización de Descuento Débito":{"canalDescuento":"","tipoDeCuenta":"","entidadBancaria":"","numeroCuentaDebito":"","fechaVencimientoTC":"","numeroCuotasTC":"","autorizaDescuentoAutomatico":false,"entiendeMoraPrima":false,"valorPrima":0,"fechaAutorizacionDebito":"","observacionesCierre":""},"Beneficiarios y Autorizaciones":{"nombreBeneficiario1":"","apellidoBeneficiario1":"","parentescoBeneficiario1":"","designacionBeneficiario1":0,"nombreBeneficiario2":"","apellidoBeneficiario2":"","parentescoBeneficiario2":"","designacionBeneficiario2":0,"nombreBeneficiario3":"","apellidoBeneficiario3":"","parentescoBeneficiario3":"","designacionBeneficiario3":0,"beneficiariosRegistrados":false,"fechaRegistroBeneficiarios":""},"Emisión de Póliza":{"numeroCertificadoFinal":"","resultadoEmision":"","fechaVigenciaPoliza":"","polizaPrincipal":"","periodicidadPagoPoliza":"MENSUAL","confirmacionVentaSegurosBolivar":false,"liderClavo":"","certificado":"75272","observacionesEmision":"","fechaEmisionPoliza":"","estadoPoliza":"","numeroContrato":""}}
A70: 45885.497 | B70: 11703744 | C70: {"poliza":"13150","nombre":"ARBOLEDA FRANSELY PULGARIN ARBOLEDA","id":"1017226064","telefono":"3104365141","correo":"franselypulgarinarboleda@gmail.com","ciudad":"MEDELLIN","direccion":"PENDIENTE","tipoInmueble":"Vivienda","canon":"1450000","fechaRadicacion":"16/8/2025","fechaAprobacion":"16/8/2025","estado":"APROBADA"} | D70: olga.obando@proyectivaseguros.com | E70: Contacto Inicial y Datos | F70: DESISTIDO | G70: Seguro de Vida | H70: [{"fecha":"2025-08-19 17:08:21","usuario":"olga.obando@segurosbolivar.com","accionRealizada":"DESISTIDO","leadEtapaActual":"Contacto Inicial y Datos","productosGestion":"Seguro de Vida","observaciones":"Canon pago en sociedad"},{"fecha":"2025-08-19 17:09:46","usuario":"olga.obando@segurosbolivar.com","accionRealizada":"DESISTIDO","leadEtapaActual":"Contacto Inicial y Datos","productosGestion":"Seguro de Vida","observaciones":"Canon pago en sociedad"}] | I70: 45888.715 | J70: {"Contacto Inicial y Datos":{"nomAgt":"","emailCte":"","autorizaDatosPersonales":false,"fechaNacimiento":"1994-12-15","tipoDocumento":"CC","observacionesPresentacion":"TODO OK","genero":"Femenino","resultadoGestion":"Cliente acepta tratamiento de datos personales","accion":"No Asegurable","usuario":"olga.obando@segurosbolivar.com"},"Cotización y Pre-Asegurabilidad":{"periosidad":"","nPagosMensuales":"","admin":"","observacionesCotizacion":"","valorAseguradoVida":0,"primaVidaITP":0,"fechaCotizacionVida":"","resultadoGestion":""},"Declaración de Asegurabilidad":{"actividadesLicita":false,"procesoPenal":false,"frecuenciaDeportesAltoRiesgo":"","peso":"","estatura":"","imcCalculado":"","observacionImc":"","estadoAsegurabilidad":"","hipertensionArterial":false,"colesterolTrigliceridosElevados":false,"diabetes":false,"enfermedadCoronariaInfarto":false,"insuficienciaRenal":false,"cancerTumores":false,"derrameTrombosisCerebral":false,"enfermedadesPsicologicasPsiquiatricas":false,"sidaVih":false,"pruebaVihPositiva":false,"secuelasEnfermedadAccidente":"","diagnosticoEnfermedadFracturas":"","tratamientoAlcoholAlucinogenos":false,"cirugiaProgramada":false,"autorizacionInformacionMedica":false,"fechaAsegurabilidad":""},"Autorización de Descuento Débito":{"canalDescuento":"","tipoDeCuenta":"","entidadBancaria":"","numeroCuentaDebito":"","fechaVencimientoTC":"","numeroCuotasTC":"","autorizaDescuentoAutomatico":false,"entiendeMoraPrima":false,"valorPrima":0,"fechaAutorizacionDebito":"","observacionesCierre":""},"Beneficiarios y Autorizaciones":{"nombreBeneficiario1":"","apellidoBeneficiario1":"","parentescoBeneficiario1":"","designacionBeneficiario1":0,"nombreBeneficiario2":"","apellidoBeneficiario2":"","parentescoBeneficiario2":"","designacionBeneficiario2":0,"nombreBeneficiario3":"","apellidoBeneficiario3":"","parentescoBeneficiario3":"","designacionBeneficiario3":0,"beneficiariosRegistrados":false,"fechaRegistroBeneficiarios":""},"Emisión de Póliza":{"numeroCertificadoFinal":"","resultadoEmision":"","fechaVigenciaPoliza":"","polizaPrincipal":"","periodicidadPagoPoliza":"MENSUAL","confirmacionVentaSegurosBolivar":false,"liderClavo":"","certificado":"75272","observacionesEmision":"","fechaEmisionPoliza":"","estadoPoliza":"","numeroContrato":""}}
A71: 45888.382 | B71: 11703992 | C71: {"poliza":"10754","nombre":"CARMEN NORFARY RIVERA CARMEN","id":"31483675","telefono":"3026815222","correo":"emily.tatis1025@gmail.com","ciudad":"CALI","direccion":"CR 14#49 15","tipoInmueble":"Comercial","canon":"700000","fechaRadicacion":"16/8/2025","fechaAprobacion":"18/8/2025","estado":"APROBADA","tipoDocumento":"CC"} | D71: luisa.herrera@segurosbolivar.com | E71: Declaración de Asegurabilidad | F71: DESISTIDO | G71: Seguro de Vida | H71: [{"fecha":"2025-08-19 09:48:05","usuario":"luisa.herrera@segurosbolivar.com","accionRealizada":"DESISTIDO","leadEtapaActual":"Declaración de Asegurabilidad","productosGestion":"Seguro de Vida","observaciones":"No lo ve necesario"}] | I71: 45888.408 | J71: {"Contacto Inicial y Datos":{"nomAgt":"","emailCte":"","autorizaDatosPersonales":false,"fechaNacimiento":"1978-05-12","tipoDocumento":"CC","observacionesPresentacion":"pero informa que mas adelante llamara para tomar el seguro ya que no esta interesada en estos momentos ","genero":"Femenino","resultadoGestion":"Cliente acepta tratamiento de datos personales","accion":"Cliente acepta tratamiento de datos personales","usuario":"luisa.herrera@segurosbolivar.com"},"Cotización y Pre-Asegurabilidad":{"periosidad":"","nPagosMensuales":"","admin":"","observacionesCotizacion":"","valorAseguradoVida":0,"primaVidaITP":0,"fechaCotizacionVida":"","resultadoGestion":""},"Declaración de Asegurabilidad":{"actividadesLicita":false,"procesoPenal":false,"frecuenciaDeportesAltoRiesgo":"","peso":"","estatura":"","imcCalculado":"","observacionImc":"","estadoAsegurabilidad":"","hipertensionArterial":false,"colesterolTrigliceridosElevados":false,"diabetes":false,"enfermedadCoronariaInfarto":false,"insuficienciaRenal":false,"cancerTumores":false,"derrameTrombosisCerebral":false,"enfermedadesPsicologicasPsiquiatricas":false,"sidaVih":false,"pruebaVihPositiva":false,"secuelasEnfermedadAccidente":"","diagnosticoEnfermedadFracturas":"","tratamientoAlcoholAlucinogenos":false,"cirugiaProgramada":false,"autorizacionInformacionMedica":false,"fechaAsegurabilidad":"","resultadoGestion":"Cliente no interesado","observacionesNegociacion":"no esta interesado","accion":"Cliente no interesado","usuario":"luisa.herrera@segurosbolivar.com"},"Autorización de Descuento Débito":{"canalDescuento":"","tipoDeCuenta":"","entidadBancaria":"","numeroCuentaDebito":"","fechaVencimientoTC":"","numeroCuotasTC":"","autorizaDescuentoAutomatico":false,"entiendeMoraPrima":false,"valorPrima":0,"fechaAutorizacionDebito":"","observacionesCierre":""},"Beneficiarios y Autorizaciones":{"nombreBeneficiario1":"","apellidoBeneficiario1":"","parentescoBeneficiario1":"","designacionBeneficiario1":0,"nombreBeneficiario2":"","apellidoBeneficiario2":"","parentescoBeneficiario2":"","designacionBeneficiario2":0,"nombreBeneficiario3":"","apellidoBeneficiario3":"","parentescoBeneficiario3":"","designacionBeneficiario3":0,"beneficiariosRegistrados":false,"fechaRegistroBeneficiarios":""},"Emisión de Póliza":{"numeroCertificadoFinal":"","resultadoEmision":"","fechaVigenciaPoliza":"","polizaPrincipal":"","periodicidadPagoPoliza":"MENSUAL","confirmacionVentaSegurosBolivar":false,"liderClavo":"","certificado":"75272","observacionesEmision":"","fechaEmisionPoliza":"","estadoPoliza":"","numeroContrato":""}}
A72: 45888.382 | B72: 11704246 | C72: {"poliza":"12364","nombre":"LEIDY JHOHANA DELGADO MIRANDA","id":"1116914853","telefono":"3144052281","correo":"leidelgado@gmail.com","ciudad":"ARMENIA","direccion":"CRA 15 # 8 43","tipoInmueble":"Vivienda","canon":"720000","fechaRadicacion":"16/8/2025","fechaAprobacion":"18/8/2025","estado":"APROBADA","tipoDocumento":"CC"} | D72: luisa.herrera@segurosbolivar.com | E72: Contacto Inicial y Datos | F72: DESISTIDO | G72: Seguro de Vida | H72: [{"fecha":"2025-08-19 09:53:36","usuario":"luisa.herrera@segurosbolivar.com","accionRealizada":"DESISTIDO","leadEtapaActual":"Contacto Inicial y Datos","productosGestion":"Seguro de Vida","observaciones":"No Contesta"}] | I72: 45888.412 | J72: {"Contacto Inicial y Datos":{"nomAgt":"","emailCte":"","autorizaDatosPersonales":false,"fechaNacimiento":"","tipoDocumento":"CC","observacionesPresentacion":"2 intentos sin respuesta ","genero":"Femenino","resultadoGestion":"Cliente ilocalizable","accion":"Cliente ilocalizable","usuario":"luisa.herrera@segurosbolivar.com"},"Cotización y Pre-Asegurabilidad":{"periosidad":"","nPagosMensuales":"","admin":"","observacionesCotizacion":"","valorAseguradoVida":0,"primaVidaITP":0,"fechaCotizacionVida":""},"Declaración de Asegurabilidad":{"actividadesLicita":false,"procesoPenal":false,"frecuenciaDeportesAltoRiesgo":"","peso":"","estatura":"","imcCalculado":"","observacionImc":"","estadoAsegurabilidad":"","hipertensionArterial":false,"colesterolTrigliceridosElevados":false,"diabetes":false,"enfermedadCoronariaInfarto":false,"insuficienciaRenal":false,"cancerTumores":false,"derrameTrombosisCerebral":false,"enfermedadesPsicologicasPsiquiatricas":false,"sidaVih":false,"pruebaVihPositiva":false,"secuelasEnfermedadAccidente":"","diagnosticoEnfermedadFracturas":"","tratamientoAlcoholAlucinogenos":false,"cirugiaProgramada":false,"autorizacionInformacionMedica":false,"fechaAsegurabilidad":""},"Autorización de Descuento Débito":{"canalDescuento":"","tipoDeCuenta":"","entidadBancaria":"","numeroCuentaDebito":"","fechaVencimientoTC":"","numeroCuotasTC":"","autorizaDescuentoAutomatico":false,"entiendeMoraPrima":false,"valorPrima":0,"fechaAutorizacionDebito":"","observacionesCierre":""},"Beneficiarios y Autorizaciones":{"nombreBeneficiario1":"","apellidoBeneficiario1":"","parentescoBeneficiario1":"","designacionBeneficiario1":0,"nombreBeneficiario2":"","apellidoBeneficiario2":"","parentescoBeneficiario2":"","designacionBeneficiario2":0,"nombreBeneficiario3":"","apellidoBeneficiario3":"","parentescoBeneficiario3":"","designacionBeneficiario3":0,"beneficiariosRegistrados":false,"fechaRegistroBeneficiarios":""},"Emisión de Póliza":{"numeroCertificadoFinal":"","resultadoEmision":"","fechaVigenciaPoliza":"","polizaPrincipal":"","periodicidadPagoPoliza":"MENSUAL","confirmacionVentaSegurosBolivar":false,"liderClavo":"","certificado":"75272","observacionesEmision":"","fechaEmisionPoliza":"","estadoPoliza":"","numeroContrato":""}}
A73: 45888.382 | B73: 11704474 | C73: {"poliza":"10840","nombre":"JOHAN FERNANDO CABAL GUERRERO","id":"1113682585","telefono":"3173816118","correo":"fercho-96@live.com","ciudad":"PALMIRA","direccion":"CL 31 # 22 07","tipoInmueble":"Vivienda","canon":"80000","fechaRadicacion":"17/8/2025","fechaAprobacion":"18/8/2025","estado":"APROBADA","tipoDocumento":"CC"} | D73: luisa.herrera@segurosbolivar.com | E73: Contacto Inicial y Datos | F73: DESISTIDO | G73: Seguro de Vida | H73: [{"fecha":"2025-08-19 09:56:18","usuario":"luisa.herrera@segurosbolivar.com","accionRealizada":"DESISTIDO","leadEtapaActual":"Contacto Inicial y Datos","productosGestion":"Seguro de Vida","observaciones":"Contesta y Cuelga Inmediatamente"}] | I73: 45888.414 | J73: {"Contacto Inicial y Datos":{"nomAgt":"","emailCte":"","autorizaDatosPersonales":false,"fechaNacimiento":"","tipoDocumento":"CC","observacionesPresentacion":"me cuelga la llamada al momento de preguntar su nombre ","genero":"Masculino","resultadoGestion":"Cliente ilocalizable","accion":"Cliente ilocalizable","usuario":"luisa.herrera@segurosbolivar.com"},"Cotización y Pre-Asegurabilidad":{"periosidad":"","nPagosMensuales":"","admin":"","observacionesCotizacion":"","valorAseguradoVida":0,"primaVidaITP":0,"fechaCotizacionVida":""},"Declaración de Asegurabilidad":{"actividadesLicita":false,"procesoPenal":false,"frecuenciaDeportesAltoRiesgo":"","peso":"","estatura":"","imcCalculado":"","observacionImc":"","estadoAsegurabilidad":"","hipertensionArterial":false,"colesterolTrigliceridosElevados":false,"diabetes":false,"enfermedadCoronariaInfarto":false,"insuficienciaRenal":false,"cancerTumores":false,"derrameTrombosisCerebral":false,"enfermedadesPsicologicasPsiquiatricas":false,"sidaVih":false,"pruebaVihPositiva":false,"secuelasEnfermedadAccidente":"","diagnosticoEnfermedadFracturas":"","tratamientoAlcoholAlucinogenos":false,"cirugiaProgramada":false,"autorizacionInformacionMedica":false,"fechaAsegurabilidad":""},"Autorización de Descuento Débito":{"canalDescuento":"","tipoDeCuenta":"","entidadBancaria":"","numeroCuentaDebito":"","fechaVencimientoTC":"","numeroCuotasTC":"","autorizaDescuentoAutomatico":false,"entiendeMoraPrima":false,"valorPrima":0,"fechaAutorizacionDebito":"","observacionesCierre":""},"Beneficiarios y Autorizaciones":{"nombreBeneficiario1":"","apellidoBeneficiario1":"","parentescoBeneficiario1":"","designacionBeneficiario1":0,"nombreBeneficiario2":"","apellidoBeneficiario2":"","parentescoBeneficiario2":"","designacionBeneficiario2":0,"nombreBeneficiario3":"","apellidoBeneficiario3":"","parentescoBeneficiario3":"","designacionBeneficiario3":0,"beneficiariosRegistrados":false,"fechaRegistroBeneficiarios":""},"Emisión de Póliza":{"numeroCertificadoFinal":"","resultadoEmision":"","fechaVigenciaPoliza":"","polizaPrincipal":"","periodicidadPagoPoliza":"MENSUAL","confirmacionVentaSegurosBolivar":false,"liderClavo":"","certificado":"75272","observacionesEmision":"","fechaEmisionPoliza":"","estadoPoliza":"","numeroContrato":""}}
A74: 45888.382 | B74: 11704657 | C74: {"poliza":"13509","nombre":"DUVAN ANDRES OGAZA HERRERA","id":"1074008892","telefono":"3115773718","correo":"dubanogaza1717@gmail.com","ciudad":"MEDELLIN","direccion":"C SU DIRECCION CRA 69 N O 36","tipoInmueble":"Vivienda","canon":"630000","fechaRadicacion":"18/8/2025","fechaAprobacion":"18/8/2025","estado":"APROBADA","tipoDocumento":"CC"} | D74: luisa.herrera@segurosbolivar.com | E74: Contacto Inicial y Datos | F74: DESISTIDO | G74: Seguro de Vida | H74: [{"fecha":"2025-08-19 10:12:39","usuario":"luisa.herrera@segurosbolivar.com","accionRealizada":"DESISTIDO","leadEtapaActual":"Contacto Inicial y Datos","productosGestion":"Seguro de Vida","observaciones":"Evita asumir más gastos"}] | I74: 45888.425 | J74: {"Contacto Inicial y Datos":{"nomAgt":"","emailCte":"","autorizaDatosPersonales":false,"fechaNacimiento":"","tipoDocumento":"CC","observacionesPresentacion":"no esta interesado por gastos adicionales ","genero":"Masculino","resultadoGestion":"Cliente no interesado","accion":"Cliente no interesado","usuario":"luisa.herrera@segurosbolivar.com"},"Cotización y Pre-Asegurabilidad":{"periosidad":"","nPagosMensuales":"","admin":"","observacionesCotizacion":"","valorAseguradoVida":0,"primaVidaITP":0,"fechaCotizacionVida":""},"Declaración de Asegurabilidad":{"actividadesLicita":false,"procesoPenal":false,"frecuenciaDeportesAltoRiesgo":"","peso":"","estatura":"","imcCalculado":"","observacionImc":"","estadoAsegurabilidad":"","hipertensionArterial":false,"colesterolTrigliceridosElevados":false,"diabetes":false,"enfermedadCoronariaInfarto":false,"insuficienciaRenal":false,"cancerTumores":false,"derrameTrombosisCerebral":false,"enfermedadesPsicologicasPsiquiatricas":false,"sidaVih":false,"pruebaVihPositiva":false,"secuelasEnfermedadAccidente":"","diagnosticoEnfermedadFracturas":"","tratamientoAlcoholAlucinogenos":false,"cirugiaProgramada":false,"autorizacionInformacionMedica":false,"fechaAsegurabilidad":""},"Autorización de Descuento Débito":{"canalDescuento":"","tipoDeCuenta":"","entidadBancaria":"","numeroCuentaDebito":"","fechaVencimientoTC":"","numeroCuotasTC":"","autorizaDescuentoAutomatico":false,"entiendeMoraPrima":false,"valorPrima":0,"fechaAutorizacionDebito":"","observacionesCierre":""},"Beneficiarios y Autorizaciones":{"nombreBeneficiario1":"","apellidoBeneficiario1":"","parentescoBeneficiario1":"","designacionBeneficiario1":0,"nombreBeneficiario2":"","apellidoBeneficiario2":"","parentescoBeneficiario2":"","designacionBeneficiario2":0,"nombreBeneficiario3":"","apellidoBeneficiario3":"","parentescoBeneficiario3":"","designacionBeneficiario3":0,"beneficiariosRegistrados":false,"fechaRegistroBeneficiarios":""},"Emisión de Póliza":{"numeroCertificadoFinal":"","resultadoEmision":"","fechaVigenciaPoliza":"","polizaPrincipal":"","periodicidadPagoPoliza":"MENSUAL","confirmacionVentaSegurosBolivar":false,"liderClavo":"","certificado":"75272","observacionesEmision":"","fechaEmisionPoliza":"","estadoPoliza":"","numeroContrato":""}}
A75: 45888.382 | B75: 11704304 | C75: {"poliza":"999","nombre":"GOMEZ ALEJANDRO BETANCUR GOMEZ","id":"94531481","telefono":"3173602224","correo":"alejandrobetancurgomez@gmail.com","ciudad":"CANDELARIA","direccion":"CRA 31 OE 14 20","tipoInmueble":"Vivienda","canon":"550000","fechaRadicacion":"17/8/2025","fechaAprobacion":"17/8/2025","estado":"APROBADA","tipoDocumento":"CC"} | D75: luisa.herrera@segurosbolivar.com | E75: Contacto Inicial y Datos | F75: DESISTIDO | G75: Seguro de Vida | H75: [{"fecha":"2025-08-19 10:17:44","usuario":"luisa.herrera@segurosbolivar.com","accionRealizada":"DESISTIDO","leadEtapaActual":"Contacto Inicial y Datos","productosGestion":"Seguro de Vida","observaciones":"Cliente sin señal"}] | I75: 45888.429 | J75: {"Contacto Inicial y Datos":{"nomAgt":"","emailCte":"","autorizaDatosPersonales":false,"fechaNacimiento":"","tipoDocumento":"","observacionesPresentacion":"cliente no disponible informa la operadora ","genero":"","resultadoGestion":"Cliente ilocalizable","accion":"Cliente ilocalizable","usuario":"luisa.herrera@segurosbolivar.com"},"Cotización y Pre-Asegurabilidad":{"periosidad":"","nPagosMensuales":"","admin":"","observacionesCotizacion":"","valorAseguradoVida":0,"primaVidaITP":0,"fechaCotizacionVida":""},"Declaración de Asegurabilidad":{"actividadesLicita":false,"procesoPenal":false,"frecuenciaDeportesAltoRiesgo":"","peso":"","estatura":"","imcCalculado":"","observacionImc":"","estadoAsegurabilidad":"","hipertensionArterial":false,"colesterolTrigliceridosElevados":false,"diabetes":false,"enfermedadCoronariaInfarto":false,"insuficienciaRenal":false,"cancerTumores":false,"derrameTrombosisCerebral":false,"enfermedadesPsicologicasPsiquiatricas":false,"sidaVih":false,"pruebaVihPositiva":false,"secuelasEnfermedadAccidente":"","diagnosticoEnfermedadFracturas":"","tratamientoAlcoholAlucinogenos":false,"cirugiaProgramada":false,"autorizacionInformacionMedica":false,"fechaAsegurabilidad":""},"Autorización de Descuento Débito":{"canalDescuento":"","tipoDeCuenta":"","entidadBancaria":"","numeroCuentaDebito":"","fechaVencimientoTC":"","numeroCuotasTC":"","autorizaDescuentoAutomatico":false,"entiendeMoraPrima":false,"valorPrima":0,"fechaAutorizacionDebito":"","observacionesCierre":""},"Beneficiarios y Autorizaciones":{"nombreBeneficiario1":"","apellidoBeneficiario1":"","parentescoBeneficiario1":"","designacionBeneficiario1":0,"nombreBeneficiario2":"","apellidoBeneficiario2":"","parentescoBeneficiario2":"","designacionBeneficiario2":0,"nombreBeneficiario3":"","apellidoBeneficiario3":"","parentescoBeneficiario3":"","designacionBeneficiario3":0,"beneficiariosRegistrados":false,"fechaRegistroBeneficiarios":""},"Emisión de Póliza":{"numeroCertificadoFinal":"","resultadoEmision":"","fechaVigenciaPoliza":"","polizaPrincipal":"","periodicidadPagoPoliza":"MENSUAL","confirmacionVentaSegurosBolivar":false,"liderClavo":"","certificado":"75272","observacionesEmision":"","fechaEmisionPoliza":"","estadoPoliza":"","numeroContrato":""}}
A76: 45888.382 | B76: 11704384 | C76: {"poliza":"2070","nombre":"FUTANICO GLORIA MILLAN FUTANICO","id":"41620288","telefono":"3127600187","correo":"juancorchuelo703@gmail.com","ciudad":"SOACHA","direccion":"CL 17#24B 17 TORRE 2 AP 217","tipoInmueble":"Vivienda","canon":"720000","fechaRadicacion":"17/8/2025","fechaAprobacion":"17/8/2025","estado":"APROBADA","tipoDocumento":"CC"} | D76: luisa.herrera@segurosbolivar.com | E76: Contacto Inicial y Datos | F76: DESISTIDO | G76: Seguro de Vida | H76: [{"fecha":"2025-08-19 10:26:42","usuario":"luisa.herrera@segurosbolivar.com","accionRealizada":"DESISTIDO","leadEtapaActual":"Contacto Inicial y Datos","productosGestion":"Seguro de Vida","observaciones":"Edad no asegurable"}] | I76: 45888.435 | J76: {"Contacto Inicial y Datos":{"nomAgt":"","emailCte":"","autorizaDatosPersonales":false,"fechaNacimiento":"","tipoDocumento":"","observacionesPresentacion":"por edad 71 años fuera de rango edad ","genero":"","resultadoGestion":"No Asegurable","accion":"No Asegurable","usuario":"luisa.herrera@segurosbolivar.com"},"Cotización y Pre-Asegurabilidad":{"periosidad":"","nPagosMensuales":"","admin":"","observacionesCotizacion":"","valorAseguradoVida":0,"primaVidaITP":0,"fechaCotizacionVida":""},"Declaración de Asegurabilidad":{"actividadesLicita":false,"procesoPenal":false,"frecuenciaDeportesAltoRiesgo":"","peso":"","estatura":"","imcCalculado":"","observacionImc":"","estadoAsegurabilidad":"","hipertensionArterial":false,"colesterolTrigliceridosElevados":false,"diabetes":false,"enfermedadCoronariaInfarto":false,"insuficienciaRenal":false,"cancerTumores":false,"derrameTrombosisCerebral":false,"enfermedadesPsicologicasPsiquiatricas":false,"sidaVih":false,"pruebaVihPositiva":false,"secuelasEnfermedadAccidente":"","diagnosticoEnfermedadFracturas":"","tratamientoAlcoholAlucinogenos":false,"cirugiaProgramada":false,"autorizacionInformacionMedica":false,"fechaAsegurabilidad":""},"Autorización de Descuento Débito":{"canalDescuento":"","tipoDeCuenta":"","entidadBancaria":"","numeroCuentaDebito":"","fechaVencimientoTC":"","numeroCuotasTC":"","autorizaDescuentoAutomatico":false,"entiendeMoraPrima":false,"valorPrima":0,"fechaAutorizacionDebito":"","observacionesCierre":""},"Beneficiarios y Autorizaciones":{"nombreBeneficiario1":"","apellidoBeneficiario1":"","parentescoBeneficiario1":"","designacionBeneficiario1":0,"nombreBeneficiario2":"","apellidoBeneficiario2":"","parentescoBeneficiario2":"","designacionBeneficiario2":0,"nombreBeneficiario3":"","apellidoBeneficiario3":"","parentescoBeneficiario3":"","designacionBeneficiario3":0,"beneficiariosRegistrados":false,"fechaRegistroBeneficiarios":""},"Emisión de Póliza":{"numeroCertificadoFinal":"","resultadoEmision":"","fechaVigenciaPoliza":"","polizaPrincipal":"","periodicidadPagoPoliza":"MENSUAL","confirmacionVentaSegurosBolivar":false,"liderClavo":"","certificado":"75272","observacionesEmision":"","fechaEmisionPoliza":"","estadoPoliza":"","numeroContrato":""}}
A77: 45888.382 | B77: 11704414 | C77: {"poliza":"12408","nombre":"LAURA MICHELL OSPINA CASTAÑO","id":"1193136051","telefono":"3142371088","correo":"lmichell126@hotmail.com","ciudad":"ARMENIA","direccion":"CRA 56 52 50 BLQ 1 AP 508","tipoInmueble":"Vivienda","canon":"600000","fechaRadicacion":"17/8/2025","fechaAprobacion":"17/8/2025","estado":"APROBADA","tipoDocumento":"CC"} | D77: luisa.herrera@segurosbolivar.com | E77: Contacto Inicial y Datos | F77: DESISTIDO | G77: Seguro de Vida | H77: [{"fecha":"2025-08-19 10:31:12","usuario":"luisa.herrera@segurosbolivar.com","accionRealizada":"DESISTIDO","leadEtapaActual":"Contacto Inicial y Datos","productosGestion":"Seguro de Vida","observaciones":"No le interesa"}] | I77: 45888.438 | J77: {"Contacto Inicial y Datos":{"nomAgt":"","emailCte":"","autorizaDatosPersonales":false,"fechaNacimiento":"","tipoDocumento":"CC","observacionesPresentacion":"no esta interesada por momento ","genero":"Femenino","resultadoGestion":"Cliente no interesado","accion":"Cliente no interesado","usuario":"luisa.herrera@segurosbolivar.com"},"Cotización y Pre-Asegurabilidad":{"periosidad":"","nPagosMensuales":"","admin":"","observacionesCotizacion":"","valorAseguradoVida":0,"primaVidaITP":0,"fechaCotizacionVida":""},"Declaración de Asegurabilidad":{"actividadesLicita":false,"procesoPenal":false,"frecuenciaDeportesAltoRiesgo":"","peso":"","estatura":"","imcCalculado":"","observacionImc":"","estadoAsegurabilidad":"","hipertensionArterial":false,"colesterolTrigliceridosElevados":false,"diabetes":false,"enfermedadCoronariaInfarto":false,"insuficienciaRenal":false,"cancerTumores":false,"derrameTrombosisCerebral":false,"enfermedadesPsicologicasPsiquiatricas":false,"sidaVih":false,"pruebaVihPositiva":false,"secuelasEnfermedadAccidente":"","diagnosticoEnfermedadFracturas":"","tratamientoAlcoholAlucinogenos":false,"cirugiaProgramada":false,"autorizacionInformacionMedica":false,"fechaAsegurabilidad":""},"Autorización de Descuento Débito":{"canalDescuento":"","tipoDeCuenta":"","entidadBancaria":"","numeroCuentaDebito":"","fechaVencimientoTC":"","numeroCuotasTC":"","autorizaDescuentoAutomatico":false,"entiendeMoraPrima":false,"valorPrima":0,"fechaAutorizacionDebito":"","observacionesCierre":""},"Beneficiarios y Autorizaciones":{"nombreBeneficiario1":"","apellidoBeneficiario1":"","parentescoBeneficiario1":"","designacionBeneficiario1":0,"nombreBeneficiario2":"","apellidoBeneficiario2":"","parentescoBeneficiario2":"","designacionBeneficiario2":0,"nombreBeneficiario3":"","apellidoBeneficiario3":"","parentescoBeneficiario3":"","designacionBeneficiario3":0,"beneficiariosRegistrados":false,"fechaRegistroBeneficiarios":""},"Emisión de Póliza":{"numeroCertificadoFinal":"","resultadoEmision":"","fechaVigenciaPoliza":"","polizaPrincipal":"","periodicidadPagoPoliza":"MENSUAL","confirmacionVentaSegurosBolivar":false,"liderClavo":"","certificado":"75272","observacionesEmision":"","fechaEmisionPoliza":"","estadoPoliza":"","numeroContrato":""}}
A78: 45888.414 | B78: 11681592 | C78: {"poliza":"13653","nombre":"ANGIE NAHASLY NARANJO CARTAGENA","id":"1007613982","telefono":"3118723132","correo":"nahasly21@gmail.com","ciudad":"ENVIGADO","direccion":"CL 33 B SUR 42 24","tipoInmueble":"Comercial","canon":"1980000","fechaRadicacion":"28/7/2025","fechaAprobacion":"19/8/2025","estado":"APROBADA","tipoDocumento":"CC"} | D78: maria.gaitan@proyectivaseguros.com | E78: Cotización y Pre-Asegurabilidad | F78: DESISTIDO | G78: Seguro de Vida | H78: [{"fecha":"2025-08-19 10:54:50","usuario":"maria.gaitan@segurosbolivar.com","accionRealizada":"DESISTIDO","leadEtapaActual":"Cotización y Pre-Asegurabilidad","productosGestion":"Seguro de Vida","observaciones":"No lo ve necesario"}] | I78: 45888.455 | J78: {"Contacto Inicial y Datos":{"nomAgt":"maria.gaitan@segurosbolivar.com","emailCte":"","autorizaDatosPersonales":true,"fechaNacimiento":"2000-09-21","tipoDocumento":"CC","observacionesPresentacion":"OK","genero":"Femenino","resultadoGestion":"Cliente acepta tratamiento de datos personales","accion":"Cliente acepta tratamiento de datos personales","usuario":"maria.gaitan@segurosbolivar.com"},"Cotización y Pre-Asegurabilidad":{"periosidad":"Mensual","nPagosMensuales":"12","admin":"","observacionesCotizacion":"SOLO DICE QUE NO LO NECESITA","valorAseguradoVida":23760000,"primaVidaITP":24354.000000000004,"fechaCotizacionVida":"19/8/2025","resultadoGestion":"Cliente no interesado","accion":"Cliente no interesado","usuario":"maria.gaitan@segurosbolivar.com"},"Declaración de Asegurabilidad":{"actividadesLicita":false,"procesoPenal":false,"frecuenciaDeportesAltoRiesgo":"","peso":"","estatura":"","imcCalculado":"","observacionImc":"","estadoAsegurabilidad":"","hipertensionArterial":false,"colesterolTrigliceridosElevados":false,"diabetes":false,"enfermedadCoronariaInfarto":false,"insuficienciaRenal":false,"cancerTumores":false,"derrameTrombosisCerebral":false,"enfermedadesPsicologicasPsiquiatricas":false,"sidaVih":false,"pruebaVihPositiva":false,"secuelasEnfermedadAccidente":"","diagnosticoEnfermedadFracturas":"","tratamientoAlcoholAlucinogenos":false,"cirugiaProgramada":false,"autorizacionInformacionMedica":false,"fechaAsegurabilidad":""},"Autorización de Descuento Débito":{"canalDescuento":"","tipoDeCuenta":"","entidadBancaria":"","numeroCuentaDebito":"","fechaVencimientoTC":"","numeroCuotasTC":"","autorizaDescuentoAutomatico":false,"entiendeMoraPrima":false,"valorPrima":0,"fechaAutorizacionDebito":"","observacionesCierre":""},"Beneficiarios y Autorizaciones":{"nombreBeneficiario1":"","apellidoBeneficiario1":"","parentescoBeneficiario1":"","designacionBeneficiario1":0,"nombreBeneficiario2":"","apellidoBeneficiario2":"","parentescoBeneficiario2":"","designacionBeneficiario2":0,"nombreBeneficiario3":"","apellidoBeneficiario3":"","parentescoBeneficiario3":"","designacionBeneficiario3":0,"beneficiariosRegistrados":false,"fechaRegistroBeneficiarios":""},"Emisión de Póliza":{"numeroCertificadoFinal":"","resultadoEmision":"","fechaVigenciaPoliza":"","polizaPrincipal":"","periodicidadPagoPoliza":"MENSUAL","confirmacionVentaSegurosBolivar":false,"liderClavo":"","certificado":"75272","observacionesEmision":"","fechaEmisionPoliza":"","estadoPoliza":"","numeroContrato":""}}
... A289: 45888.588 | B289: 11704584 | C289: {"poliza":"10160","nombre":"SARRIA ANGELICA MORENO SARRIA","id":"1144171595","telefono":"3013551364","correo":"angeli-k2208@hotmail.com","ciudad":"CALI","direccion":"CL 20 7 08","tipoInmueble":"Comercial","canon":"750000","fechaRadicacion":"18/8/2025","fechaAprobacion":"19/8/2025","estado":"APROBADA","tipoDocumento":"CC"} | D289: maria.gaitan@proyectivaseguros.com | E289: Declaración de Asegurabilidad | F289: DESISTIDO | G289: Seguro de Vida | H289: [{"fecha":"2025-08-22 09:59:57","usuario":"maria.gaitan@segurosbolivar.com","accionRealizada":"DESISTIDO","leadEtapaActual":"Declaración de Asegurabilidad","productosGestion":"Seguro de Vida","observaciones":"Declaración"}] | I289: 45891.417 | J289: {"Contacto Inicial y Datos":{"nomAgt":"maria.gaitan@segurosbolivar.com","emailCte":"","autorizaDatosPersonales":true,"fechaNacimiento":"2000-08-22","tipoDocumento":"CC","observacionesPresentacion":"ok","genero":"Femenino","resultadoGestion":"Cliente acepta tratamiento de datos personales","accion":"Cliente acepta tratamiento de datos personales","usuario":"maria.gaitan@segurosbolivar.com"},"Cotización y Pre-Asegurabilidad":{"periosidad":"Mensual","nPagosMensuales":"12","admin":"","observacionesCotizacion":"ok","valorAseguradoVida":10020000,"primaVidaITP":10270.5,"fechaCotizacionVida":"22/8/2025","resultadoGestion":"Cliente acepta Cotización","accion":"Cliente acepta Cotización","usuario":"maria.gaitan@segurosbolivar.com"},"Declaración de Asegurabilidad":{"actividadesLicita":true,"procesoPenal":true,"frecuenciaDeportesAltoRiesgo":"0","peso":"50","estatura":"150","imcCalculado":"22.22","observacionImc":"pok","estadoAsegurabilidad":"ASEGURABLE","hipertensionArterial":false,"colesterolTrigliceridosElevados":false,"diabetes":false,"enfermedadCoronariaInfarto":false,"insuficienciaRenal":false,"cancerTumores":false,"derrameTrombosisCerebral":false,"enfermedadesPsicologicasPsiquiatricas":false,"sidaVih":false,"pruebaVihPositiva":false,"secuelasEnfermedadAccidente":false,"diagnosticoEnfermedadFracturas":false,"tratamientoAlcoholAlucinogenos":false,"cirugiaProgramada":false,"autorizacionInformacionMedica":true,"fechaAsegurabilidad":"22/8/2025","sarlaft":false,"resultadoGestion":"Venta Cancelada","observacionesNegociacion":"ok","accion":"Venta Cancelada","usuario":"maria.gaitan@segurosbolivar.com"},"Autorización de Descuento Débito":{"canalDescuento":"","tipoDeCuenta":"","entidadBancaria":"","numeroCuentaDebito":"","fechaVencimientoTC":"","numeroCuotasTC":"","autorizaDescuentoAutomatico":false,"entiendeMoraPrima":false,"valorPrima":0,"fechaAutorizacionDebito":"","observacionesCierre":""},"Beneficiarios y Autorizaciones":{"nombreBeneficiario1":"","apellidoBeneficiario1":"","parentescoBeneficiario1":"","designacionBeneficiario1":0,"nombreBeneficiario2":"","apellidoBeneficiario2":"","parentescoBeneficiario2":"","designacionBeneficiario2":0,"nombreBeneficiario3":"","apellidoBeneficiario3":"","parentescoBeneficiario3":"","designacionBeneficiario3":0,"beneficiariosRegistrados":false,"fechaRegistroBeneficiarios":""},"Emisión de Póliza":{"numeroCertificadoFinal":"","resultadoEmision":"","fechaVigenciaPoliza":"","polizaPrincipal":"","periodicidadPagoPoliza":"MENSUAL","confirmacionVentaSegurosBolivar":false,"liderClavo":"","certificado":"75272","observacionesEmision":"","fechaEmisionPoliza":"","estadoPoliza":"","numeroContrato":""}}
A290: 45888.588 | B290: 11704601 | C290: {"poliza":"429","nombre":"MADERA AVIMAEL HERNÁNDEZ MADERA","id":"1003306606","telefono":"3136848818","correo":"maderaavi@gmail.com","ciudad":"BOGOTA, D.C.","direccion":"CL 17 C # 135 51 TO 1 AP 403","tipoInmueble":"Vivienda","canon":"1200000","fechaRadicacion":"18/8/2025","fechaAprobacion":"19/8/2025","estado":"APROBADA","tipoDocumento":"CC"} | D290: angie.ariza.roncancio@proyectivaseguros.com | E290: Contacto Inicial y Datos | F290: DESISTIDO | G290: Seguro de Desempleo | H290: [{"fecha":"2025-08-29 08:58:29","usuario":"angie.ariza.roncancio@segurosbolivar.com","accionRealizada":"DESISTIDO","leadEtapaActual":"Contacto Inicial y Datos","productosGestion":"Seguro de Desempleo","observaciones":"No Contesta"}] | I290: 45898.374 | K290: {"Contacto Inicial y Datos":{"nomAgt":"","emailCte":"","autorizaDatosPersonales":false,"tipoVinculacion":"","nombreEmpleador":"","confirmaCanon":"","canonArrendamiento":0,"costoProteccionMensual":0,"medioDebito":"","continuarVentaIndependiente":"","observacionesContacto":"","fechaNacimiento":"","genero":"","tipoDocumento":"","resultadoGestion":"Cliente no contesta","observacionesPresentacion":"No contesta ","accion":"Cliente no contesta","usuario":"angie.ariza.roncancio@segurosbolivar.com"},"Cotización y Pre-Asegurabilidad":{"valorAseguradoDesempleo":0,"primaDesempleo":0,"fechaCotizacionDesempleo":"","autorizaDatosInd":false,"ocupacionLicitaInd":false,"procesadoPenalInd":false,"otraOcupacionInd":"","otraOcupacionIndText":"","observacionesCotizacion":""},"Declaración de Asegurabilidad":{"autorizaInfoGeneral":false,"observacionesNegociacion":""},"Autorización de Descuento Débito":{"canalDescuento":"","tipoDeCuenta":"","entidadBancaria":"","numeroCuentaDebito":"","fechaVencimientoTC":"","numeroCuotasTC":"","valorPrima":0,"autorizaDescuentoAutomatico":false,"entiendeMoraPrima":false,"fechaAutorizacionDebito":"","observacionesCierre":""},"Beneficiarios y Autorizaciones":{"continuarReiteracionInd":"","observacionesRectificacion":"","fechaRectificacion":""},"Emisión de Póliza":{"confirmacionVentaActivacion":"","fechaActivacionPoliza":"","seccion":"","producto":"","polizaPrincipal":"","tomador":"","nitLibertador":"","tipoEnvio":"","periodicidadPagoPoliza":"MENSUAL","formaCobroPoliza":"AUTOMÁTICO","fechaInicioVigencia":"","fechaFinVigencia":"","agente":"","moneda":"","polizaRenovable":"","periodoFacturacion":"","numeroSolicitud":"","fechaIngresoContrato":"","duracionContratoMeses":"","codigoPromotor":"","subproducto":"","localidadRiesgo":"","actividadLaboral":"","codigoOcupacion":"","opcion":"","alternativa":"","beneficiariosInfo":"","tipoDocumentoCliente":"","numeroDocumentoCliente":"","primerNombreCliente":"","segundoNombreCliente":"","primerApellidoCliente":"","segundoApellidoCliente":"","sexoCliente":"","fechaNacimientoCliente":"","direccionCliente":"","ciudadCorrespondenciaCliente":"","telefonoCliente":"","celularCliente":"","ciudadResidenciaCliente":"","departamentoCliente":"","tipoContratoLaboral":"","reiterarCoberturas":"","numeroPoliza":"","observacionesFinal":"","certificado":"75272"}}
A291: 45888.588 | B291: 11704604 | C291: {"poliza":"1704","nombre":"JESUS ANTONIO CABEZAS DUARTE","id":"79602655","telefono":"3015674512","correo":"antoniocabedu@gmail.com","ciudad":"BOGOTA, D.C.","direccion":"CONJ CAMPI AS DEL SOL","tipoInmueble":"Vivienda","canon":"2350000","fechaRadicacion":"18/8/2025","fechaAprobacion":"19/8/2025","estado":"APROBADA","tipoDocumento":"CC"} | D291: luisa.herrera@segurosbolivar.com | E291: Contacto Inicial y Datos | F291: DESISTIDO | G291: Seguro de Vida | H291: [{"fecha":"2025-08-19 16:31:24","usuario":"luisa.herrera@segurosbolivar.com","accionRealizada":"DESISTIDO","leadEtapaActual":"Contacto Inicial y Datos","productosGestion":"Seguro de Vida","observaciones":"No Contesta"}] | I291: 45888.688 | J291: {"Contacto Inicial y Datos":{"nomAgt":"","emailCte":"","autorizaDatosPersonales":false,"fechaNacimiento":"","tipoDocumento":"","observacionesPresentacion":"no contesta ","genero":"","resultadoGestion":"Cliente ilocalizable","accion":"Cliente ilocalizable","usuario":"luisa.herrera@segurosbolivar.com"},"Cotización y Pre-Asegurabilidad":{"periosidad":"","nPagosMensuales":"","admin":"","observacionesCotizacion":"","valorAseguradoVida":0,"primaVidaITP":0,"fechaCotizacionVida":""},"Declaración de Asegurabilidad":{"actividadesLicita":false,"procesoPenal":false,"frecuenciaDeportesAltoRiesgo":"","peso":"","estatura":"","imcCalculado":"","observacionImc":"","estadoAsegurabilidad":"","hipertensionArterial":false,"colesterolTrigliceridosElevados":false,"diabetes":false,"enfermedadCoronariaInfarto":false,"insuficienciaRenal":false,"cancerTumores":false,"derrameTrombosisCerebral":false,"enfermedadesPsicologicasPsiquiatricas":false,"sidaVih":false,"pruebaVihPositiva":false,"secuelasEnfermedadAccidente":"","diagnosticoEnfermedadFracturas":"","tratamientoAlcoholAlucinogenos":false,"cirugiaProgramada":false,"autorizacionInformacionMedica":false,"fechaAsegurabilidad":""},"Autorización de Descuento Débito":{"canalDescuento":"","tipoDeCuenta":"","entidadBancaria":"","numeroCuentaDebito":"","fechaVencimientoTC":"","numeroCuotasTC":"","autorizaDescuentoAutomatico":false,"entiendeMoraPrima":false,"valorPrima":0,"fechaAutorizacionDebito":"","observacionesCierre":""},"Beneficiarios y Autorizaciones":{"nombreBeneficiario1":"","apellidoBeneficiario1":"","parentescoBeneficiario1":"","designacionBeneficiario1":0,"nombreBeneficiario2":"","apellidoBeneficiario2":"","parentescoBeneficiario2":"","designacionBeneficiario2":0,"nombreBeneficiario3":"","apellidoBeneficiario3":"","parentescoBeneficiario3":"","designacionBeneficiario3":0,"beneficiariosRegistrados":false,"fechaRegistroBeneficiarios":""},"Emisión de Póliza":{"numeroCertificadoFinal":"","resultadoEmision":"","fechaVigenciaPoliza":"","polizaPrincipal":"","periodicidadPagoPoliza":"MENSUAL","confirmacionVentaSegurosBolivar":false,"liderClavo":"","certificado":"75272","observacionesEmision":"","fechaEmisionPoliza":"","estadoPoliza":"","numeroContrato":""}}
A292: 45888.588 | B292: 11704627 | C292: {"poliza":"14039","nombre":"JUAN ELIAS ACOSTA ERAZO","id":"16686214","telefono":"3146269080","correo":"JUANELI.AC@HOTMAIL.COM","ciudad":"BARRANQUILLA","direccion":"CR 67 76 116 CA 1","tipoInmueble":"Vivienda","canon":"2500000","fechaRadicacion":"18/8/2025","fechaAprobacion":"19/8/2025","estado":"APROBADA","tipoDocumento":"CC"} | D292: Anyuley.daza@aselibertador.com | E292: Contacto Inicial y Datos | F292: DESISTIDO | G292: Seguro de Vida | H292: [{"fecha":"2025-08-19 15:41:46","usuario":"anyuley.daza@aselibertador.com","accionRealizada":"DESISTIDO","leadEtapaActual":"Contacto Inicial y Datos","productosGestion":"Seguro de Vida","observaciones":"No le interesa"}] | I292: 45888.654 | J292: {"Contacto Inicial y Datos":{"nomAgt":"","emailCte":"","autorizaDatosPersonales":false,"fechaNacimiento":"","tipoDocumento":"","observacionesPresentacion":"no le interesa","genero":"","resultadoGestion":"Cliente no interesado","accion":"Cliente no interesado","usuario":"anyuley.daza@aselibertador.com"},"Cotización y Pre-Asegurabilidad":{"periosidad":"","nPagosMensuales":"","admin":"","observacionesCotizacion":"","valorAseguradoVida":0,"primaVidaITP":0,"fechaCotizacionVida":""},"Declaración de Asegurabilidad":{"actividadesLicita":false,"procesoPenal":false,"frecuenciaDeportesAltoRiesgo":"","peso":"","estatura":"","imcCalculado":"","observacionImc":"","estadoAsegurabilidad":"","hipertensionArterial":false,"colesterolTrigliceridosElevados":false,"diabetes":false,"enfermedadCoronariaInfarto":false,"insuficienciaRenal":false,"cancerTumores":false,"derrameTrombosisCerebral":false,"enfermedadesPsicologicasPsiquiatricas":false,"sidaVih":false,"pruebaVihPositiva":false,"secuelasEnfermedadAccidente":"","diagnosticoEnfermedadFracturas":"","tratamientoAlcoholAlucinogenos":false,"cirugiaProgramada":false,"autorizacionInformacionMedica":false,"fechaAsegurabilidad":""},"Autorización de Descuento Débito":{"canalDescuento":"","tipoDeCuenta":"","entidadBancaria":"","numeroCuentaDebito":"","fechaVencimientoTC":"","numeroCuotasTC":"","autorizaDescuentoAutomatico":false,"entiendeMoraPrima":false,"valorPrima":0,"fechaAutorizacionDebito":"","observacionesCierre":""},"Beneficiarios y Autorizaciones":{"nombreBeneficiario1":"","apellidoBeneficiario1":"","parentescoBeneficiario1":"","designacionBeneficiario1":0,"nombreBeneficiario2":"","apellidoBeneficiario2":"","parentescoBeneficiario2":"","designacionBeneficiario2":0,"nombreBeneficiario3":"","apellidoBeneficiario3":"","parentescoBeneficiario3":"","designacionBeneficiario3":0,"beneficiariosRegistrados":false,"fechaRegistroBeneficiarios":""},"Emisión de Póliza":{"numeroCertificadoFinal":"","resultadoEmision":"","fechaVigenciaPoliza":"","polizaPrincipal":"","periodicidadPagoPoliza":"MENSUAL","confirmacionVentaSegurosBolivar":false,"liderClavo":"","certificado":"75272","observacionesEmision":"","fechaEmisionPoliza":"","estadoPoliza":"","numeroContrato":""}}
A293: 45888.588 | B293: 11704632 | C293: {"poliza":"483","nombre":"CADENA SUSAN KLIGMAN CADENA","id":"1020838123","telefono":"3102910510","correo":"susan_klic@hotmail.com","ciudad":"BOGOTA, D.C.","direccion":"CL 146 13 48","tipoInmueble":"Vivienda","canon":"2168000","fechaRadicacion":"18/8/2025","fechaAprobacion":"19/8/2025","estado":"APROBADA","tipoDocumento":"CC"} | D293: ana.prieto@aselibertador.com | E293: Contacto Inicial y Datos | F293: DESISTIDO | G293: Seguro de Vida | H293: [{"fecha":"2025-08-19 15:53:00","usuario":"ana.prieto@aselibertador.com","accionRealizada":"DESISTIDO","leadEtapaActual":"Contacto Inicial y Datos","productosGestion":"Seguro de Vida","observaciones":"No Contesta"}] | I293: 45888.662 | J293: {"Contacto Inicial y Datos":{"nomAgt":"","emailCte":"","autorizaDatosPersonales":false,"fechaNacimiento":"","tipoDocumento":"","observacionesPresentacion":"","genero":"","resultadoGestion":"Cliente ilocalizable","accion":"Cliente ilocalizable","usuario":"ana.prieto@aselibertador.com"},"Cotización y Pre-Asegurabilidad":{"periosidad":"","nPagosMensuales":"","admin":"","observacionesCotizacion":"","valorAseguradoVida":0,"primaVidaITP":0,"fechaCotizacionVida":""},"Declaración de Asegurabilidad":{"actividadesLicita":false,"procesoPenal":false,"frecuenciaDeportesAltoRiesgo":"","peso":"","estatura":"","imcCalculado":"","observacionImc":"","estadoAsegurabilidad":"","hipertensionArterial":false,"colesterolTrigliceridosElevados":false,"diabetes":false,"enfermedadCoronariaInfarto":false,"insuficienciaRenal":false,"cancerTumores":false,"derrameTrombosisCerebral":false,"enfermedadesPsicologicasPsiquiatricas":false,"sidaVih":false,"pruebaVihPositiva":false,"secuelasEnfermedadAccidente":"","diagnosticoEnfermedadFracturas":"","tratamientoAlcoholAlucinogenos":false,"cirugiaProgramada":false,"autorizacionInformacionMedica":false,"fechaAsegurabilidad":""},"Autorización de Descuento Débito":{"canalDescuento":"","tipoDeCuenta":"","entidadBancaria":"","numeroCuentaDebito":"","fechaVencimientoTC":"","numeroCuotasTC":"","autorizaDescuentoAutomatico":false,"entiendeMoraPrima":false,"valorPrima":0,"fechaAutorizacionDebito":"","observacionesCierre":""},"Beneficiarios y Autorizaciones":{"nombreBeneficiario1":"","apellidoBeneficiario1":"","parentescoBeneficiario1":"","designacionBeneficiario1":0,"nombreBeneficiario2":"","apellidoBeneficiario2":"","parentescoBeneficiario2":"","designacionBeneficiario2":0,"nombreBeneficiario3":"","apellidoBeneficiario3":"","parentescoBeneficiario3":"","designacionBeneficiario3":0,"beneficiariosRegistrados":false,"fechaRegistroBeneficiarios":""},"Emisión de Póliza":{"numeroCertificadoFinal":"","resultadoEmision":"","fechaVigenciaPoliza":"","polizaPrincipal":"","periodicidadPagoPoliza":"MENSUAL","confirmacionVentaSegurosBolivar":false,"liderClavo":"","certificado":"75272","observacionesEmision":"","fechaEmisionPoliza":"","estadoPoliza":"","numeroContrato":""}}
A294: 45888.588 | B294: 11704703 | C294: {"poliza":"14220","nombre":"JUAN PABLO GUEVARA PINZON","id":"1234089087","telefono":"3135139304","correo":"jpguevarap@yahoo.com","ciudad":"PUERTO COLOMBIA","direccion":"CL 2 10C 121","tipoInmueble":"Vivienda","canon":"2500000","fechaRadicacion":"18/8/2025","fechaAprobacion":"19/8/2025","estado":"APROBADA","tipoDocumento":"CC"} | D294: maria.gaitan@proyectivaseguros.com | E294: Contacto Inicial y Datos | F294: DESISTIDO | G294: Seguro de Vida | H294: [{"fecha":"2025-08-22 09:57:36","usuario":"maria.gaitan@segurosbolivar.com","accionRealizada":"DESISTIDO","leadEtapaActual":"Contacto Inicial y Datos","productosGestion":"Seguro de Vida","observaciones":"No Contesta"}] | I294: 45891.415 | J294: {"Contacto Inicial y Datos":{"nomAgt":"","emailCte":"","autorizaDatosPersonales":false,"fechaNacimiento":"2025-08-22","tipoDocumento":"","observacionesPresentacion":"","genero":"","resultadoGestion":"Cliente ilocalizable","accion":"Cliente ilocalizable","usuario":"maria.gaitan@segurosbolivar.com"},"Cotización y Pre-Asegurabilidad":{"periosidad":"","nPagosMensuales":"","admin":"","observacionesCotizacion":"","valorAseguradoVida":0,"primaVidaITP":0,"fechaCotizacionVida":""},"Declaración de Asegurabilidad":{"actividadesLicita":false,"procesoPenal":false,"frecuenciaDeportesAltoRiesgo":"","peso":"","estatura":"","imcCalculado":"","observacionImc":"","estadoAsegurabilidad":"","hipertensionArterial":false,"colesterolTrigliceridosElevados":false,"diabetes":false,"enfermedadCoronariaInfarto":false,"insuficienciaRenal":false,"cancerTumores":false,"derrameTrombosisCerebral":false,"enfermedadesPsicologicasPsiquiatricas":false,"sidaVih":false,"pruebaVihPositiva":false,"secuelasEnfermedadAccidente":"","diagnosticoEnfermedadFracturas":"","tratamientoAlcoholAlucinogenos":false,"cirugiaProgramada":false,"autorizacionInformacionMedica":false,"fechaAsegurabilidad":""},"Autorización de Descuento Débito":{"canalDescuento":"","tipoDeCuenta":"","entidadBancaria":"","numeroCuentaDebito":"","fechaVencimientoTC":"","numeroCuotasTC":"","autorizaDescuentoAutomatico":false,"entiendeMoraPrima":false,"valorPrima":0,"fechaAutorizacionDebito":"","observacionesCierre":""},"Beneficiarios y Autorizaciones":{"nombreBeneficiario1":"","apellidoBeneficiario1":"","parentescoBeneficiario1":"","designacionBeneficiario1":0,"nombreBeneficiario2":"","apellidoBeneficiario2":"","parentescoBeneficiario2":"","designacionBeneficiario2":0,"nombreBeneficiario3":"","apellidoBeneficiario3":"","parentescoBeneficiario3":"","designacionBeneficiario3":0,"beneficiariosRegistrados":false,"fechaRegistroBeneficiarios":""},"Emisión de Póliza":{"numeroCertificadoFinal":"","resultadoEmision":"","fechaVigenciaPoliza":"","polizaPrincipal":"","periodicidadPagoPoliza":"MENSUAL","confirmacionVentaSegurosBolivar":false,"liderClavo":"","certificado":"75272","observacionesEmision":"","fechaEmisionPoliza":"","estadoPoliza":"","numeroContrato":""}}
A295: 45888.588 | B295: 11704745 | C295: {"poliza":"429","nombre":"LINA MARIA PARRADO ORTIZ","id":"1006877785","telefono":"3118943643","correo":"LINA.PARRADO01@GMAIL.COM","ciudad":"CHIA","direccion":"CL 2 # 1 C 00 TO 2 AP 131","tipoInmueble":"Vivienda","canon":"1300000","fechaRadicacion":"18/8/2025","fechaAprobacion":"19/8/2025","estado":"APROBADA","tipoDocumento":"CC"} | D295: luisa.herrera@segurosbolivar.com | E295: Contacto Inicial y Datos | F295: DESISTIDO | G295: Seguro de Vida | H295: [{"fecha":"2025-08-19 16:34:08","usuario":"luisa.herrera@segurosbolivar.com","accionRealizada":"DESISTIDO","leadEtapaActual":"Contacto Inicial y Datos","productosGestion":"Seguro de Vida","observaciones":"No Contesta"}] | I295: 45888.69 | J295: {"Contacto Inicial y Datos":{"nomAgt":"","emailCte":"","autorizaDatosPersonales":false,"fechaNacimiento":"","tipoDocumento":"","observacionesPresentacion":"no contesta ","genero":"","resultadoGestion":"Cliente ilocalizable","accion":"Cliente ilocalizable","usuario":"luisa.herrera@segurosbolivar.com"},"Cotización y Pre-Asegurabilidad":{"periosidad":"","nPagosMensuales":"","admin":"","observacionesCotizacion":"","valorAseguradoVida":0,"primaVidaITP":0,"fechaCotizacionVida":""},"Declaración de Asegurabilidad":{"actividadesLicita":false,"procesoPenal":false,"frecuenciaDeportesAltoRiesgo":"","peso":"","estatura":"","imcCalculado":"","observacionImc":"","estadoAsegurabilidad":"","hipertensionArterial":false,"colesterolTrigliceridosElevados":false,"diabetes":false,"enfermedadCoronariaInfarto":false,"insuficienciaRenal":false,"cancerTumores":false,"derrameTrombosisCerebral":false,"enfermedadesPsicologicasPsiquiatricas":false,"sidaVih":false,"pruebaVihPositiva":false,"secuelasEnfermedadAccidente":"","diagnosticoEnfermedadFracturas":"","tratamientoAlcoholAlucinogenos":false,"cirugiaProgramada":false,"autorizacionInformacionMedica":false,"fechaAsegurabilidad":""},"Autorización de Descuento Débito":{"canalDescuento":"","tipoDeCuenta":"","entidadBancaria":"","numeroCuentaDebito":"","fechaVencimientoTC":"","numeroCuotasTC":"","autorizaDescuentoAutomatico":false,"entiendeMoraPrima":false,"valorPrima":0,"fechaAutorizacionDebito":"","observacionesCierre":""},"Beneficiarios y Autorizaciones":{"nombreBeneficiario1":"","apellidoBeneficiario1":"","parentescoBeneficiario1":"","designacionBeneficiario1":0,"nombreBeneficiario2":"","apellidoBeneficiario2":"","parentescoBeneficiario2":"","designacionBeneficiario2":0,"nombreBeneficiario3":"","apellidoBeneficiario3":"","parentescoBeneficiario3":"","designacionBeneficiario3":0,"beneficiariosRegistrados":false,"fechaRegistroBeneficiarios":""},"Emisión de Póliza":{"numeroCertificadoFinal":"","resultadoEmision":"","fechaVigenciaPoliza":"","polizaPrincipal":"","periodicidadPagoPoliza":"MENSUAL","confirmacionVentaSegurosBolivar":false,"liderClavo":"","certificado":"75272","observacionesEmision":"","fechaEmisionPoliza":"","estadoPoliza":"","numeroContrato":""}}
A296: 45888.588 | B296: 11704841 | C296: {"poliza":"13327","nombre":"LUISA FERNANDA CARVAJAL RODRÍGUEZ","id":"1000211226","telefono":"3127242770","correo":"luisacarvajal211226@gmail.com","ciudad":"MEDELLIN","direccion":"PENDIENTE","tipoInmueble":"Vivienda","canon":"1600000","fechaRadicacion":"19/8/2025","fechaAprobacion":"19/8/2025","estado":"APROBADA","tipoDocumento":"CC"} | D296: Anyuley.daza@aselibertador.com | E296: Contacto Inicial y Datos | F296: DESISTIDO | G296: Seguro de Vida | H296: [{"fecha":"2025-08-19 15:33:28","usuario":"anyuley.daza@aselibertador.com","accionRealizada":"DESISTIDO","leadEtapaActual":"Contacto Inicial y Datos","productosGestion":"Seguro de Vida","observaciones":"No Contesta"}] | I296: 45888.648 | J296: {"Contacto Inicial y Datos":{"nomAgt":"","emailCte":"","autorizaDatosPersonales":false,"fechaNacimiento":"","tipoDocumento":"","observacionesPresentacion":"Se marca tres vces,No contesta","genero":"","resultadoGestion":"Cliente ilocalizable","accion":"Cliente ilocalizable","usuario":"anyuley.daza@aselibertador.com"},"Cotización y Pre-Asegurabilidad":{"periosidad":"","nPagosMensuales":"","admin":"","observacionesCotizacion":"","valorAseguradoVida":0,"primaVidaITP":0,"fechaCotizacionVida":""},"Declaración de Asegurabilidad":{"actividadesLicita":false,"procesoPenal":false,"frecuenciaDeportesAltoRiesgo":"","peso":"","estatura":"","imcCalculado":"","observacionImc":"","estadoAsegurabilidad":"","hipertensionArterial":false,"colesterolTrigliceridosElevados":false,"diabetes":false,"enfermedadCoronariaInfarto":false,"insuficienciaRenal":false,"cancerTumores":false,"derrameTrombosisCerebral":false,"enfermedadesPsicologicasPsiquiatricas":false,"sidaVih":false,"pruebaVihPositiva":false,"secuelasEnfermedadAccidente":"","diagnosticoEnfermedadFracturas":"","tratamientoAlcoholAlucinogenos":false,"cirugiaProgramada":false,"autorizacionInformacionMedica":false,"fechaAsegurabilidad":""},"Autorización de Descuento Débito":{"canalDescuento":"","tipoDeCuenta":"","entidadBancaria":"","numeroCuentaDebito":"","fechaVencimientoTC":"","numeroCuotasTC":"","autorizaDescuentoAutomatico":false,"entiendeMoraPrima":false,"valorPrima":0,"fechaAutorizacionDebito":"","observacionesCierre":""},"Beneficiarios y Autorizaciones":{"nombreBeneficiario1":"","apellidoBeneficiario1":"","parentescoBeneficiario1":"","designacionBeneficiario1":0,"nombreBeneficiario2":"","apellidoBeneficiario2":"","parentescoBeneficiario2":"","designacionBeneficiario2":0,"nombreBeneficiario3":"","apellidoBeneficiario3":"","parentescoBeneficiario3":"","designacionBeneficiario3":0,"beneficiariosRegistrados":false,"fechaRegistroBeneficiarios":""},"Emisión de Póliza":{"numeroCertificadoFinal":"","resultadoEmision":"","fechaVigenciaPoliza":"","polizaPrincipal":"","periodicidadPagoPoliza":"MENSUAL","confirmacionVentaSegurosBolivar":false,"liderClavo":"","certificado":"75272","observacionesEmision":"","fechaEmisionPoliza":"","estadoPoliza":"","numeroContrato":""}}
A297: 45888.588 | B297: 11704849 | C297: {"poliza":"13226","nombre":"LEIDY TATIANA ROJAS VANEGAS","id":"1000637347","telefono":"3007466631","correo":"tatianavanegas1105@gmail.com","ciudad":"SABANETA","direccion":"PENDIENTE","tipoInmueble":"Vivienda","canon":"1480000","fechaRadicacion":"19/8/2025","fechaAprobacion":"19/8/2025","estado":"APROBADA","tipoDocumento":"CC"} | D297: ana.prieto@aselibertador.com | E297: Contacto Inicial y Datos | F297: DESISTIDO | G297: Seguro de Vida | H297: [{"fecha":"2025-08-19 15:48:11","usuario":"ana.prieto@aselibertador.com","accionRealizada":"DESISTIDO","leadEtapaActual":"Contacto Inicial y Datos","productosGestion":"Seguro de Vida","observaciones":"No le interesa"}] | I297: 45888.658 | J297: {"Contacto Inicial y Datos":{"nomAgt":"","emailCte":"","autorizaDatosPersonales":false,"fechaNacimiento":"","tipoDocumento":"","observacionesPresentacion":"","genero":"","resultadoGestion":"","accion":"No Asegurable","usuario":"ana.prieto@aselibertador.com"},"Cotización y Pre-Asegurabilidad":{"periosidad":"","nPagosMensuales":"","admin":"","observacionesCotizacion":"","valorAseguradoVida":0,"primaVidaITP":0,"fechaCotizacionVida":""},"Declaración de Asegurabilidad":{"actividadesLicita":false,"procesoPenal":false,"frecuenciaDeportesAltoRiesgo":"","peso":"","estatura":"","imcCalculado":"","observacionImc":"","estadoAsegurabilidad":"","hipertensionArterial":false,"colesterolTrigliceridosElevados":false,"diabetes":false,"enfermedadCoronariaInfarto":false,"insuficienciaRenal":false,"cancerTumores":false,"derrameTrombosisCerebral":false,"enfermedadesPsicologicasPsiquiatricas":false,"sidaVih":false,"pruebaVihPositiva":false,"secuelasEnfermedadAccidente":"","diagnosticoEnfermedadFracturas":"","tratamientoAlcoholAlucinogenos":false,"cirugiaProgramada":false,"autorizacionInformacionMedica":false,"fechaAsegurabilidad":""},"Autorización de Descuento Débito":{"canalDescuento":"","tipoDeCuenta":"","entidadBancaria":"","numeroCuentaDebito":"","fechaVencimientoTC":"","numeroCuotasTC":"","autorizaDescuentoAutomatico":false,"entiendeMoraPrima":false,"valorPrima":0,"fechaAutorizacionDebito":"","observacionesCierre":""},"Beneficiarios y Autorizaciones":{"nombreBeneficiario1":"","apellidoBeneficiario1":"","parentescoBeneficiario1":"","designacionBeneficiario1":0,"nombreBeneficiario2":"","apellidoBeneficiario2":"","parentescoBeneficiario2":"","designacionBeneficiario2":0,"nombreBeneficiario3":"","apellidoBeneficiario3":"","parentescoBeneficiario3":"","designacionBeneficiario3":0,"beneficiariosRegistrados":false,"fechaRegistroBeneficiarios":""},"Emisión de Póliza":{"numeroCertificadoFinal":"","resultadoEmision":"","fechaVigenciaPoliza":"","polizaPrincipal":"","periodicidadPagoPoliza":"MENSUAL","confirmacionVentaSegurosBolivar":false,"liderClavo":"","certificado":"75272","observacionesEmision":"","fechaEmisionPoliza":"","estadoPoliza":"","numeroContrato":""}}
A298: 45888.588 | B298: 11704894 | C298: {"poliza":"2158","nombre":"YULIETH PATRICIA OSORIO MEDINA","id":"1002979485","telefono":"3172253393","correo":"osorio14yuli@gmail.com","ciudad":"SOACHA","direccion":"CONJ RESIDENCIAL SAUCE2","tipoInmueble":"Vivienda","canon":"610000","fechaRadicacion":"19/8/2025","fechaAprobacion":"19/8/2025","estado":"APROBADA","tipoDocumento":"CC"} | D298: maria.gaitan@proyectivaseguros.com | E298: Contacto Inicial y Datos | F298: DESISTIDO | G298: Seguro de Vida | H298: [{"fecha":"2025-08-22 09:57:03","usuario":"maria.gaitan@segurosbolivar.com","accionRealizada":"DESISTIDO","leadEtapaActual":"Contacto Inicial y Datos","productosGestion":"Seguro de Vida","observaciones":"No Contesta"}] | I298: 45891.415 | J298: {"Contacto Inicial y Datos":{"nomAgt":"","emailCte":"","autorizaDatosPersonales":false,"fechaNacimiento":"2025-08-22","tipoDocumento":"","observacionesPresentacion":"","genero":"","resultadoGestion":"Cliente ilocalizable","accion":"Cliente ilocalizable","usuario":"maria.gaitan@segurosbolivar.com"},"Cotización y Pre-Asegurabilidad":{"periosidad":"","nPagosMensuales":"","admin":"","observacionesCotizacion":"","valorAseguradoVida":0,"primaVidaITP":0,"fechaCotizacionVida":""},"Declaración de Asegurabilidad":{"actividadesLicita":false,"procesoPenal":false,"frecuenciaDeportesAltoRiesgo":"","peso":"","estatura":"","imcCalculado":"","observacionImc":"","estadoAsegurabilidad":"","hipertensionArterial":false,"colesterolTrigliceridosElevados":false,"diabetes":false,"enfermedadCoronariaInfarto":false,"insuficienciaRenal":false,"cancerTumores":false,"derrameTrombosisCerebral":false,"enfermedadesPsicologicasPsiquiatricas":false,"sidaVih":false,"pruebaVihPositiva":false,"secuelasEnfermedadAccidente":"","diagnosticoEnfermedadFracturas":"","tratamientoAlcoholAlucinogenos":false,"cirugiaProgramada":false,"autorizacionInformacionMedica":false,"fechaAsegurabilidad":""},"Autorización de Descuento Débito":{"canalDescuento":"","tipoDeCuenta":"","entidadBancaria":"","numeroCuentaDebito":"","fechaVencimientoTC":"","numeroCuotasTC":"","autorizaDescuentoAutomatico":false,"entiendeMoraPrima":false,"valorPrima":0,"fechaAutorizacionDebito":"","observacionesCierre":""},"Beneficiarios y Autorizaciones":{"nombreBeneficiario1":"","apellidoBeneficiario1":"","parentescoBeneficiario1":"","designacionBeneficiario1":0,"nombreBeneficiario2":"","apellidoBeneficiario2":"","parentescoBeneficiario2":"","designacionBeneficiario2":0,"nombreBeneficiario3":"","apellidoBeneficiario3":"","parentescoBeneficiario3":"","designacionBeneficiario3":0,"beneficiariosRegistrados":false,"fechaRegistroBeneficiarios":""},"Emisión de Póliza":{"numeroCertificadoFinal":"","resultadoEmision":"","fechaVigenciaPoliza":"","polizaPrincipal":"","periodicidadPagoPoliza":"MENSUAL","confirmacionVentaSegurosBolivar":false,"liderClavo":"","certificado":"75272","observacionesEmision":"","fechaEmisionPoliza":"","estadoPoliza":"","numeroContrato":""}}
A299: 45888.588 | B299: 11704904 | C299: {"poliza":"13093","nombre":"YOLIMA MARCELA TORRES PEREA","id":"1003850411","telefono":"3126040604","correo":"yomatope@gmail.com","ciudad":"MEDELLIN","direccion":"CL 45 12 23","tipoInmueble":"Vivienda","canon":"1900000","fechaRadicacion":"19/8/2025","fechaAprobacion":"19/8/2025","estado":"APROBADA","tipoDocumento":"CC"} | D299: angie.ariza.roncancio@proyectivaseguros.com | E299: Contacto Inicial y Datos | F299: DESISTIDO | G299: Seguro de Desempleo | H299: [{"fecha":"2025-08-28 14:31:50","usuario":"angie.ariza.roncancio@segurosbolivar.com","accionRealizada":"DESISTIDO","leadEtapaActual":"Contacto Inicial y Datos","productosGestion":"Seguro de Desempleo","observaciones":"Ya habia tomado inmueble, no se hace ofrecimiento"}] | I299: 45897.605 | K299: {"Contacto Inicial y Datos":{"nomAgt":"","emailCte":"","autorizaDatosPersonales":false,"tipoVinculacion":"","nombreEmpleador":"","confirmaCanon":"","canonArrendamiento":0,"costoProteccionMensual":0,"medioDebito":"","continuarVentaIndependiente":"","observacionesContacto":"","fechaNacimiento":"","genero":"","tipoDocumento":"","resultadoGestion":"Venta Cancelada","observacionesPresentacion":"Ya habia tomado el inmueble ","accion":"Venta Cancelada","usuario":"angie.ariza.roncancio@segurosbolivar.com"},"Cotización y Pre-Asegurabilidad":{"valorAseguradoDesempleo":0,"primaDesempleo":0,"fechaCotizacionDesempleo":"","autorizaDatosInd":false,"ocupacionLicitaInd":false,"procesadoPenalInd":false,"otraOcupacionInd":"","otraOcupacionIndText":"","observacionesCotizacion":""},"Declaración de Asegurabilidad":{"autorizaInfoGeneral":false,"observacionesNegociacion":""},"Autorización de Descuento Débito":{"canalDescuento":"","tipoDeCuenta":"","entidadBancaria":"","numeroCuentaDebito":"","fechaVencimientoTC":"","numeroCuotasTC":"","valorPrima":0,"autorizaDescuentoAutomatico":false,"entiendeMoraPrima":false,"fechaAutorizacionDebito":"","observacionesCierre":""},"Beneficiarios y Autorizaciones":{"continuarReiteracionInd":"","observacionesRectificacion":"","fechaRectificacion":""},"Emisión de Póliza":{"confirmacionVentaActivacion":"","fechaActivacionPoliza":"","seccion":"","producto":"","polizaPrincipal":"","tomador":"","nitLibertador":"","tipoEnvio":"","periodicidadPagoPoliza":"MENSUAL","formaCobroPoliza":"AUTOMÁTICO","fechaInicioVigencia":"","fechaFinVigencia":"","agente":"","moneda":"","polizaRenovable":"","periodoFacturacion":"","numeroSolicitud":"","fechaIngresoContrato":"","duracionContratoMeses":"","codigoPromotor":"","subproducto":"","localidadRiesgo":"","actividadLaboral":"","codigoOcupacion":"","opcion":"","alternativa":"","beneficiariosInfo":"","tipoDocumentoCliente":"","numeroDocumentoCliente":"","primerNombreCliente":"","segundoNombreCliente":"","primerApellidoCliente":"","segundoApellidoCliente":"","sexoCliente":"","fechaNacimientoCliente":"","direccionCliente":"","ciudadCorrespondenciaCliente":"","telefonoCliente":"","celularCliente":"","ciudadResidenciaCliente":"","departamentoCliente":"","tipoContratoLaboral":"","reiterarCoberturas":"","numeroPoliza":"","observacionesFinal":"","certificado":"75272"}}
A300: 45888.588 | B300: 11704959 | C300: {"poliza":"483","nombre":"GABRIEL SEBASTIAN GUTIERRREZ ARBELAEZ","id":"1019111911","telefono":"3108190776","correo":"gabriel1809gu@gmail.com","ciudad":"BOGOTA, D.C.","direccion":"CL 176 54 15 TO 4 AP 1232","tipoInmueble":"Vivienda","canon":"1300000","fechaRadicacion":"19/8/2025","fechaAprobacion":"19/8/2025","estado":"APROBADA","tipoDocumento":"CC"} | D300: luisa.herrera@segurosbolivar.com | E300: Contacto Inicial y Datos | F300: DESISTIDO | G300: Seguro de Vida | H300: [{"fecha":"2025-08-19 16:36:13","usuario":"luisa.herrera@segurosbolivar.com","accionRealizada":"DESISTIDO","leadEtapaActual":"Contacto Inicial y Datos","productosGestion":"Seguro de Vida","observaciones":"No Contesta"}] | I300: 45888.692 | J300: {"Contacto Inicial y Datos":{"nomAgt":"","emailCte":"","autorizaDatosPersonales":false,"fechaNacimiento":"","tipoDocumento":"","observacionesPresentacion":"no contesta ","genero":"","resultadoGestion":"Cliente ilocalizable","accion":"Cliente ilocalizable","usuario":"luisa.herrera@segurosbolivar.com"},"Cotización y Pre-Asegurabilidad":{"periosidad":"","nPagosMensuales":"","admin":"","observacionesCotizacion":"","valorAseguradoVida":0,"primaVidaITP":0,"fechaCotizacionVida":""},"Declaración de Asegurabilidad":{"actividadesLicita":false,"procesoPenal":false,"frecuenciaDeportesAltoRiesgo":"","peso":"","estatura":"","imcCalculado":"","observacionImc":"","estadoAsegurabilidad":"","hipertensionArterial":false,"colesterolTrigliceridosElevados":false,"diabetes":false,"enfermedadCoronariaInfarto":false,"insuficienciaRenal":false,"cancerTumores":false,"derrameTrombosisCerebral":false,"enfermedadesPsicologicasPsiquiatricas":false,"sidaVih":false,"pruebaVihPositiva":false,"secuelasEnfermedadAccidente":"","diagnosticoEnfermedadFracturas":"","tratamientoAlcoholAlucinogenos":false,"cirugiaProgramada":false,"autorizacionInformacionMedica":false,"fechaAsegurabilidad":""},"Autorización de Descuento Débito":{"canalDescuento":"","tipoDeCuenta":"","entidadBancaria":"","numeroCuentaDebito":"","fechaVencimientoTC":"","numeroCuotasTC":"","autorizaDescuentoAutomatico":false,"entiendeMoraPrima":false,"valorPrima":0,"fechaAutorizacionDebito":"","observacionesCierre":""},"Beneficiarios y Autorizaciones":{"nombreBeneficiario1":"","apellidoBeneficiario1":"","parentescoBeneficiario1":"","designacionBeneficiario1":0,"nombreBeneficiario2":"","apellidoBeneficiario2":"","parentescoBeneficiario2":"","designacionBeneficiario2":0,"nombreBeneficiario3":"","apellidoBeneficiario3":"","parentescoBeneficiario3":"","designacionBeneficiario3":0,"beneficiariosRegistrados":false,"fechaRegistroBeneficiarios":""},"Emisión de Póliza":{"numeroCertificadoFinal":"","resultadoEmision":"","fechaVigenciaPoliza":"","polizaPrincipal":"","periodicidadPagoPoliza":"MENSUAL","confirmacionVentaSegurosBolivar":false,"liderClavo":"","certificado":"75272","observacionesEmision":"","fechaEmisionPoliza":"","estadoPoliza":"","numeroContrato":""}}
A301: 45888.588 | B301: 11704977 | C301: {"poliza":"13002","nombre":"SUAREZ ALEJANDRA RUIZ SUAREZ","id":"1037593214","telefono":"3001306650","correo":"alejaruizsuarez@gmail.com","ciudad":"MEDELLIN","direccion":"CL 30 B 80 A 36 AP 501","tipoInmueble":"Vivienda","canon":"2600000","fechaRadicacion":"19/8/2025","fechaAprobacion":"19/8/2025","estado":"APROBADA","tipoDocumento":"CC"} | D301: angela.caipa@segurosbolivar.com | E301: Contacto Inicial y Datos | F301: DESISTIDO | G301: Seguro de Vida | H301: [{"fecha":"2025-08-19 14:22:15","usuario":"angela.caipa@segurosbolivar.com","accionRealizada":"DESISTIDO","leadEtapaActual":"Contacto Inicial y Datos","productosGestion":"Seguro de Vida","observaciones":"No le interesa"}] | I301: 45888.599 | J301: {"Contacto Inicial y Datos":{"nomAgt":"","emailCte":"","autorizaDatosPersonales":false,"fechaNacimiento":"","tipoDocumento":"","observacionesPresentacion":"","genero":"","resultadoGestion":"","accion":"No Asegurable","usuario":"angela.caipa@segurosbolivar.com"},"Cotización y Pre-Asegurabilidad":{"periosidad":"","nPagosMensuales":"","admin":"","observacionesCotizacion":"","valorAseguradoVida":0,"primaVidaITP":0,"fechaCotizacionVida":""},"Declaración de Asegurabilidad":{"actividadesLicita":false,"procesoPenal":false,"frecuenciaDeportesAltoRiesgo":"","peso":"","estatura":"","imcCalculado":"","observacionImc":"","estadoAsegurabilidad":"","hipertensionArterial":false,"colesterolTrigliceridosElevados":false,"diabetes":false,"enfermedadCoronariaInfarto":false,"insuficienciaRenal":false,"cancerTumores":false,"derrameTrombosisCerebral":false,"enfermedadesPsicologicasPsiquiatricas":false,"sidaVih":false,"pruebaVihPositiva":false,"secuelasEnfermedadAccidente":"","diagnosticoEnfermedadFracturas":"","tratamientoAlcoholAlucinogenos":false,"cirugiaProgramada":false,"autorizacionInformacionMedica":false,"fechaAsegurabilidad":""},"Autorización de Descuento Débito":{"canalDescuento":"","tipoDeCuenta":"","entidadBancaria":"","numeroCuentaDebito":"","fechaVencimientoTC":"","numeroCuotasTC":"","autorizaDescuentoAutomatico":false,"entiendeMoraPrima":false,"valorPrima":0,"fechaAutorizacionDebito":"","observacionesCierre":""},"Beneficiarios y Autorizaciones":{"nombreBeneficiario1":"","apellidoBeneficiario1":"","parentescoBeneficiario1":"","designacionBeneficiario1":0,"nombreBeneficiario2":"","apellidoBeneficiario2":"","parentescoBeneficiario2":"","designacionBeneficiario2":0,"nombreBeneficiario3":"","apellidoBeneficiario3":"","parentescoBeneficiario3":"","designacionBeneficiario3":0,"beneficiariosRegistrados":false,"fechaRegistroBeneficiarios":""},"Emisión de Póliza":{"numeroCertificadoFinal":"","resultadoEmision":"","fechaVigenciaPoliza":"","polizaPrincipal":"","periodicidadPagoPoliza":"MENSUAL","confirmacionVentaSegurosBolivar":false,"liderClavo":"","certificado":"75272","observacionesEmision":"","fechaEmisionPoliza":"","estadoPoliza":"","numeroContrato":""}}
A302: 45888.588 | B302: 11705103 | C302: {"poliza":"11131","nombre":"YEISON ESTIBEN GARCIA TARAZONA","id":"1102355747","telefono":"3015986147","correo":"garciatarazonanahir@gmail.com","ciudad":"PIEDECUESTA","direccion":"CRA 2W # 16D 21","tipoInmueble":"Vivienda","canon":"500000","fechaRadicacion":"19/8/2025","fechaAprobacion":"19/8/2025","estado":"APROBADA","tipoDocumento":"CC"} | D302: Anyuley.daza@aselibertador.com | E302: Contacto Inicial y Datos | F302: DESISTIDO | G302: Seguro de Vida | H302: [{"fecha":"2025-08-19 15:30:28","usuario":"anyuley.daza@aselibertador.com","accionRealizada":"DESISTIDO","leadEtapaActual":"Contacto Inicial y Datos","productosGestion":"Seguro de Vida","observaciones":"No Contesta"}] | I302: 45888.646 | J302: {"Contacto Inicial y Datos":{"nomAgt":"","emailCte":"","autorizaDatosPersonales":false,"fechaNacimiento":"","tipoDocumento":"","observacionesPresentacion":"Se marca tres vces,No contesta","genero":"","resultadoGestion":"Cliente ilocalizable","accion":"Cliente ilocalizable","usuario":"anyuley.daza@aselibertador.com"},"Cotización y Pre-Asegurabilidad":{"periosidad":"","nPagosMensuales":"","admin":"","observacionesCotizacion":"","valorAseguradoVida":0,"primaVidaITP":0,"fechaCotizacionVida":""},"Declaración de Asegurabilidad":{"actividadesLicita":false,"procesoPenal":false,"frecuenciaDeportesAltoRiesgo":"","peso":"","estatura":"","imcCalculado":"","observacionImc":"","estadoAsegurabilidad":"","hipertensionArterial":false,"colesterolTrigliceridosElevados":false,"diabetes":false,"enfermedadCoronariaInfarto":false,"insuficienciaRenal":false,"cancerTumores":false,"derrameTrombosisCerebral":false,"enfermedadesPsicologicasPsiquiatricas":false,"sidaVih":false,"pruebaVihPositiva":false,"secuelasEnfermedadAccidente":"","diagnosticoEnfermedadFracturas":"","tratamientoAlcoholAlucinogenos":false,"cirugiaProgramada":false,"autorizacionInformacionMedica":false,"fechaAsegurabilidad":""},"Autorización de Descuento Débito":{"canalDescuento":"","tipoDeCuenta":"","entidadBancaria":"","numeroCuentaDebito":"","fechaVencimientoTC":"","numeroCuotasTC":"","autorizaDescuentoAutomatico":false,"entiendeMoraPrima":false,"valorPrima":0,"fechaAutorizacionDebito":"","observacionesCierre":""},"Beneficiarios y Autorizaciones":{"nombreBeneficiario1":"","apellidoBeneficiario1":"","parentescoBeneficiario1":"","designacionBeneficiario1":0,"nombreBeneficiario2":"","apellidoBeneficiario2":"","parentescoBeneficiario2":"","designacionBeneficiario2":0,"nombreBeneficiario3":"","apellidoBeneficiario3":"","parentescoBeneficiario3":"","designacionBeneficiario3":0,"beneficiariosRegistrados":false,"fechaRegistroBeneficiarios":""},"Emisión de Póliza":{"numeroCertificadoFinal":"","resultadoEmision":"","fechaVigenciaPoliza":"","polizaPrincipal":"","periodicidadPagoPoliza":"MENSUAL","confirmacionVentaSegurosBolivar":false,"liderClavo":"","certificado":"75272","observacionesEmision":"","fechaEmisionPoliza":"","estadoPoliza":"","numeroContrato":""}}
A303: 45888.588 | B303: 11705151 | C303: {"poliza":"13072","nombre":"BETANCUR DANIEL VANEGAS BETANCUR","id":"1037649025","telefono":"3127488290","correo":"Danielvb.2965@gmail.com","ciudad":"MEDELLIN","direccion":"CL 71 SUR 65 D 30","tipoInmueble":"Vivienda","canon":"1400000","fechaRadicacion":"19/8/2025","fechaAprobacion":"19/8/2025","estado":"APROBADA","tipoDocumento":"CC"} | D303: ana.prieto@aselibertador.com | E303: Contacto Inicial y Datos | F303: DESISTIDO | G303: Seguro de Vida | H303: [{"fecha":"2025-08-19 15:40:47","usuario":"ana.prieto@aselibertador.com","accionRealizada":"DESISTIDO","leadEtapaActual":"Contacto Inicial y Datos","productosGestion":"Seguro de Vida","observaciones":"No le interesa"}] | I303: 45888.653 | J303: {"Contacto Inicial y Datos":{"nomAgt":"","emailCte":"","autorizaDatosPersonales":false,"fechaNacimiento":"","tipoDocumento":"","observacionesPresentacion":"","genero":"","resultadoGestion":"","accion":"No Asegurable","usuario":"ana.prieto@aselibertador.com"},"Cotización y Pre-Asegurabilidad":{"periosidad":"","nPagosMensuales":"","admin":"","observacionesCotizacion":"","valorAseguradoVida":0,"primaVidaITP":0,"fechaCotizacionVida":""},"Declaración de Asegurabilidad":{"actividadesLicita":false,"procesoPenal":false,"frecuenciaDeportesAltoRiesgo":"","peso":"","estatura":"","imcCalculado":"","observacionImc":"","estadoAsegurabilidad":"","hipertensionArterial":false,"colesterolTrigliceridosElevados":false,"diabetes":false,"enfermedadCoronariaInfarto":false,"insuficienciaRenal":false,"cancerTumores":false,"derrameTrombosisCerebral":false,"enfermedadesPsicologicasPsiquiatricas":false,"sidaVih":false,"pruebaVihPositiva":false,"secuelasEnfermedadAccidente":"","diagnosticoEnfermedadFracturas":"","tratamientoAlcoholAlucinogenos":false,"cirugiaProgramada":false,"autorizacionInformacionMedica":false,"fechaAsegurabilidad":""},"Autorización de Descuento Débito":{"canalDescuento":"","tipoDeCuenta":"","entidadBancaria":"","numeroCuentaDebito":"","fechaVencimientoTC":"","numeroCuotasTC":"","autorizaDescuentoAutomatico":false,"entiendeMoraPrima":false,"valorPrima":0,"fechaAutorizacionDebito":"","observacionesCierre":""},"Beneficiarios y Autorizaciones":{"nombreBeneficiario1":"","apellidoBeneficiario1":"","parentescoBeneficiario1":"","designacionBeneficiario1":0,"nombreBeneficiario2":"","apellidoBeneficiario2":"","parentescoBeneficiario2":"","designacionBeneficiario2":0,"nombreBeneficiario3":"","apellidoBeneficiario3":"","parentescoBeneficiario3":"","designacionBeneficiario3":0,"beneficiariosRegistrados":false,"fechaRegistroBeneficiarios":""},"Emisión de Póliza":{"numeroCertificadoFinal":"","resultadoEmision":"","fechaVigenciaPoliza":"","polizaPrincipal":"","periodicidadPagoPoliza":"MENSUAL","confirmacionVentaSegurosBolivar":false,"liderClavo":"","certificado":"75272","observacionesEmision":"","fechaEmisionPoliza":"","estadoPoliza":"","numeroContrato":""}}
A304: 45888.588 | B304: 11705204 | C304: {"poliza":"13078","nombre":"MIRANDA SUSANA HENAO MIRANDA","id":"1017229637","telefono":"3502121376","correo":"susana.henaomiranda@gmail.com","ciudad":"RIONEGRO","direccion":"DG 83A 51 46 TO 1 AP 704","tipoInmueble":"Vivienda","canon":"2200000","fechaRadicacion":"19/8/2025","fechaAprobacion":"19/8/2025","estado":"APROBADA","tipoDocumento":"CC"} | D304: maria.gaitan@proyectivaseguros.com | E304: Contacto Inicial y Datos | F304: DESISTIDO | G304: Seguro de Vida | H304: [{"fecha":"2025-08-22 09:56:04","usuario":"maria.gaitan@segurosbolivar.com","accionRealizada":"DESISTIDO","leadEtapaActual":"Contacto Inicial y Datos","productosGestion":"Seguro de Vida","observaciones":"No Contesta"},{"fecha":"2025-08-22 09:56:33","usuario":"maria.gaitan@segurosbolivar.com","accionRealizada":"DESISTIDO","leadEtapaActual":"Contacto Inicial y Datos","productosGestion":"Seguro de Vida","observaciones":"No Contesta"}] | I304: 45891.414 | J304: {"Contacto Inicial y Datos":{"nomAgt":"","emailCte":"","autorizaDatosPersonales":false,"fechaNacimiento":"2025-08-22","tipoDocumento":"","observacionesPresentacion":"","genero":"","resultadoGestion":"Cliente no interesado","accion":"Cliente no interesado","usuario":"maria.gaitan@segurosbolivar.com"},"Cotización y Pre-Asegurabilidad":{"periosidad":"","nPagosMensuales":"","admin":"","observacionesCotizacion":"","valorAseguradoVida":0,"primaVidaITP":0,"fechaCotizacionVida":""},"Declaración de Asegurabilidad":{"actividadesLicita":false,"procesoPenal":false,"frecuenciaDeportesAltoRiesgo":"","peso":"","estatura":"","imcCalculado":"","observacionImc":"","estadoAsegurabilidad":"","hipertensionArterial":false,"colesterolTrigliceridosElevados":false,"diabetes":false,"enfermedadCoronariaInfarto":false,"insuficienciaRenal":false,"cancerTumores":false,"derrameTrombosisCerebral":false,"enfermedadesPsicologicasPsiquiatricas":false,"sidaVih":false,"pruebaVihPositiva":false,"secuelasEnfermedadAccidente":"","diagnosticoEnfermedadFracturas":"","tratamientoAlcoholAlucinogenos":false,"cirugiaProgramada":false,"autorizacionInformacionMedica":false,"fechaAsegurabilidad":""},"Autorización de Descuento Débito":{"canalDescuento":"","tipoDeCuenta":"","entidadBancaria":"","numeroCuentaDebito":"","fechaVencimientoTC":"","numeroCuotasTC":"","autorizaDescuentoAutomatico":false,"entiendeMoraPrima":false,"valorPrima":0,"fechaAutorizacionDebito":"","observacionesCierre":""},"Beneficiarios y Autorizaciones":{"nombreBeneficiario1":"","apellidoBeneficiario1":"","parentescoBeneficiario1":"","designacionBeneficiario1":0,"nombreBeneficiario2":"","apellidoBeneficiario2":"","parentescoBeneficiario2":"","designacionBeneficiario2":0,"nombreBeneficiario3":"","apellidoBeneficiario3":"","parentescoBeneficiario3":"","designacionBeneficiario3":0,"beneficiariosRegistrados":false,"fechaRegistroBeneficiarios":""},"Emisión de Póliza":{"numeroCertificadoFinal":"","resultadoEmision":"","fechaVigenciaPoliza":"","polizaPrincipal":"","periodicidadPagoPoliza":"MENSUAL","confirmacionVentaSegurosBolivar":false,"liderClavo":"","certificado":"75272","observacionesEmision":"","fechaEmisionPoliza":"","estadoPoliza":"","numeroContrato":""}}
A305: 45888.588 | B305: 11705385 | C305: {"poliza":"13002","nombre":"DIANA ALEXANDRA GONZALEZ ZAPATA","id":"21424637","telefono":"3054391302","correo":"dgonzalez0911z@gmail.com","ciudad":"SABANETA","direccion":"CL 77 SUR 47 11","tipoInmueble":"Vivienda","canon":"1700000","fechaRadicacion":"19/8/2025","fechaAprobacion":"19/8/2025","estado":"APROBADA","tipoDocumento":"CC"} | D305: luisa.herrera@segurosbolivar.com | E305: Contacto Inicial y Datos | F305: DESISTIDO | G305: Seguro de Vida | H305: [{"fecha":"2025-08-19 16:39:36","usuario":"luisa.herrera@segurosbolivar.com","accionRealizada":"DESISTIDO","leadEtapaActual":"Contacto Inicial y Datos","productosGestion":"Seguro de Vida","observaciones":"No Contesta"}] | I305: 45888.694 | J305: {"Contacto Inicial y Datos":{"nomAgt":"","emailCte":"","autorizaDatosPersonales":false,"fechaNacimiento":"","tipoDocumento":"","observacionesPresentacion":"no contesta ","genero":"","resultadoGestion":"Cliente ilocalizable","accion":"Cliente ilocalizable","usuario":"luisa.herrera@segurosbolivar.com"},"Cotización y Pre-Asegurabilidad":{"periosidad":"","nPagosMensuales":"","admin":"","observacionesCotizacion":"","valorAseguradoVida":0,"primaVidaITP":0,"fechaCotizacionVida":""},"Declaración de Asegurabilidad":{"actividadesLicita":false,"procesoPenal":false,"frecuenciaDeportesAltoRiesgo":"","peso":"","estatura":"","imcCalculado":"","observacionImc":"","estadoAsegurabilidad":"","hipertensionArterial":false,"colesterolTrigliceridosElevados":false,"diabetes":false,"enfermedadCoronariaInfarto":false,"insuficienciaRenal":false,"cancerTumores":false,"derrameTrombosisCerebral":false,"enfermedadesPsicologicasPsiquiatricas":false,"sidaVih":false,"pruebaVihPositiva":false,"secuelasEnfermedadAccidente":"","diagnosticoEnfermedadFracturas":"","tratamientoAlcoholAlucinogenos":false,"cirugiaProgramada":false,"autorizacionInformacionMedica":false,"fechaAsegurabilidad":""},"Autorización de Descuento Débito":{"canalDescuento":"","tipoDeCuenta":"","entidadBancaria":"","numeroCuentaDebito":"","fechaVencimientoTC":"","numeroCuotasTC":"","autorizaDescuentoAutomatico":false,"entiendeMoraPrima":false,"valorPrima":0,"fechaAutorizacionDebito":"","observacionesCierre":""},"Beneficiarios y Autorizaciones":{"nombreBeneficiario1":"","apellidoBeneficiario1":"","parentescoBeneficiario1":"","designacionBeneficiario1":0,"nombreBeneficiario2":"","apellidoBeneficiario2":"","parentescoBeneficiario2":"","designacionBeneficiario2":0,"nombreBeneficiario3":"","apellidoBeneficiario3":"","parentescoBeneficiario3":"","designacionBeneficiario3":0,"beneficiariosRegistrados":false,"fechaRegistroBeneficiarios":""},"Emisión de Póliza":{"numeroCertificadoFinal":"","resultadoEmision":"","fechaVigenciaPoliza":"","polizaPrincipal":"","periodicidadPagoPoliza":"MENSUAL","confirmacionVentaSegurosBolivar":false,"liderClavo":"","certificado":"75272","observacionesEmision":"","fechaEmisionPoliza":"","estadoPoliza":"","numeroContrato":""}}
A306: 45888.588 | B306: 11697228 | C306: {"poliza":"13092","nombre":"JOHANNA PAOLA VARGAS HERNANDEZ","id":"37862032","telefono":"3004403498","correo":"cokomusica@gmail.com","ciudad":"ENVIGADO","direccion":"CL 21SUR#41 117","tipoInmueble":"Vivienda","canon":"1750000","fechaRadicacion":"11/8/2025 4:08:04","fechaAprobacion":"19/8/2025 12:08:59","estado":"APROBADA","tipoDocumento":"CC"} | D306: angela.caipa@segurosbolivar.com | E306: Contacto Inicial y Datos | F306: DESISTIDO | G306: Seguro de Vida | H306: [{"fecha":"2025-08-19 16:59:48","usuario":"angela.caipa@segurosbolivar.com","accionRealizada":"Cliente no contesta","leadEtapaActual":"Contacto Inicial y Datos","productosGestion":"Seguro de Vida","observaciones":"Sin observaciones específicas"},{"fecha":"2025-08-26 10:50:14","usuario":"angela.caipa@segurosbolivar.com","accionRealizada":"DESISTIDO","leadEtapaActual":"Contacto Inicial y Datos","productosGestion":"Seguro de Vida","observaciones":"No Contesta"}] | I306: 45895.452 | J306: {"Contacto Inicial y Datos":{"nomAgt":"","emailCte":"","autorizaDatosPersonales":false,"fechaNacimiento":"2001-01-21","tipoDocumento":"CC","observacionesPresentacion":"","genero":"Femenino","resultadoGestion":"Cliente ilocalizable","accion":"Cliente ilocalizable","usuario":"angela.caipa@segurosbolivar.com"},"Cotización y Pre-Asegurabilidad":{"periosidad":"","nPagosMensuales":"","admin":"","observacionesCotizacion":"","valorAseguradoVida":0,"primaVidaITP":0,"fechaCotizacionVida":""},"Declaración de Asegurabilidad":{"actividadesLicita":false,"procesoPenal":false,"frecuenciaDeportesAltoRiesgo":"","peso":"","estatura":"","imcCalculado":"","observacionImc":"","estadoAsegurabilidad":"","hipertensionArterial":false,"colesterolTrigliceridosElevados":false,"diabetes":false,"enfermedadCoronariaInfarto":false,"insuficienciaRenal":false,"cancerTumores":false,"derrameTrombosisCerebral":false,"enfermedadesPsicologicasPsiquiatricas":false,"sidaVih":false,"pruebaVihPositiva":false,"secuelasEnfermedadAccidente":"","diagnosticoEnfermedadFracturas":"","tratamientoAlcoholAlucinogenos":false,"cirugiaProgramada":false,"autorizacionInformacionMedica":false,"fechaAsegurabilidad":""},"Autorización de Descuento Débito":{"canalDescuento":"","tipoDeCuenta":"","entidadBancaria":"","numeroCuentaDebito":"","fechaVencimientoTC":"","numeroCuotasTC":"","autorizaDescuentoAutomatico":false,"entiendeMoraPrima":false,"valorPrima":0,"fechaAutorizacionDebito":"","observacionesCierre":""},"Beneficiarios y Autorizaciones":{"nombreBeneficiario1":"","apellidoBeneficiario1":"","parentescoBeneficiario1":"","designacionBeneficiario1":0,"nombreBeneficiario2":"","apellidoBeneficiario2":"","parentescoBeneficiario2":"","designacionBeneficiario2":0,"nombreBeneficiario3":"","apellidoBeneficiario3":"","parentescoBeneficiario3":"","designacionBeneficiario3":0,"beneficiariosRegistrados":false,"fechaRegistroBeneficiarios":""},"Emisión de Póliza":{"numeroCertificadoFinal":"","resultadoEmision":"","fechaVigenciaPoliza":"","polizaPrincipal":"","periodicidadPagoPoliza":"MENSUAL","confirmacionVentaSegurosBolivar":false,"liderClavo":"","certificado":"75272","observacionesEmision":"","fechaEmisionPoliza":"","estadoPoliza":"","numeroContrato":""}}
A307: 45888.588 | B307: 11692414 | C307: {"poliza":"13466","nombre":"SERGIO ANDRES VILLA RIOS","id":"71798807","telefono":"3147144717","correo":"sergioriosdk2@gmail.com","ciudad":"MEDELLIN","direccion":"CL 56 41 95","tipoInmueble":"Comercial","canon":"1851835","fechaRadicacion":"6/8/2025 3:08:38","fechaAprobacion":"19/8/2025 12:08:43","estado":"APROBADA","tipoDocumento":"CC"} | D307: Anyuley.daza@aselibertador.com | E307: Contacto Inicial y Datos | F307: DESISTIDO | G307: Seguro de Vida | H307: [{"fecha":"2025-08-19 15:27:44","usuario":"anyuley.daza@aselibertador.com","accionRealizada":"DESISTIDO","leadEtapaActual":"Contacto Inicial y Datos","productosGestion":"Seguro de Vida","observaciones":"No Contesta"}] | I307: 45888.644 | J307: {"Contacto Inicial y Datos":{"nomAgt":"","emailCte":"","autorizaDatosPersonales":false,"fechaNacimiento":"","tipoDocumento":"","observacionesPresentacion":"Buzón de voz ","genero":"","resultadoGestion":"Cliente ilocalizable","accion":"Cliente ilocalizable","usuario":"anyuley.daza@aselibertador.com"},"Cotización y Pre-Asegurabilidad":{"periosidad":"","nPagosMensuales":"","admin":"","observacionesCotizacion":"","valorAseguradoVida":0,"primaVidaITP":0,"fechaCotizacionVida":""},"Declaración de Asegurabilidad":{"actividadesLicita":false,"procesoPenal":false,"frecuenciaDeportesAltoRiesgo":"","peso":"","estatura":"","imcCalculado":"","observacionImc":"","estadoAsegurabilidad":"","hipertensionArterial":false,"colesterolTrigliceridosElevados":false,"diabetes":false,"enfermedadCoronariaInfarto":false,"insuficienciaRenal":false,"cancerTumores":false,"derrameTrombosisCerebral":false,"enfermedadesPsicologicasPsiquiatricas":false,"sidaVih":false,"pruebaVihPositiva":false,"secuelasEnfermedadAccidente":"","diagnosticoEnfermedadFracturas":"","tratamientoAlcoholAlucinogenos":false,"cirugiaProgramada":false,"autorizacionInformacionMedica":false,"fechaAsegurabilidad":""},"Autorización de Descuento Débito":{"canalDescuento":"","tipoDeCuenta":"","entidadBancaria":"","numeroCuentaDebito":"","fechaVencimientoTC":"","numeroCuotasTC":"","autorizaDescuentoAutomatico":false,"entiendeMoraPrima":false,"valorPrima":0,"fechaAutorizacionDebito":"","observacionesCierre":""},"Beneficiarios y Autorizaciones":{"nombreBeneficiario1":"","apellidoBeneficiario1":"","parentescoBeneficiario1":"","designacionBeneficiario1":0,"nombreBeneficiario2":"","apellidoBeneficiario2":"","parentescoBeneficiario2":"","designacionBeneficiario2":0,"nombreBeneficiario3":"","apellidoBeneficiario3":"","parentescoBeneficiario3":"","designacionBeneficiario3":0,"beneficiariosRegistrados":false,"fechaRegistroBeneficiarios":""},"Emisión de Póliza":{"numeroCertificadoFinal":"","resultadoEmision":"","fechaVigenciaPoliza":"","polizaPrincipal":"","periodicidadPagoPoliza":"MENSUAL","confirmacionVentaSegurosBolivar":false,"liderClavo":"","certificado":"75272","observacionesEmision":"","fechaEmisionPoliza":"","estadoPoliza":"","numeroContrato":""}}
A308: 45888.588 | B308: 7848334 | C308: {"poliza":"13336","nombre":"FELIX ANDRES ROSERO SANTACRUZ","id":"98394629","telefono":"3104224540","correo":"FELIXARS@HOTMAIL.COM","ciudad":"ITAGUI","direccion":"CL 27 D SUR 128 80 APTO 609 TORRE 2 CORALES DE LA ABADIA ENVIGADO ANT","tipoInmueble":"Vivienda","canon":"3300000","fechaRadicacion":"19/8/2025 10:08:23","fechaAprobacion":"19/8/2025 12:08:29","estado":"APROBADA","tipoDocumento":"CC"} | D308: ana.prieto@aselibertador.com | E308: Contacto Inicial y Datos | F308: DESISTIDO | G308: Seguro de Vida | H308: [{"fecha":"2025-08-19 15:35:22","usuario":"ana.prieto@aselibertador.com","accionRealizada":"DESISTIDO","leadEtapaActual":"Contacto Inicial y Datos","productosGestion":"Seguro de Vida","observaciones":"No Contesta"}] | I308: 45888.65 | J308: {"Contacto Inicial y Datos":{"nomAgt":"","emailCte":"","autorizaDatosPersonales":false,"fechaNacimiento":"","tipoDocumento":"","observacionesPresentacion":"","genero":"","resultadoGestion":"Cliente ilocalizable","accion":"Cliente ilocalizable","usuario":"ana.prieto@aselibertador.com"},"Cotización y Pre-Asegurabilidad":{"periosidad":"","nPagosMensuales":"","admin":"","observacionesCotizacion":"","valorAseguradoVida":0,"primaVidaITP":0,"fechaCotizacionVida":""},"Declaración de Asegurabilidad":{"actividadesLicita":false,"procesoPenal":false,"frecuenciaDeportesAltoRiesgo":"","peso":"","estatura":"","imcCalculado":"","observacionImc":"","estadoAsegurabilidad":"","hipertensionArterial":false,"colesterolTrigliceridosElevados":false,"diabetes":false,"enfermedadCoronariaInfarto":false,"insuficienciaRenal":false,"cancerTumores":false,"derrameTrombosisCerebral":false,"enfermedadesPsicologicasPsiquiatricas":false,"sidaVih":false,"pruebaVihPositiva":false,"secuelasEnfermedadAccidente":"","diagnosticoEnfermedadFracturas":"","tratamientoAlcoholAlucinogenos":false,"cirugiaProgramada":false,"autorizacionInformacionMedica":false,"fechaAsegurabilidad":""},"Autorización de Descuento Débito":{"canalDescuento":"","tipoDeCuenta":"","entidadBancaria":"","numeroCuentaDebito":"","fechaVencimientoTC":"","numeroCuotasTC":"","autorizaDescuentoAutomatico":false,"entiendeMoraPrima":false,"valorPrima":0,"fechaAutorizacionDebito":"","observacionesCierre":""},"Beneficiarios y Autorizaciones":{"nombreBeneficiario1":"","apellidoBeneficiario1":"","parentescoBeneficiario1":"","designacionBeneficiario1":0,"nombreBeneficiario2":"","apellidoBeneficiario2":"","parentescoBeneficiario2":"","designacionBeneficiario2":0,"nombreBeneficiario3":"","apellidoBeneficiario3":"","parentescoBeneficiario3":"","designacionBeneficiario3":0,"beneficiariosRegistrados":false,"fechaRegistroBeneficiarios":""},"Emisión de Póliza":{"numeroCertificadoFinal":"","resultadoEmision":"","fechaVigenciaPoliza":"","polizaPrincipal":"","periodicidadPagoPoliza":"MENSUAL","confirmacionVentaSegurosBolivar":false,"liderClavo":"","certificado":"75272","observacionesEmision":"","fechaEmisionPoliza":"","estadoPoliza":"","numeroContrato":""}}
A309: 45888.588 | B309: 7848022 | C309: {"poliza":"1704","nombre":"HENRY DUVAN SERRANO CONTRERAS","id":"1070954599","telefono":"3116125811","correo":"heduse@hotmail.com","ciudad":"MOSQUERA","direccion":"CL 1 2 74 CAMELIAS DEL DIAMANTE","tipoInmueble":"Vivienda","canon":"2200000","fechaRadicacion":"19/8/2025 10:08:21","fechaAprobacion":"19/8/2025 12:08:25","estado":"APROBADA","tipoDocumento":"CC"} | D309: maria.gaitan@proyectivaseguros.com | E309: Emisión de Póliza | F309: VENTA | G309: Seguro de Vida | H309: [{"fecha":"2025-08-19 14:41:49","usuario":"maria.gaitan@segurosbolivar.com","accionRealizada":"VENTA","leadEtapaActual":"Emisión de Póliza","productosGestion":"Seguro de Vida","observaciones":"VENTA VIDA SARLAFT ACTUALIZADO"}] | I309: 45888.612 | J309: {"Contacto Inicial y Datos":{"nomAgt":"maria.gaitan@segurosbolivar.com","emailCte":"","autorizaDatosPersonales":true,"fechaNacimiento":"1989-07-01","tipoDocumento":"CC","observacionesPresentacion":"OK","genero":"Masculino","resultadoGestion":"Cliente acepta tratamiento de datos personales","accion":"Cliente acepta tratamiento de datos personales","usuario":"maria.gaitan@segurosbolivar.com"},"Cotización y Pre-Asegurabilidad":{"periosidad":"Mensual","nPagosMensuales":"12","admin":"","observacionesCotizacion":"OK","valorAseguradoVida":26400000,"primaVidaITP":27060.000000000004,"fechaCotizacionVida":"19/8/2025","resultadoGestion":"Cliente acepta Cotización","accion":"Cliente acepta Cotización","usuario":"maria.gaitan@segurosbolivar.com"},"Declaración de Asegurabilidad":{"actividadesLicita":true,"procesoPenal":true,"frecuenciaDeportesAltoRiesgo":"0","peso":"85","estatura":"176","imcCalculado":"27.44","observacionImc":"OK","estadoAsegurabilidad":"ASEGURABLE","hipertensionArterial":false,"colesterolTrigliceridosElevados":false,"diabetes":false,"enfermedadCoronariaInfarto":false,"insuficienciaRenal":false,"cancerTumores":false,"derrameTrombosisCerebral":false,"enfermedadesPsicologicasPsiquiatricas":false,"sidaVih":false,"pruebaVihPositiva":false,"secuelasEnfermedadAccidente":false,"diagnosticoEnfermedadFracturas":false,"tratamientoAlcoholAlucinogenos":false,"cirugiaProgramada":false,"autorizacionInformacionMedica":true,"fechaAsegurabilidad":"19/8/2025","sarlaft":false,"resultadoGestion":"Cliente Asegurable","observacionesNegociacion":"OK","accion":"Cliente Asegurable","usuario":"maria.gaitan@segurosbolivar.com"},"Autorización de Descuento Débito":{"canalDescuento":"Tarjeta Credito","tipoDeCuenta":"","entidadBancaria":"BBVA","numeroCuentaDebito":"4504087552309031","fechaVencimientoTC":"2029-03","numeroCuotasTC":null,"autorizaDescuentoAutomatico":true,"entiendeMoraPrima":true,"valorPrima":27060.000000000004,"fechaAutorizacionDebito":"19/8/2025","observacionesCierre":"OK","franquiciaDescuento":"VISA","resultadoGestion":"Cliente Autoriza Debito Automatico","accion":"Cliente Autoriza Debito Automatico","usuario":"maria.gaitan@segurosbolivar.com"},"Beneficiarios y Autorizaciones":{"nombreBeneficiario1":"ANGIE GERALDIN ","apellidoBeneficiario1":"VILLAREAL","parentescoBeneficiario1":"conyuge","designacionBeneficiario1":100,"nombreBeneficiario2":"","apellidoBeneficiario2":"","parentescoBeneficiario2":"","designacionBeneficiario2":0,"nombreBeneficiario3":"","apellidoBeneficiario3":"","parentescoBeneficiario3":"","designacionBeneficiario3":0,"beneficiariosRegistrados":true,"fechaRegistroBeneficiarios":"19/8/2025","resultadoGestion":"Cliente Valida Beneficiarios","observacionesPostVenta":"OK","accion":"Cliente Valida Beneficiarios","usuario":"maria.gaitan@segurosbolivar.com"},"Emisión de Póliza":{"numeroCertificadoFinal":"","resultadoEmision":"Confirmacion de venta","fechaVigenciaPoliza":"2025-08-30","polizaPrincipal":"","periodicidadPagoPoliza":"MENSUAL","confirmacionVentaSegurosBolivar":false,"liderClavo":"","certificado":"75272","observacionesEmision":"VENTA VIDA SARLAFT ACTUALIZADO","fechaEmisionPoliza":"19/8/2025","estadoPoliza":"","numeroContrato":"","fechaSeguimiento":"2025-08-30","resultadoGestion":"Confirmacion de venta","observacionesPostVenta":"VENTA VIDA SARLAFT ACTUALIZADO","accion":"Confirmacion de venta","usuario":"maria.gaitan@segurosbolivar.com"}}
A310: 45888.588 | B310: 11699470 | C310: {"poliza":"13150","nombre":"FABIAN ANDRES MORENO CARMONA","id":"9097078","telefono":"3133612946","correo":"famorenoc@gmail.com","ciudad":"MEDELLIN","direccion":"CL 53 64 32 AP 402 BL12","tipoInmueble":"Vivienda","canon":"3000000","fechaRadicacion":"13/8/2025 10:08:47","fechaAprobacion":"19/8/2025 12:08:24","estado":"APROBADA","tipoDocumento":"CC"} | D310: luisa.herrera@segurosbolivar.com | E310: Contacto Inicial y Datos | F310: DESISTIDO | G310: Seguro de Vida | H310: [{"fecha":"2025-08-19 16:51:56","usuario":"luisa.herrera@segurosbolivar.com","accionRealizada":"DESISTIDO","leadEtapaActual":"Contacto Inicial y Datos","productosGestion":"Seguro de Vida","observaciones":"No le interesa"}] | I310: 45888.703 | J310: {"Contacto Inicial y Datos":{"nomAgt":"","emailCte":"","autorizaDatosPersonales":false,"fechaNacimiento":"","tipoDocumento":"","observacionesPresentacion":"no interesado por momento ","genero":"","resultadoGestion":"Cliente no interesado","accion":"Cliente no interesado","usuario":"luisa.herrera@segurosbolivar.com"},"Cotización y Pre-Asegurabilidad":{"periosidad":"","nPagosMensuales":"","admin":"","observacionesCotizacion":"","valorAseguradoVida":0,"primaVidaITP":0,"fechaCotizacionVida":""},"Declaración de Asegurabilidad":{"actividadesLicita":false,"procesoPenal":false,"frecuenciaDeportesAltoRiesgo":"","peso":"","estatura":"","imcCalculado":"","observacionImc":"","estadoAsegurabilidad":"","hipertensionArterial":false,"colesterolTrigliceridosElevados":false,"diabetes":false,"enfermedadCoronariaInfarto":false,"insuficienciaRenal":false,"cancerTumores":false,"derrameTrombosisCerebral":false,"enfermedadesPsicologicasPsiquiatricas":false,"sidaVih":false,"pruebaVihPositiva":false,"secuelasEnfermedadAccidente":"","diagnosticoEnfermedadFracturas":"","tratamientoAlcoholAlucinogenos":false,"cirugiaProgramada":false,"autorizacionInformacionMedica":false,"fechaAsegurabilidad":""},"Autorización de Descuento Débito":{"canalDescuento":"","tipoDeCuenta":"","entidadBancaria":"","numeroCuentaDebito":"","fechaVencimientoTC":"","numeroCuotasTC":"","autorizaDescuentoAutomatico":false,"entiendeMoraPrima":false,"valorPrima":0,"fechaAutorizacionDebito":"","observacionesCierre":""},"Beneficiarios y Autorizaciones":{"nombreBeneficiario1":"","apellidoBeneficiario1":"","parentescoBeneficiario1":"","designacionBeneficiario1":0,"nombreBeneficiario2":"","apellidoBeneficiario2":"","parentescoBeneficiario2":"","designacionBeneficiario2":0,"nombreBeneficiario3":"","apellidoBeneficiario3":"","parentescoBeneficiario3":"","designacionBeneficiario3":0,"beneficiariosRegistrados":false,"fechaRegistroBeneficiarios":""},"Emisión de Póliza":{"numeroCertificadoFinal":"","resultadoEmision":"","fechaVigenciaPoliza":"","polizaPrincipal":"","periodicidadPagoPoliza":"MENSUAL","confirmacionVentaSegurosBolivar":false,"liderClavo":"","certificado":"75272","observacionesEmision":"","fechaEmisionPoliza":"","estadoPoliza":"","numeroContrato":""}}
A311: 45888.588 | B311: 11696795 | C311: {"poliza":"2256","nombre":"CRISTIAN FABIAN GARZON PLAZAS","id":"1110497096","telefono":"3177041647","correo":"crisfabgarplazas@gmail.com","ciudad":"BOGOTA, D.C.","direccion":"CR 116 152 20","tipoInmueble":"Vivienda","canon":"1400000","fechaRadicacion":"11/8/2025 12:08:26","fechaAprobacion":"19/8/2025 12:08:17","estado":"APROBADA","tipoDocumento":"CC"} | D311: mildre.rico@segurosbolivar.com | E311: Emisión de Póliza | F311: VENTA | G311: Seguro de Vida | H311: [{"fecha":"2025-08-19 16:14:33","usuario":"mildre.rico@segurosbolivar.com","accionRealizada":"VENTA","leadEtapaActual":"Emisión de Póliza","productosGestion":"Seguro de Vida","observaciones":"VENTA"}] | I311: 45888.677 | J311: {"Contacto Inicial y Datos":{"nomAgt":"mildre.rico@segurosbolivar.com","emailCte":"","autorizaDatosPersonales":true,"fechaNacimiento":"1990-01-28","tipoDocumento":"CC","observacionesPresentacion":".","genero":"Femenino","resultadoGestion":"Cliente acepta tratamiento de datos personales","accion":"Cliente acepta tratamiento de datos personales","usuario":"mildre.rico@segurosbolivar.com"},"Cotización y Pre-Asegurabilidad":{"periosidad":"Mensual","nPagosMensuales":"24","admin":"","observacionesCotizacion":".","valorAseguradoVida":33600000,"primaVidaITP":34440,"fechaCotizacionVida":"19/8/2025","resultadoGestion":"Cliente acepta Cotización","accion":"Cliente acepta Cotización","usuario":"mildre.rico@segurosbolivar.com"},"Declaración de Asegurabilidad":{"actividadesLicita":true,"procesoPenal":true,"frecuenciaDeportesAltoRiesgo":"0","peso":"78","estatura":"170","imcCalculado":"26.99","observacionImc":"ASEGURABLE","estadoAsegurabilidad":"ASEGURABLE","hipertensionArterial":false,"colesterolTrigliceridosElevados":false,"diabetes":false,"enfermedadCoronariaInfarto":false,"insuficienciaRenal":false,"cancerTumores":false,"derrameTrombosisCerebral":false,"enfermedadesPsicologicasPsiquiatricas":false,"sidaVih":false,"pruebaVihPositiva":false,"secuelasEnfermedadAccidente":false,"diagnosticoEnfermedadFracturas":false,"tratamientoAlcoholAlucinogenos":false,"cirugiaProgramada":false,"autorizacionInformacionMedica":true,"fechaAsegurabilidad":"19/8/2025","sarlaft":true,"resultadoGestion":"Cliente Asegurable","observacionesNegociacion":"V","accion":"Cliente Asegurable","usuario":"mildre.rico@segurosbolivar.com"},"Autorización de Descuento Débito":{"canalDescuento":"Cuenta Ahorros","tipoDeCuenta":"","entidadBancaria":"BANCO POPULAR","numeroCuentaDebito":"554130484","fechaVencimientoTC":"","numeroCuotasTC":null,"autorizaDescuentoAutomatico":true,"entiendeMoraPrima":true,"valorPrima":34440,"fechaAutorizacionDebito":"19/8/2025","observacionesCierre":"V","resultadoGestion":"Cliente Autoriza Debito Automatico","accion":"Cliente Autoriza Debito Automatico","usuario":"mildre.rico@segurosbolivar.com","franquiciaDescuento":""},"Beneficiarios y Autorizaciones":{"nombreBeneficiario1":"VIOLETA FERNANDA ","apellidoBeneficiario1":"LUNA","parentescoBeneficiario1":"conyuge","designacionBeneficiario1":100,"nombreBeneficiario2":"","apellidoBeneficiario2":"","parentescoBeneficiario2":"","designacionBeneficiario2":0,"nombreBeneficiario3":"","apellidoBeneficiario3":"","parentescoBeneficiario3":"","designacionBeneficiario3":0,"beneficiariosRegistrados":true,"fechaRegistroBeneficiarios":"19/8/2025","resultadoGestion":"Cliente Valida Beneficiarios","observacionesPostVenta":"VENTA","accion":"Cliente Valida Beneficiarios","usuario":"mildre.rico@segurosbolivar.com"},"Emisión de Póliza":{"numeroCertificadoFinal":"","resultadoEmision":"Confirmacion de venta","fechaVigenciaPoliza":"2025-09-26","polizaPrincipal":"","periodicidadPagoPoliza":"MENSUAL","confirmacionVentaSegurosBolivar":false,"liderClavo":"","certificado":"75272","observacionesEmision":"VENTA","fechaEmisionPoliza":"19/8/2025","estadoPoliza":"","numeroContrato":"","fechaSeguimiento":"2025-09-26","resultadoGestion":"Confirmacion de venta","observacionesPostVenta":"VENTA","accion":"Confirmacion de venta","usuario":"mildre.rico@segurosbolivar.com"}}
... A334: 45894.338 | B334: 11711721 | C334: {"poliza":"902","nombre":"GOMEZ NICOLAS GUTIERREZ GOMEZ","id":"1020835946","telefono":"3243742463","correo":"nicogutigomez@gmail.com","ciudad":"BOGOTA, D.C.","direccion":"CRA 139 # 142F 67","tipoInmueble":"Vivienda","canon":"620000","fechaRadicacion":"24/8/2025","fechaAprobacion":"24/8/2025","estado":"APROBADA","tipoDocumento":"CC","cuota":"","nombreInmobiliaria":"VIAPLAN LTDA VIP SOLUCIONES AUDIOLOGICAS"} | D334: maria.gaitan@proyectivaseguros.com | E334: Contacto Inicial y Datos | F334: DESISTIDO | G334: Seguro de Vida | H334: [{"fecha":"2025-08-25 08:22:30","usuario":"maria.gaitan@segurosbolivar.com","accionRealizada":"DESISTIDO","leadEtapaActual":"Contacto Inicial y Datos","productosGestion":"Seguro de Vida","observaciones":"No le interesa"}] | I334: 45894.349 | J334: {"Contacto Inicial y Datos":{"nomAgt":"maria.gaitan@segurosbolivar.com","emailCte":"","autorizaDatosPersonales":true,"fechaNacimiento":"2000-08-25","tipoDocumento":"CC","observacionesPresentacion":"NO DA RAZÓN, SOLO NO LE INTERESA","genero":"Femenino","resultadoGestion":"Cliente no interesado","accion":"Cliente no interesado","usuario":"maria.gaitan@segurosbolivar.com"},"Cotización y Pre-Asegurabilidad":{"periosidad":"Mensual","nPagosMensuales":24,"admin":"","observacionesCotizacion":"","valorAseguradoVida":14880000,"primaVidaITP":15252.000000000002,"fechaCotizacionVida":"25/8/2025"},"Declaración de Asegurabilidad":{"actividadesLicita":false,"procesoPenal":false,"frecuenciaDeportesAltoRiesgo":"","peso":"","estatura":"","imcCalculado":"","observacionImc":"","estadoAsegurabilidad":"","hipertensionArterial":false,"colesterolTrigliceridosElevados":false,"diabetes":false,"enfermedadCoronariaInfarto":false,"insuficienciaRenal":false,"cancerTumores":false,"derrameTrombosisCerebral":false,"enfermedadesPsicologicasPsiquiatricas":false,"sidaVih":false,"pruebaVihPositiva":false,"secuelasEnfermedadAccidente":"","diagnosticoEnfermedadFracturas":"","tratamientoAlcoholAlucinogenos":false,"cirugiaProgramada":false,"autorizacionInformacionMedica":false,"fechaAsegurabilidad":""},"Autorización de Descuento Débito":{"canalDescuento":"","tipoDeCuenta":"","entidadBancaria":"","numeroCuentaDebito":"","fechaVencimientoTC":"","numeroCuotasTC":"","autorizaDescuentoAutomatico":false,"entiendeMoraPrima":false,"valorPrima":0,"fechaAutorizacionDebito":"","observacionesCierre":""},"Beneficiarios y Autorizaciones":{"nombreBeneficiario1":"","apellidoBeneficiario1":"","parentescoBeneficiario1":"","designacionBeneficiario1":0,"nombreBeneficiario2":"","apellidoBeneficiario2":"","parentescoBeneficiario2":"","designacionBeneficiario2":0,"nombreBeneficiario3":"","apellidoBeneficiario3":"","parentescoBeneficiario3":"","designacionBeneficiario3":0,"beneficiariosRegistrados":false,"fechaRegistroBeneficiarios":""},"Emisión de Póliza":{"numeroCertificadoFinal":"","resultadoEmision":"","fechaVigenciaPoliza":"","polizaPrincipal":"","periodicidadPagoPoliza":"MENSUAL","confirmacionVentaSegurosBolivar":false,"liderClavo":"","certificado":"75272","observacionesEmision":"","fechaEmisionPoliza":"","estadoPoliza":"","numeroContrato":""}}

Sheet Gestion
A1: no | B1: Nombre Comercial | C1: Correo | D1: seguro | E1: Novedad | F1: Capacidad Total | G1: Pendiente de Gestión | H1: En gestión total | I1: Asignados Últimos 30 días | J1: ventas Ultimos 30 días | K1: % Efectividad | L1: gestionadas | M1: CEDULA
A2: 8 | B2: Maria Fernanda Gaitan | C2: maria.gaitan@proyectivaseguros.com | D2: Autos | F2: 55 | G2: =IFERROR(VLOOKUP(C2,Dinamicas!$A:$B,2,0),0) -> 0 | H2: =IFERROR(VLOOKUP(C2,Dinamicas!$D:$E,2,0),0) -> 0 | I2: =IFERROR(VLOOKUP(C2,Dinamicas!$G:$H,2,0),0) -> 0 | J2: =IFERROR(VLOOKUP(C2,Dinamicas!$J:$K,2,0),0) -> 0 | K2: =IFERROR((J2/I2),0) -> 0 | L2: =IFERROR(VLOOKUP(C2,Dinamicas!$N:$O,2,0),0) -> 0
A3: 2 | B3: Ada Ospina | C3: ada.ospina@aselibertador.com | D3: Seguro de Contenidos | E3: Terminación de conrato | F3: 55 | G3: =IFERROR(VLOOKUP(C3,Dinamicas!$A:$B,2,0),0) -> 0 | H3: =IFERROR(VLOOKUP(C3,Dinamicas!$D:$E,2,0),0) -> 0 | I3: =IFERROR(VLOOKUP(C3,Dinamicas!$G:$H,2,0),0) -> 0 | J3: =IFERROR(VLOOKUP(C3,Dinamicas!$J:$K,2,0),0) -> 0 | K3: =IFERROR((I3/J3),0) -> 0 | L3: =IFERROR(VLOOKUP(C3,Dinamicas!$N:$O,2,0),0) -> 0
A4: 15 | B4: Laura Zapata | C4: laura.zapata.hurtado@proyectivaseguros.com | D4: Coordinadora | F4: 0 | G4: =IFERROR(VLOOKUP(C4,Dinamicas!$A:$B,2,0),0) -> 0 | H4: =IFERROR(VLOOKUP(C4,Dinamicas!$D:$E,2,0),0) -> 0 | I4: =IFERROR(VLOOKUP(C4,Dinamicas!$G:$H,2,0),0) -> 0 | J4: =IFERROR(VLOOKUP(C4,Dinamicas!$J:$K,2,0),0) -> 0 | K4: =IFERROR((J4/I4),0) -> 0 | L4: =IFERROR(VLOOKUP(C4,Dinamicas!$N:$O,2,0),0) -> 0
A5: 4 | B5: Lady Lorena Forero Mendez | C5: lady.forero@aselibertador.com | D5: Seguro de Desempleo | E5: Renuncio | F5: 55 | G5: =IFERROR(VLOOKUP(C5,Dinamicas!$A:$B,2,0),0) -> 0 | H5: =IFERROR(VLOOKUP(C5,Dinamicas!$D:$E,2,0),0) -> 0 | I5: =IFERROR(VLOOKUP(C5,Dinamicas!$G:$H,2,0),0) -> 0 | J5: =IFERROR(VLOOKUP(C5,Dinamicas!$J:$K,2,0),0) -> 0 | K5: =IFERROR((I5/J5),0) -> 0 | L5: =IFERROR(VLOOKUP(C5,Dinamicas!$N:$O,2,0),0) -> 0
A6: 7 | B6: Diana Carolina De Las Salas | C6: diana.salas@segurosbolivar.com | D6: Seguro de Vida | E6: Renuncio | F6: 55 | G6: =IFERROR(VLOOKUP(C6,Dinamicas!$A:$B,2,0),0) -> 0 | H6: =IFERROR(VLOOKUP(C6,Dinamicas!$D:$E,2,0),0) -> 0 | I6: =IFERROR(VLOOKUP(C6,Dinamicas!$G:$H,2,0),0) -> 0 | J6: =IFERROR(VLOOKUP(C6,Dinamicas!$J:$K,2,0),0) -> 0 | K6: =IFERROR((J6/I6),0) -> 0 | L6: =IFERROR(VLOOKUP(C6,Dinamicas!$N:$O,2,0),0) -> 0
A7: 6 | B7: Amanda Villamil | C7: arcelia.villamil@proyectivaseguros.com | D7: CorreccionesBI | F7: 1 | G7: 0 | H7: =IFERROR(VLOOKUP(C7,Dinamicas!$D:$E,2,0),0) -> 0 | I7: =IFERROR(VLOOKUP(C7,Dinamicas!$G:$H,2,0),0) -> 0 | J7: =IFERROR(VLOOKUP(C7,Dinamicas!$J:$K,2,0),0) -> 0 | K7: =IFERROR((J7/I7),0) -> 0 | L7: =IFERROR(VLOOKUP(C7,Dinamicas!$N:$O,2,0),0) -> 0
B8: Yazmin Estefania Mora Torres | C8: yazmin.mora@proyectivaseguros.com | D8: Renovations | F8: 55 | G8: =IFERROR(VLOOKUP(C8,Dinamicas!$A:$B,2,0),0) -> 0 | H8: =IFERROR(VLOOKUP(C8,Dinamicas!$D:$E,2,0),0) -> 0 | I8: =IFERROR(VLOOKUP(C8,Dinamicas!$G:$H,2,0),0) -> 0 | J8: =IFERROR(VLOOKUP(C8,Dinamicas!$J:$K,2,0),0) -> 0 | K8: =IFERROR((J8/I8),0) -> 0 | L8: =IFERROR(VLOOKUP(C8,Dinamicas!$N:$O,2,0),0) -> 0
A9: 10 | B9: Luisa Fernanda Herrera Bermúdez | C9: luisa.herrera@segurosbolivar.com | D9: Seguro de Vida | E9: Renuncio | F9: 55 | G9: =IFERROR(VLOOKUP(C9,Dinamicas!$A:$B,2,0),0) -> 0 | H9: =IFERROR(VLOOKUP(C9,Dinamicas!$D:$E,2,0),0) -> 0 | I9: =IFERROR(VLOOKUP(C9,Dinamicas!$G:$H,2,0),0) -> 0 | J9: =IFERROR(VLOOKUP(C9,Dinamicas!$J:$K,2,0),0) -> 0 | K9: =IFERROR((J9/I9),0) -> 0 | L9: =IFERROR(VLOOKUP(C9,Dinamicas!$N:$O,2,0),0) -> 0
A10: 11 | B10: Angela Vivíana Caipa Cadena | C10: angela.caipa@segurosbolivar.com | D10: Seguro de Vida | E10: Terminación de conrato | F10: 55 | G10: =IFERROR(VLOOKUP(C10,Dinamicas!$A:$B,2,0),0) -> 0 | H10: =IFERROR(VLOOKUP(C10,Dinamicas!$D:$E,2,0),0) -> 0 | I10: =IFERROR(VLOOKUP(C10,Dinamicas!$G:$H,2,0),0) -> 0 | J10: =IFERROR(VLOOKUP(C10,Dinamicas!$J:$K,2,0),0) -> 0 | K10: =IFERROR((J10/I10),0) -> 0 | L10: =IFERROR(VLOOKUP(C10,Dinamicas!$N:$O,2,0),0) -> 0
A11: 12 | B11: Mildre Johana Rico Castillo | C11: mildre.rico@segurosbolivar.com | D11: Seguro de Vida | E11: Terminación de conrato | F11: 55 | G11: =IFERROR(VLOOKUP(C11,Dinamicas!$A:$B,2,0),0) -> 0 | H11: =IFERROR(VLOOKUP(C11,Dinamicas!$D:$E,2,0),0) -> 0 | I11: =IFERROR(VLOOKUP(C11,Dinamicas!$G:$H,2,0),0) -> 0 | J11: =IFERROR(VLOOKUP(C11,Dinamicas!$J:$K,2,0),0) -> 0 | K11: =IFERROR((J11/I11),0) -> 0 | L11: =IFERROR(VLOOKUP(C11,Dinamicas!$N:$O,2,0),0) -> 0
A12: 13 | B12: Anyuley Daza | C12: Anyuley.daza@aselibertador.com | D12: pqr | F12: 55 | G12: =IFERROR(VLOOKUP(C12,Dinamicas!$A:$B,2,0),0) -> 0 | H12: =IFERROR(VLOOKUP(C12,Dinamicas!$D:$E,2,0),0) -> 0 | I12: =IFERROR(VLOOKUP(C12,Dinamicas!$G:$H,2,0),0) -> 0 | J12: =IFERROR(VLOOKUP(C12,Dinamicas!$J:$K,2,0),0) -> 0 | K12: =IFERROR((J12/I12),0) -> 0 | L12: =IFERROR(VLOOKUP(C12,Dinamicas!$N:$O,2,0),0) -> 0
A13: 14 | B13: Ana María Prieto Mayorga | C13: ana.prieto@aselibertador.com | D13: pqr | F13: 55 | G13: =IFERROR(VLOOKUP(C13,Dinamicas!$A:$B,2,0),0) -> 0 | H13: =IFERROR(VLOOKUP(C13,Dinamicas!$D:$E,2,0),0) -> 0 | I13: =IFERROR(VLOOKUP(C13,Dinamicas!$G:$H,2,0),0) -> 0 | J13: =IFERROR(VLOOKUP(C13,Dinamicas!$J:$K,2,0),0) -> 0 | K13: =IFERROR((J13/I13),0) -> 0 | L13: =IFERROR(VLOOKUP(C13,Dinamicas!$N:$O,2,0),0) -> 0
A14: 1 | B14: Sofia Narváez Garzón | C14: sofia.narvaez@proyectivaseguros.com | D14: Seguro de Contenidos | F14: 55 | G14: =IFERROR(VLOOKUP(C14,Dinamicas!$A:$B,2,0),0) -> 0 | H14: =IFERROR(VLOOKUP(C14,Dinamicas!$D:$E,2,0),0) -> 0 | I14: =IFERROR(VLOOKUP(C14,Dinamicas!$G:$H,2,0),0) -> 0 | J14: =IFERROR(VLOOKUP(C14,Dinamicas!$J:$K,2,0),0) -> 0 | K14: =IFERROR((I14/J14),0) -> 0 | L14: =IFERROR(VLOOKUP(C14,Dinamicas!$N:$O,2,0),0) -> 0
A15: 18 | B15: Camilo Moncada | C15: camilo.moncada@segurosbolivar.com | D15: Seguro de Vida | E15: Renuncio | F15: 55 | G15: =IFERROR(VLOOKUP(C15,Dinamicas!$A:$B,2,0),0) -> 0 | H15: =IFERROR(VLOOKUP(C15,Dinamicas!$D:$E,2,0),0) -> 0 | I15: =IFERROR(VLOOKUP(C15,Dinamicas!$G:$H,2,0),0) -> 0 | J15: =IFERROR(VLOOKUP(C15,Dinamicas!$J:$K,2,0),0) -> 0 | K15: =IFERROR((J15/I15),0) -> 0 | L15: =IFERROR(VLOOKUP(C15,Dinamicas!$N:$O,2,0),0) -> 0
A16: 19 | B16: Henry Hernandez | C16: henry.hernandez@segurosbolivar.com | D16: Renovations | E16: Capacitación | F16: 55 | G16: =IFERROR(VLOOKUP(C16,Dinamicas!$A:$B,2,0),0) -> 0 | H16: =IFERROR(VLOOKUP(C16,Dinamicas!$D:$E,2,0),0) -> 0 | I16: =IFERROR(VLOOKUP(C16,Dinamicas!$G:$H,2,0),0) -> 0 | J16: =IFERROR(VLOOKUP(C16,Dinamicas!$J:$K,2,0),0) -> 0 | K16: =IFERROR((J16/I16),0) -> 0 | L16: =IFERROR(VLOOKUP(C16,Dinamicas!$N:$O,2,0),0) -> 0
A17: 3 | B17: Angie Yoley Ariza Roncancio | C17: angie.ariza.roncancio@proyectivaseguros.com | D17: Seguro de Desempleo | F17: 55 | G17: =IFERROR(VLOOKUP(C17,Dinamicas!$A:$B,2,0),0) -> 0 | H17: =IFERROR(VLOOKUP(C17,Dinamicas!$D:$E,2,0),0) -> 0 | I17: =IFERROR(VLOOKUP(C17,Dinamicas!$G:$H,2,0),0) -> 0 | J17: =IFERROR(VLOOKUP(C17,Dinamicas!$J:$K,2,0),0) -> 0 | K17: =IFERROR((J17/I17),0) -> 0 | L17: =IFERROR(VLOOKUP(C17,Dinamicas!$N:$O,2,0),0) -> 0 | M17: 1024550984
A18: 21 | B18: Magda Mendez | C18: magda.mendez@segurosbolivar.com | D18: Seguro de Vida | E18: Terminación de conrato | F18: 55 | G18: =IFERROR(VLOOKUP(C18,Dinamicas!$A:$B,2,0),0) -> 0 | H18: =IFERROR(VLOOKUP(C18,Dinamicas!$D:$E,2,0),0) -> 0 | I18: =IFERROR(VLOOKUP(C18,Dinamicas!$G:$H,2,0),0) -> 0 | J18: =IFERROR(VLOOKUP(C18,Dinamicas!$J:$K,2,0),0) -> 0 | K18: =IFERROR((J18/I18),0) -> 0 | L18: =IFERROR(VLOOKUP(C18,Dinamicas!$N:$O,2,0),0) -> 0
A19: 24 | B19: Hector Diaz | C19: hector.diaz@segurosbolivar.com | D19: Seguro de Desempleo | F19: 55 | G19: =IFERROR(VLOOKUP(C19,Dinamicas!$A:$B,2,0),0) -> 0 | H19: =IFERROR(VLOOKUP(C19,Dinamicas!$D:$E,2,0),0) -> 0 | I19: =IFERROR(VLOOKUP(C19,Dinamicas!$G:$H,2,0),0) -> 0 | J19: =IFERROR(VLOOKUP(C19,Dinamicas!$J:$K,2,0),0) -> 0 | K19: =IFERROR((J19/I19),0) -> 0 | L19: =IFERROR(VLOOKUP(C19,Dinamicas!$N:$O,2,0),0) -> 0 | M19: 1012425598
A20: 16 | B20: Andres Aristizabal | C20: andres.aristizabal@proyectivaseguros.com | D20: Seguro de Desempleo | F20: 55 | G20: =IFERROR(VLOOKUP(C20,Dinamicas!$A:$B,2,0),0) -> 0 | H20: =IFERROR(VLOOKUP(C20,Dinamicas!$D:$E,2,0),0) -> 0 | I20: =IFERROR(VLOOKUP(C20,Dinamicas!$G:$H,2,0),0) -> 0 | J20: =IFERROR(VLOOKUP(C20,Dinamicas!$J:$K,2,0),0) -> 0 | K20: =IFERROR((J20/I20),0) -> 0 | L20: =IFERROR(VLOOKUP(C20,Dinamicas!$N:$O,2,0),0) -> 0 | M20: 1002633742
A21: 23 | B21: Carlos Zamora | C21: carlos.zamora@proyectivaseguros.com | D21: Seguro de Vida | F21: 55 | G21: =IFERROR(VLOOKUP(C21,Dinamicas!$A:$B,2,0),0) -> 0 | H21: =IFERROR(VLOOKUP(C21,Dinamicas!$D:$E,2,0),0) -> 0 | I21: =IFERROR(VLOOKUP(C21,Dinamicas!$G:$H,2,0),0) -> 0 | J21: =IFERROR(VLOOKUP(C21,Dinamicas!$J:$K,2,0),0) -> 0 | K21: =IFERROR((J21/I21),0) -> 0 | L21: =IFERROR(VLOOKUP(C21,Dinamicas!$N:$O,2,0),0) -> 0 | M21: 1033801814
A22: 5 | B22: Desarrollador Cristian Mosquera | C22: cristian.mosquera@segurosbolivar.com | D22: superAdmin | F22: 1 | G22: =IFERROR(VLOOKUP(C22,Dinamicas!$A:$B,2,0),0) -> 0 | H22: =IFERROR(VLOOKUP(C22,Dinamicas!$D:$E,2,0),0) -> 0 | I22: =IFERROR(VLOOKUP(C22,Dinamicas!$G:$H,2,0),0) -> 0 | J22: =IFERROR(VLOOKUP(C22,Dinamicas!$J:$K,2,0),0) -> 0 | K22: =IFERROR((I22/J22),0) -> 0 | L22: =IFERROR(VLOOKUP(C22,Dinamicas!$N:$O,2,0),0) -> 0
A23: 9 | B23: Olga Lucia Obando Campos | C23: olga.obando@proyectivaseguros.com | D23: Seguro de Vida | E23: Renuncio | F23: 55 | G23: =IFERROR(VLOOKUP(C23,Dinamicas!$A:$B,2,0),0) -> 0 | H23: 8 | I23: =IFERROR(VLOOKUP(C23,Dinamicas!$G:$H,2,0),0) -> 0 | J23: =IFERROR(VLOOKUP(C23,Dinamicas!$J:$K,2,0),0) -> 0 | K23: =IFERROR((J23/I23),0) -> 0 | L23: =IFERROR(VLOOKUP(C23,Dinamicas!$N:$O,2,0),0) -> 0
A24: 25 | B24: Manuela Lopez | C24: manuela.lopez@proyectivaseguros.com | D24: Seguro de Vida | F24: 55 | G24: =IFERROR(VLOOKUP(C24,Dinamicas!$A:$B,2,0),0) -> 0 | H24: =IFERROR(VLOOKUP(C24,Dinamicas!$D:$E,2,0),0) -> 0 | I24: =IFERROR(VLOOKUP(C24,Dinamicas!$G:$H,2,0),0) -> 0 | J24: =IFERROR(VLOOKUP(C24,Dinamicas!$J:$K,2,0),0) -> 0 | K24: =IFERROR((J24/I24),0) -> 0 | L24: =IFERROR(VLOOKUP(C24,Dinamicas!$N:$O,2,0),0) -> 0 | M24: 1021665924
A25: 24 | B25: Diana rojas | C25: diana.marcela.rojas@proyectivaseguros.com | D25: Seguro de Vida | F25: 55 | G25: =IFERROR(VLOOKUP(C25,Dinamicas!$A:$B,2,0),0) -> 0 | H25: =IFERROR(VLOOKUP(C25,Dinamicas!$D:$E,2,0),0) -> 0 | I25: =IFERROR(VLOOKUP(C25,Dinamicas!$G:$H,2,0),0) -> 0 | J25: =IFERROR(VLOOKUP(C25,Dinamicas!$J:$K,2,0),0) -> 0 | K25: =IFERROR((J25/I25),0) -> 0 | L25: =IFERROR(VLOOKUP(C25,Dinamicas!$N:$O,2,0),0) -> 0 | M25: 52778015
A26: 20 | B26: Asesor de pruebas uno | C26: desarrollocrmlibertador@ellibertador.co | D26: Renovations | F26: 0 | G26: =IFERROR(VLOOKUP(C26,Dinamicas!$A:$B,2,0),0) -> 0 | H26: =IFERROR(VLOOKUP(C26,Dinamicas!$D:$E,2,0),0) -> 0 | I26: =IFERROR(VLOOKUP(C26,Dinamicas!$G:$H,2,0),0) -> 0 | J26: =IFERROR(VLOOKUP(C26,Dinamicas!$J:$K,2,0),0) -> 0 | K26: =IFERROR((J26/I26),0) -> 0 | L26: =IFERROR(VLOOKUP(C26,Dinamicas!$N:$O,2,0),0) -> 0
A27: 22 | B27: Marisol Cruz | C27: marisol.cruz@segurosbolivar.com | D27: Seguro de Vida | F27: 55 | G27: =IFERROR(VLOOKUP(C27,Dinamicas!$A:$B,2,0),0) -> 0 | H27: =IFERROR(VLOOKUP(C27,Dinamicas!$D:$E,2,0),0) -> 0 | I27: =IFERROR(VLOOKUP(C27,Dinamicas!$G:$H,2,0),0) -> 0 | J27: =IFERROR(VLOOKUP(C27,Dinamicas!$J:$K,2,0),0) -> 0 | K27: =IFERROR((J27/I27),0) -> 0 | L27: =IFERROR(VLOOKUP(C27,Dinamicas!$N:$O,2,0),0) -> 0 | M27: 1019038914
A28: 17 | B28: Luis Alberto Vasquez | C28: Luis.alberto.vasquez@proyectivaseguros.com | D28: Admin | F28: 0 | G28: =IFERROR(VLOOKUP(C28,Dinamicas!$A:$B,2,0),0) -> 0 | H28: =IFERROR(VLOOKUP(C28,Dinamicas!$D:$E,2,0),0) -> 0 | I28: =IFERROR(VLOOKUP(C28,Dinamicas!$G:$H,2,0),0) -> 0 | J28: =IFERROR(VLOOKUP(C28,Dinamicas!$J:$K,2,0),0) -> 0 | K28: =IFERROR((J28/I28),0) -> 0 | L28: =IFERROR(VLOOKUP(C28,Dinamicas!$N:$O,2,0),0) -> 0
A29: 26 | B29: Adriana Olier | C29: adriana.olier@proyectivaseguros.com | D29: Seguro de Vida | F29: 55 | G29: =IFERROR(VLOOKUP(C29,Dinamicas!$A:$B,2,0),0) -> 0 | H29: =IFERROR(VLOOKUP(C29,Dinamicas!$D:$E,2,0),0) -> 0 | I29: =IFERROR(VLOOKUP(C29,Dinamicas!$G:$H,2,0),0) -> 0 | J29: =IFERROR(VLOOKUP(C29,Dinamicas!$J:$K,2,0),0) -> 0 | K29: =IFERROR((J29/I29),0) -> 0 | L29: =IFERROR(VLOOKUP(C29,Dinamicas!$N:$O,2,0),0) -> 0 | M29: 1127959367
B30: Nicolas Riveros Ortiz | C30: nicolas.riveros.ortiz@proyectivaseguros.com | D30: Seguro de Vida | F30: 55 | G30: =IFERROR(VLOOKUP(C30,Dinamicas!$A:$B,2,0),0) -> 0 | H30: =IFERROR(VLOOKUP(C30,Dinamicas!$D:$E,2,0),0) -> 0 | I30: =IFERROR(VLOOKUP(C30,Dinamicas!$G:$H,2,0),0) -> 0 | J30: =IFERROR(VLOOKUP(C30,Dinamicas!$J:$K,2,0),0) -> 0 | K30: =IFERROR((J30/I30),0) -> 0 | L30: =IFERROR(VLOOKUP(C30,Dinamicas!$N:$O,2,0),0) -> 0 | M30: 1010242097
B31: Victor Alexander Vanegas Carreño | C31: victor.alexander.vanegas@proyectivaseguros.com | D31: Seguro de Vida | F31: 55 | G31: =IFERROR(VLOOKUP(C31,Dinamicas!$A:$B,2,0),0) -> 0 | H31: =IFERROR(VLOOKUP(C31,Dinamicas!$D:$E,2,0),0) -> 0 | I31: =IFERROR(VLOOKUP(C31,Dinamicas!$G:$H,2,0),0) -> 0 | J31: =IFERROR(VLOOKUP(C31,Dinamicas!$J:$K,2,0),0) -> 0 | K31: =IFERROR((J31/I31),0) -> 0 | L31: =IFERROR(VLOOKUP(C31,Dinamicas!$N:$O,2,0),0) -> 0 | M31: 1000626437
B32: Ana Sofia Nieto | C32: ana.nieto@proyectivaseguros.com | D32: Seguro de Vida | F32: 55 | G32: =IFERROR(VLOOKUP(C32,Dinamicas!$A:$B,2,0),0) -> 0 | H32: =IFERROR(VLOOKUP(C32,Dinamicas!$D:$E,2,0),0) -> 0 | I32: =IFERROR(VLOOKUP(C32,Dinamicas!$G:$H,2,0),0) -> 0 | J32: =IFERROR(VLOOKUP(C32,Dinamicas!$J:$K,2,0),0) -> 0 | K32: =IFERROR((J32/I32),0) -> 0 | L32: =IFERROR(VLOOKUP(C32,Dinamicas!$N:$O,2,0),0) -> 0 | M32: 1019604736
B33: Leidy Johana Pacheco Alarcon | C33: leidy.pacheco@proyectivaseguros.com | D33: Seguro de Vida | F33: 55 | G33: =IFERROR(VLOOKUP(C33,Dinamicas!$A:$B,2,0),0) -> 0 | H33: =IFERROR(VLOOKUP(C33,Dinamicas!$D:$E,2,0),0) -> 0 | I33: =IFERROR(VLOOKUP(C33,Dinamicas!$G:$H,2,0),0) -> 0 | J33: =IFERROR(VLOOKUP(C33,Dinamicas!$J:$K,2,0),0) -> 0 | K33: =IFERROR((J33/I33),0) -> 0 | L33: =IFERROR(VLOOKUP(C33,Dinamicas!$N:$O,2,0),0) -> 0 | M33: 1023036172
B34: Maria Daniela Garcia | C34: maria.garcia@proyectivaseguros.com | D34: Seguro de Vida | F34: 55 | G34: =IFERROR(VLOOKUP(C34,Dinamicas!$A:$B,2,0),0) -> 0 | H34: =IFERROR(VLOOKUP(C34,Dinamicas!$D:$E,2,0),0) -> 0 | I34: =IFERROR(VLOOKUP(C34,Dinamicas!$G:$H,2,0),0) -> 0 | J34: =IFERROR(VLOOKUP(C34,Dinamicas!$J:$K,2,0),0) -> 0 | K34: =IFERROR((J34/I34),0) -> 0 | L34: =IFERROR(VLOOKUP(C34,Dinamicas!$N:$O,2,0),0) -> 0 | M34: 1000931072
B35: Julieth Andrea Ossma Acero | C35: julieth.andrea.ossma@proyectivaseguros.com | D35: Seguro de Vida | F35: 55 | G35: =IFERROR(VLOOKUP(C35,Dinamicas!$A:$B,2,0),0) -> 0 | H35: =IFERROR(VLOOKUP(C35,Dinamicas!$D:$E,2,0),0) -> 0 | I35: =IFERROR(VLOOKUP(C35,Dinamicas!$G:$H,2,0),0) -> 0 | J35: =IFERROR(VLOOKUP(C35,Dinamicas!$J:$K,2,0),0) -> 0 | K35: =IFERROR((J35/I35),0) -> 0 | L35: =IFERROR(VLOOKUP(C35,Dinamicas!$N:$O,2,0),0) -> 0 | M35: 1024596414

Sheet JSON
A1: Fecha_Actual | B1: json | C1: asignado | D1: SEGMENTO | E1: Estado Gestion | F1: Autogestion | G1: Observaciones | H1: json_Jorney
A2: 46030.817 | B2: { "id": 2204, "mesVencimientoPoliza": "January/2026", "poliza": 5010001207404, "asegurado": "LIGIA SANTOFIMIO TORRES", "tipoDocumento": "CC", "documento": 41407068, "vigencia": "01/01/2025", "vencimiento": "01/01/2026", "canon": 1480212.0, "admon": 346500.0, "valorAsegSep": 1000000.0, "valorAsegDyf": 0.0, "direccionRiesgo": "CL 151 C 104 50 TO 1 AP 1302", "solicitud": 7344846, "telefono1": 2144243.0, "celular": 3143945906.0, "email": "LISATO1945@GMAIL.COM", "destinoInmueble": "Vivienda", "segmento": "PROPIETARIO", "nuevoCanon": 1555702.812, "nuevoValorAsegurado": 1902202.812, "vigenciaNPoliza": NaN, "vencimientoNPoliza": NaN, "motivoNoRenovacion": NaN, "polizaRenovacion": NaN, "sarlaft": NaN, "fechaUltimoSarlaft": NaN, "renovarSarlaft": NaN, "costo": NaN, "valorPagado": NaN, "fechaDePago": NaN, "observacionPagos": NaN, "emailBrIn": "LISATO1945@GMAIL.COM", "nombreBrIn": "LIGIA SANTOFIMIO TORRES", "idBrIn": 41407068.0, "numBrIn": "3143945906" } | C2: cristian.mosquera@segurosbolivar.com | D2: PROPIETARIO | F2: {"fechaInicioNuevaVigencia":"2026-01-01","documento":"41407068","datosCesion":null,"tipoPoliza":"nueva","asegurado":"LIGIA SANTOFIMIO TORRES","telefono1":"2144243","admon":391432,"pazSalvo":"2026-01-01","fechaFinNuevaVigencia":"2027-01-01","valorAsegDyf":0,"canon":1565595,"procesoEspecial":"NINGUNO","sarlaftFecha":"","cotizacionTotal":0,"sarlaftEstado":"VIGENTE","tipoDocumento":"CC","solicitud":"7344846","poliza":"5010001207404","email":"LISATO1945@GMAIL.COM","ajusteIPC":5.1,"direccionRiesgo":"CL 151 C 104 50 TO 1 AP 1302","valorAsegSep":1000000,"detalleFinanciero":{"primaNetaServ":0,"primaNetaCanon":821951,"ivaServ":0,"primaNetaDyF":0,"ivaDyF":0,"ivaCanon":156171},"celular":"3143945906","sarlaftURL":"https://drive.google.com/file/d/1qVOGT674oYHhaQKI9O1naN7YH3PCzfjS/view?usp=drivesdk","comprobanteURL":"https://drive.google.com/file/d/1HMOFwkXubbI49kij4PJqSttneG3I06Qx/view?usp=drivesdk","polizaAjusteURL":"https://drive.google.com/file/d/1NQYqy0ircaTrYslV6OyoaT9kZsfroiYS/view?usp=drivesdk","polizaURL":"https://drive.google.com/file/d/1_Z17Qb8gvCDDTKL9thk2AAMUsXpkXTlv/view?usp=drivesdk","granTotal":0,"fechaEdicion":"2026-01-28T19:19:48.019Z","mesesVigencia":12,"tipoServicio":"VIVIENDA","editadoPorAnalista":true} | G2: [{"fecha":"21/01/2026 12:07:11","usuario":"yazmin.mora@proyectivaseguros.com","observacion":"21/01 Prop renueva nuevo canon $1.595.418 nva admins, $425.580\nNOTA: Dani el prop pago el año pasado la R.A, sin embargo le subio al canon a $1.518.000 pero no pago el excedente, este año desea subir el ipc total a ese valor. \nCliente con tasa especial\nSe le envia sarlaft y copia de la cedula a Ana p, ya que en crm no permite cargarlo","estado":"Enviar a Expedicion","seguimiento":"N/A","procesoEspecial":"NINGUNO"},{"fecha":"2026-01-22T14:44:27.429Z","usuario":"steven.vargas@segurosbolivar.com","observacion":"Buenos dias compañeras devuelvo este proceso ya que el sistema no genero renovación automática por lo tanto debe tramitarse como una poliza nueva, sebe enviar a Jeymmy y a Paola garcia para que salga como nueva de envio correo para que tengan todos los datos que me colocaron 22/01/2026","estado":"CORRECCION","accion":"GESTION_ANALISTA"},{"fecha":"28/01/2026 13:57:37","usuario":"yazmin.mora@proyectivaseguros.com","observacion":"28/01 \nDani esta poliza se habia renovado bajo la poliza 5010003031501, sin embargo la propietaria cambia los val,ores siendo ;\ncanon: $1.565.595\nAdmin.$391.432\n\nPor favor ten en cuenta que el año pasado pago la R.A pero si había aumentado el canon al arrendatario.\n\nGracias Dani","estado":"Enviar a Expedicion","seguimiento":"N/A","procesoEspecial":"NINGUNO"},{"fecha":"2026-01-28T19:20:25.153Z","usuario":"steven.vargas@segurosbolivar.com","observacion":"Renovación Aprobada","estado":"Expedido","accion":"GESTION_ANALISTA"}]
